Workbook
Name Category: 'Material Input (2)'!$B$2
Name Category: 'Material Input'!$B$2
Name Client_Name: 'Material Input (2)'!$B$1
Name Client_Name: 'Material Input'!$B$1
Name End_Clamp: 'Material Input (2)'!$B$15
Name End_Clamp: 'Material Input'!$B$15
Name Grounding_Clip: 'Material Input (2)'!$B$16
Name Grounding_Clip: 'Material Input'!$B$16
Name Grounding_Lug: 'Material Input (2)'!$B$17
Name Grounding_Lug: 'Material Input'!$B$17
Name Klip_Lok_Clamp: 'Material Input (2)'!$B$8
Name Klip_Lok_Clamp: 'Material Input'!$B$8
Name L_Foot: 'Material Input (2)'!$B$7
Name L_Foot: 'Material Input'!$B$7
Name Mid_Clamp: 'Material Input (2)'!$B$14
Name Mid_Clamp: 'Material Input'!$B$14
Name Precast_Concrete_Block: 'Material Input (2)'!$B$18
Name Precast_Concrete_Block: 'Material Input'!$B$18
Name Rail: 'Material Input (2)'!$B$9
Name Rail: 'Material Input'!$B$9
Name Rail_2.6: 'Material Input (2)'!$B$9
Name Rail_2.6: 'Material Input'!$B$9
Name Rail_26: 'Material Input (2)'!$B$9
Name Rail_26: 'Material Input'!$B$9
Name Rail_36: 'Material Input (2)'!$B$12
Name Rail_36: 'Material Input'!$B$12
Name Rail_47: 'Material Input (2)'!$B$11
Name Rail_47: 'Material Input'!$B$11
Name Rail_53: 'Material Input (2)'!$B$10
Name Rail_53: 'Material Input'!$B$10
Name Roof_Type: 'Material Input (2)'!$B$3
Name Roof_Type: 'Material Input'!$B$3
Name Splicer: 'Material Input (2)'!$B$13
Name Splicer: 'Material Input'!$B$13
Name Tile_Hook: 'Material Input (2)'!$B$6
Name Tile_Hook: 'Material Input'!$B$6

Sheet Dashboard
W3: Residential | Z3: =B37 -> 3635.145
W8: C&I | Z8: =B38 -> 3718.01
B35: System Capacity | H35: Project Value (RM) | N35: Revenue (RM) | T35: Collection (RM) | Z35: No of Sites
B36: Total | C36: 2023 | D36: 2024 | E36: 2025 | F36: 2026 | H36: Total | I36: 2023 | J36: 2024 | K36: 2025 | L36: 2026 | N36: Total | O36: 2023 | P36: 2024 | Q36: 2025 | R36: 2026 | T36: Total | U36: 2023 | V36: 2024 | W36: 2025 | X36: 2026 | Z36: Total | AA36: 2023 | AB36: 2024 | AC36: 2025 | AD36: 2026
A37: Residential (PV System) | B37: =SUMIFS(Table1[PV System Capacity (kWp)],Table1[Category],"*R*") -> 3635.145 | C37: =SUMIFS(Table1[PV System Capacity (kWp)],Table1[Category],"*R*",Table1[Closed Date],">="&DATE(2023,1,1),Table1[Closed Date],"<="&DATE(2023,12,31)) -> 313.3 | D37: =SUMIFS(Table1[PV System Capacity (kWp)],Table1[Category],"*R*",Table1[Closed Date],">="&DATE(2024,1,1),Table1[Closed Date],"<="&DATE(2024,12,31)) -> 1637.165 | E37: =SUMIFS(Table1[PV System Capacity (kWp)],Table1[Category],"*R*",Table1[Closed Date],">="&DATE(2025,1,1),Table1[Closed Date],"<="&DATE(2025,12,31)) -> 1684.68 | F37: =SUMIFS(Table1[PV System Capacity (kWp)],Table1[Category],"*R*",Table1[Closed Date],">="&DATE(2026,1,1),Table1[Closed Date],"<="&DATE(2026,12,31)) -> 0 | H37: =SUMIFS(Table1[Project Value (RM)],Table1[Category],"R-PV") -> 10314868 | I37: =SUMIFS(Table1[Project Value (RM)],Table1[Category],"R-PV",Table1[Closed Date],">="&DATE(2023,1,1),Table1[Closed Date],"<="&DATE(2023,12,31)) -> 782725 | J37: =SUMIFS(Table1[Project Value (RM)],Table1[Category],"R-PV",Table1[Closed Date],">="&DATE(2024,1,1),Table1[Closed Date],"<="&DATE(2024,12,31)) -> 5036797.2 | K37: =SUMIFS(Table1[Project Value (RM)],Table1[Category],"R-PV",Table1[Closed Date],">="&DATE(2025,1,1),Table1[Closed Date],"<="&DATE(2025,12,31)) -> 4495345.4 | L37: =SUMIFS(Table1[Project Value (RM)],Table1[Category],"R-PV",Table1[Closed Date],">="&DATE(2026,1,1),Table1[Closed Date],"<="&DATE(2026,12,31)) -> 0 | N37: =SUM(O37:R37) -> 8802124.6 | O37: =SUMIFS('Finance Tracker'!M:M,'Finance Tracker'!L:L,">="&DATE(2023,1,1),'Finance Tracker'!L:L,"<="&DATE(2023,12,31),'Finance Tracker'!F:F,"R-PV") +SUMIFS('Finance Tracker'!Q:Q,'Finance Tracker'!P:P,">="&DATE(2023,1,1),'Finance Tracker'!P:P,"<="&DATE(2023,12,31),'Finance Tracker'!F:F,"R-PV") +SUMIFS('Finance Tracker'!U:U,'Finance Tracker'!T:T,">="&DATE(2023,1,1),'Finance Tracker'!T:T,"<="&DATE(2023,12,31),'Finance Tracker'!F:F,"R-PV") +SUMIFS('Finance Tracker'!Y:Y,'Finance Tracker'!X:X,">="&DATE(2023,1,1),'Finance Tracker'!X:X,"<="&DATE(2023,12,31),'Finance Tracker'!F:F,"R-PV") +SUMIFS('Finance Tracker'!AC:AC,'Finance Tracker'!AB:AB,">="&DATE(2023,1,1),'Finance Tracker'!AB:AB,"<="&DATE(2023,12,31),'Finance Tracker'!F:F,"R-PV") +SUMIFS('Finance Tracker'!AG:AG,'Finance Tracker'!AF:AF,">="&DATE(2023,1,1),'Finance Tracker'!AF:AF,"<="&DATE(2023,12,31),'Finance Tracker'!F:F,"R-PV") -> 379240 | P37: =SUMIFS('Finance Tracker'!M:M,'Finance Tracker'!L:L,">="&DATE(2024,1,1),'Finance Tracker'!L:L,"<="&DATE(2024,12,31),'Finance Tracker'!F:F,"R-PV") +SUMIFS('Finance Tracker'!Q:Q,'Finance Tracker'!P:P,">="&DATE(2024,1,1),'Finance Tracker'!P:P,"<="&DATE(2024,12,31),'Finance Tracker'!F:F,"R-PV") +SUMIFS('Finance Tracker'!U:U,'Finance Tracker'!T:T,">="&DATE(2024,1,1),'Finance Tracker'!T:T,"<="&DATE(2024,12,31),'Finance Tracker'!F:F,"R-PV") +SUMIFS('Finance Tracker'!Y:Y,'Finance Tracker'!X:X,">="&DATE(2024,1,1),'Finance Tracker'!X:X,"<="&DATE(2024,12,31),'Finance Tracker'!F:F,"R-PV") +SUMIFS('Finance Tracker'!AC:AC,'Finance Tracker'!AB:AB,">="&DATE(2024,1,1),'Finance Tracker'!AB:AB,"<="&DATE(2024,12,31),'Finance Tracker'!F:F,"R-PV") +SUMIFS('Finance Tracker'!AG:AG,'Finance Tracker'!AF:AF,">="&DATE(2024,1,1),'Finance Tracker'!AF:AF,"<="&DATE(2024,12,31),'Finance Tracker'!F:F,"R-PV") -> 3897315.2 | Q37: =SUMIFS('Finance Tracker'!M:M,'Finance Tracker'!L:L,">="&DATE(2025,1,1),'Finance Tracker'!L:L,"<="&DATE(2025,12,31),'Finance Tracker'!F:F,"R-PV") +SUMIFS('Finance Tracker'!Q:Q,'Finance Tracker'!P:P,">="&DATE(2025,1,1),'Finance Tracker'!P:P,"<="&DATE(2025,12,31),'Finance Tracker'!F:F,"R-PV") +SUMIFS('Finance Tracker'!U:U,'Finance Tracker'!T:T,">="&DATE(2025,1,1),'Finance Tracker'!T:T,"<="&DATE(2025,12,31),'Finance Tracker'!F:F,"R-PV") +SUMIFS('Finance Tracker'!Y:Y,'Finance Tracker'!X:X,">="&DATE(2025,1,1),'Finance Tracker'!X:X,"<="&DATE(2025,12,31),'Finance Tracker'!F:F,"R-PV") +SUMIFS('Finance Tracker'!AC:AC,'Finance Tracker'!AB:AB,">="&DATE(2025,1,1),'Finance Tracker'!AB:AB,"<="&DATE(2025,12,31),'Finance Tracker'!F:F,"R-PV") +SUMIFS('Finance Tracker'!AG:AG,'Finance Tracker'!AF:AF,">="&DATE(2025,1,1),'Finance Tracker'!AF:AF,"<="&DATE(2025,12,31),'Finance Tracker'!F:F,"R-PV") -> 4525569.4 | R37: =SUMIFS('Finance Tracker'!M:M,'Finance Tracker'!L:L,">="&DATE(2026,1,1),'Finance Tracker'!L:L,"<="&DATE(2026,12,31),'Finance Tracker'!F:F,"R-PV") +SUMIFS('Finance Tracker'!Q:Q,'Finance Tracker'!P:P,">="&DATE(2026,1,1),'Finance Tracker'!P:P,"<="&DATE(2026,12,31),'Finance Tracker'!F:F,"R-PV") +SUMIFS('Finance Tracker'!U:U,'Finance Tracker'!T:T,">="&DATE(2026,1,1),'Finance Tracker'!T:T,"<="&DATE(2026,12,31),'Finance Tracker'!F:F,"R-PV") +SUMIFS('Finance Tracker'!Y:Y,'Finance Tracker'!X:X,">="&DATE(2026,1,1),'Finance Tracker'!X:X,"<="&DATE(2026,12,31),'Finance Tracker'!F:F,"R-PV") +SUMIFS('Finance Tracker'!AC:AC,'Finance Tracker'!AB:AB,">="&DATE(2026,1,1),'Finance Tracker'!AB:AB,"<="&DATE(2026,12,31),'Finance Tracker'!F:F,"R-PV") +SUMIFS('Finance Tracker'!AG:AG,'Finance Tracker'!AF:AF,">="&DATE(2026,1,1),'Finance Tracker'!AF:AF,"<="&DATE(2026,12,31),'Finance Tracker'!F:F,"R-PV") -> 0 | T37: =SUM(U37:X37) -> 8586827.6 | U37: =SUMIFS('Finance Tracker'!O:O,'Finance Tracker'!N:N,">="&DATE(2023,1,1),'Finance Tracker'!N:N,"<="&DATE(2023,12,31),'Finance Tracker'!F:F,"R-PV") +SUMIFS('Finance Tracker'!S:S,'Finance Tracker'!R:R,">="&DATE(2023,1,1),'Finance Tracker'!R:R,"<="&DATE(2023,12,31),'Finance Tracker'!F:F,"R-PV") +SUMIFS('Finance Tracker'!W:W,'Finance Tracker'!V:V,">="&DATE(2023,1,1),'Finance Tracker'!V:V,"<="&DATE(2023,12,31),'Finance Tracker'!F:F,"R-PV") +SUMIFS('Finance Tracker'!AA:AA,'Finance Tracker'!Z:Z,">="&DATE(2023,1,1),'Finance Tracker'!Z:Z,"<="&DATE(2023,12,31),'Finance Tracker'!F:F,"R-PV") +SUMIFS('Finance Tracker'!AD:AD,'Finance Tracker'!AE:AE,">="&DATE(2023,1,1),'Finance Tracker'!AE:AE,"<="&DATE(2023,12,31),'Finance Tracker'!F:F,"R-PV") +SUMIFS('Finance Tracker'!AI:AI,'Finance Tracker'!AH:AH,">="&DATE(2023,1,1),'Finance Tracker'!AH:AH,"<="&DATE(2023,12,31),'Finance Tracker'!F:F,"R-PV") -> 301640 | V37: =SUMIFS('Finance Tracker'!O:O,'Finance Tracker'!N:N,">="&DATE(2024,1,1),'Finance Tracker'!N:N,"<="&DATE(2024,12,31),'Finance Tracker'!F:F,"R-PV") +SUMIFS('Finance Tracker'!S:S,'Finance Tracker'!R:R,">="&DATE(2024,1,1),'Finance Tracker'!R:R,"<="&DATE(2024,12,31),'Finance Tracker'!F:F,"R-PV") +SUMIFS('Finance Tracker'!W:W,'Finance Tracker'!V:V,">="&DATE(2024,1,1),'Finance Tracker'!V:V,"<="&DATE(2024,12,31),'Finance Tracker'!F:F,"R-PV") +SUMIFS('Finance Tracker'!AA:AA,'Finance Tracker'!Z:Z,">="&DATE(2024,1,1),'Finance Tracker'!Z:Z,"<="&DATE(2024,12,31),'Finance Tracker'!F:F,"R-PV") +SUMIFS('Finance Tracker'!AD:AD,'Finance Tracker'!AE:AE,">="&DATE(2024,1,1),'Finance Tracker'!AE:AE,"<="&DATE(2024,12,31),'Finance Tracker'!F:F,"R-PV") +SUMIFS('Finance Tracker'!AI:AI,'Finance Tracker'!AH:AH,">="&DATE(2024,1,1),'Finance Tracker'!AH:AH,"<="&DATE(2024,12,31),'Finance Tracker'!F:F,"R-PV") -> 3691311.2 | W37: =SUMIFS('Finance Tracker'!O:O,'Finance Tracker'!N:N,">="&DATE(2025,1,1),'Finance Tracker'!N:N,"<="&DATE(2025,12,31),'Finance Tracker'!F:F,"R-PV") +SUMIFS('Finance Tracker'!S:S,'Finance Tracker'!R:R,">="&DATE(2025,1,1),'Finance Tracker'!R:R,"<="&DATE(2025,12,31),'Finance Tracker'!F:F,"R-PV") +SUMIFS('Finance Tracker'!W:W,'Finance Tracker'!V:V,">="&DATE(2025,1,1),'Finance Tracker'!V:V,"<="&DATE(2025,12,31),'Finance Tracker'!F:F,"R-PV") +SUMIFS('Finance Tracker'!AA:AA,'Finance Tracker'!Z:Z,">="&DATE(2025,1,1),'Finance Tracker'!Z:Z,"<="&DATE(2025,12,31),'Finance Tracker'!F:F,"R-PV") +SUMIFS('Finance Tracker'!AD:AD,'Finance Tracker'!AE:AE,">="&DATE(2025,1,1),'Finance Tracker'!AE:AE,"<="&DATE(2025,12,31),'Finance Tracker'!F:F,"R-PV") +SUMIFS('Finance Tracker'!AI:AI,'Finance Tracker'!AH:AH,">="&DATE(2025,1,1),'Finance Tracker'!AH:AH,"<="&DATE(2025,12,31),'Finance Tracker'!F:F,"R-PV") -> 4593876.4 | X37: =SUMIFS('Finance Tracker'!O:O,'Finance Tracker'!N:N,">="&DATE(2026,1,1),'Finance Tracker'!N:N,"<="&DATE(2026,12,31),'Finance Tracker'!F:F,"R-PV") +SUMIFS('Finance Tracker'!S:S,'Finance Tracker'!R:R,">="&DATE(2026,1,1),'Finance Tracker'!R:R,"<="&DATE(2026,12,31),'Finance Tracker'!F:F,"R-PV") +SUMIFS('Finance Tracker'!W:W,'Finance Tracker'!V:V,">="&DATE(2026,1,1),'Finance Tracker'!V:V,"<="&DATE(2026,12,31),'Finance Tracker'!F:F,"R-PV") +SUMIFS('Finance Tracker'!AA:AA,'Finance Tracker'!Z:Z,">="&DATE(2026,1,1),'Finance Tracker'!Z:Z,"<="&DATE(2026,12,31),'Finance Tracker'!F:F,"R-PV") +SUMIFS('Finance Tracker'!AE:AE,'Finance Tracker'!AE:AE,">="&DATE(2026,1,1),'Finance Tracker'!AD:AD,"<="&DATE(2026,12,31),'Finance Tracker'!F:F,"R-PV") +SUMIFS('Finance Tracker'!AI:AI,'Finance Tracker'!AH:AH,">="&DATE(2026,1,1),'Finance Tracker'!AH:AH,"<="&DATE(2026,12,31),'Finance Tracker'!F:F,"R-PV") -> 0 | Z37: =COUNTIF(Table1[Category],"R-PV") -> 313 | AA37: =COUNTIFS(Table1[Category],"R-PV",Table1[Closed Date],">="&DATE(2023,1,1),Table1[Closed Date],"<="&DATE(2023,12,31)) -> 23 | AB37: =COUNTIFS(Table1[Category],"R-PV",Table1[Closed Date],">="&DATE(2024,1,1),Table1[Closed Date],"<="&DATE(2024,12,31)) -> 143 | AC37: =COUNTIFS(Table1[Category],"R-PV",Table1[Closed Date],">="&DATE(2025,1,1),Table1[Closed Date],"<="&DATE(2025,12,31)) -> 147 | AD37: =COUNTIFS(Table1[Category],"R-PV",Table1[Closed Date],">="&DATE(2026,1,1),Table1[Closed Date],"<="&DATE(2026,12,31)) -> 0
A38: C&I (PV System) | B38: =SUMIFS(Table1[PV System Capacity (kWp)],Table1[Category],"*C&I*") -> 3718.01 | C38: =SUMIFS(Table1[PV System Capacity (kWp)],Table1[Category],"*C&I*",Table1[Closed Date],">="&DATE(2023,1,1),Table1[Closed Date],"<="&DATE(2023,12,31)) -> 428.695 | D38: =SUMIFS(Table1[PV System Capacity (kWp)],Table1[Category],"*C&I*",Table1[Closed Date],">="&DATE(2024,1,1),Table1[Closed Date],"<="&DATE(2024,12,31)) -> 2088.345 | E38: =SUMIFS(Table1[PV System Capacity (kWp)],Table1[Category],"*C&I*",Table1[Closed Date],">="&DATE(2025,1,1),Table1[Closed Date],"<="&DATE(2025,12,31)) -> 1200.97 | F38: =SUMIFS(Table1[PV System Capacity (kWp)],Table1[Category],"*C&I*",Table1[Closed Date],">="&DATE(2026,1,1),Table1[Closed Date],"<="&DATE(2026,12,31)) -> 0 | H38: =SUMIFS(Table1[Project Value (RM)],Table1[Category],"C&I-PV") -> 7185553.6 | I38: =SUMIFS(Table1[Project Value (RM)],Table1[Category],"C&I-PV",Table1[Closed Date],">="&DATE(2023,1,1),Table1[Closed Date],"<="&DATE(2023,12,31)) -> 521800 | J38: =SUMIFS(Table1[Project Value (RM)],Table1[Category],"C&I-PV",Table1[Closed Date],">="&DATE(2024,1,1),Table1[Closed Date],"<="&DATE(2024,12,31)) -> 4266680 | K38: =SUMIFS(Table1[Project Value (RM)],Table1[Category],"C&I-PV",Table1[Closed Date],">="&DATE(2025,1,1),Table1[Closed Date],"<="&DATE(2025,12,31)) -> 2397073.6 | L38: =SUMIFS(Table1[Project Value (RM)],Table1[Category],"C&I-PV",Table1[Closed Date],">="&DATE(2026,1,1),Table1[Closed Date],"<="&DATE(2026,12,31)) -> 0 | N38: =SUM(O38:R38) -> 6946746.4 | O38: =SUMIFS('Finance Tracker'!M:M,'Finance Tracker'!L:L,">="&DATE(2023,1,1),'Finance Tracker'!L:L,"<="&DATE(2023,12,31),'Finance Tracker'!F:F,"C&I-PV") +SUMIFS('Finance Tracker'!Q:Q,'Finance Tracker'!P:P,">="&DATE(2023,1,1),'Finance Tracker'!P:P,"<="&DATE(2023,12,31),'Finance Tracker'!F:F,"C&I-PV") +SUMIFS('Finance Tracker'!U:U,'Finance Tracker'!T:T,">="&DATE(2023,1,1),'Finance Tracker'!T:T,"<="&DATE(2023,12,31),'Finance Tracker'!F:F,"C&I-PV") +SUMIFS('Finance Tracker'!Y:Y,'Finance Tracker'!X:X,">="&DATE(2023,1,1),'Finance Tracker'!X:X,"<="&DATE(2023,12,31),'Finance Tracker'!F:F,"C&I-PV") +SUMIFS('Finance Tracker'!AC:AC,'Finance Tracker'!AB:AB,">="&DATE(2023,1,1),'Finance Tracker'!AB:AB,"<="&DATE(2023,12,31),'Finance Tracker'!F:F,"C&I-PV") +SUMIFS('Finance Tracker'!AG:AG,'Finance Tracker'!AF:AF,">="&DATE(2023,1,1),'Finance Tracker'!AF:AF,"<="&DATE(2023,12,31),'Finance Tracker'!F:F,"C&I-PV") -> 278820 | P38: =SUMIFS('Finance Tracker'!M:M,'Finance Tracker'!L:L,">="&DATE(2024,1,1),'Finance Tracker'!L:L,"<="&DATE(2024,12,31),'Finance Tracker'!F:F,"C&I-PV") +SUMIFS('Finance Tracker'!Q:Q,'Finance Tracker'!P:P,">="&DATE(2024,1,1),'Finance Tracker'!P:P,"<="&DATE(2024,12,31),'Finance Tracker'!F:F,"C&I-PV") +SUMIFS('Finance Tracker'!U:U,'Finance Tracker'!T:T,">="&DATE(2024,1,1),'Finance Tracker'!T:T,"<="&DATE(2024,12,31),'Finance Tracker'!F:F,"C&I-PV") +SUMIFS('Finance Tracker'!Y:Y,'Finance Tracker'!X:X,">="&DATE(2024,1,1),'Finance Tracker'!X:X,"<="&DATE(2024,12,31),'Finance Tracker'!F:F,"C&I-PV") +SUMIFS('Finance Tracker'!AC:AC,'Finance Tracker'!AB:AB,">="&DATE(2024,1,1),'Finance Tracker'!AB:AB,"<="&DATE(2024,12,31),'Finance Tracker'!F:F,"C&I-PV") +SUMIFS('Finance Tracker'!AG:AG,'Finance Tracker'!AF:AF,">="&DATE(2024,1,1),'Finance Tracker'!AF:AF,"<="&DATE(2024,12,31),'Finance Tracker'!F:F,"C&I-PV") -> 2643170 | Q38: =SUMIFS('Finance Tracker'!M:M,'Finance Tracker'!L:L,">="&DATE(2025,1,1),'Finance Tracker'!L:L,"<="&DATE(2025,12,31),'Finance Tracker'!F:F,"C&I-PV") +SUMIFS('Finance Tracker'!Q:Q,'Finance Tracker'!P:P,">="&DATE(2025,1,1),'Finance Tracker'!P:P,"<="&DATE(2025,12,31),'Finance Tracker'!F:F,"C&I-PV") +SUMIFS('Finance Tracker'!U:U,'Finance Tracker'!T:T,">="&DATE(2025,1,1),'Finance Tracker'!T:T,"<="&DATE(2025,12,31),'Finance Tracker'!F:F,"C&I-PV") +SUMIFS('Finance Tracker'!Y:Y,'Finance Tracker'!X:X,">="&DATE(2025,1,1),'Finance Tracker'!X:X,"<="&DATE(2025,12,31),'Finance Tracker'!F:F,"C&I-PV") +SUMIFS('Finance Tracker'!AC:AC,'Finance Tracker'!AB:AB,">="&DATE(2025,1,1),'Finance Tracker'!AB:AB,"<="&DATE(2025,12,31),'Finance Tracker'!F:F,"C&I-PV") +SUMIFS('Finance Tracker'!AG:AG,'Finance Tracker'!AF:AF,">="&DATE(2025,1,1),'Finance Tracker'!AF:AF,"<="&DATE(2025,12,31),'Finance Tracker'!F:F,"C&I-PV") -> 4024756.4 | R38: =SUMIFS('Finance Tracker'!M:M,'Finance Tracker'!L:L,">="&DATE(2026,1,1),'Finance Tracker'!L:L,"<="&DATE(2026,12,31),'Finance Tracker'!F:F,"C&I-PV") +SUMIFS('Finance Tracker'!Q:Q,'Finance Tracker'!P:P,">="&DATE(2026,1,1),'Finance Tracker'!P:P,"<="&DATE(2026,12,31),'Finance Tracker'!F:F,"C&I-PV") +SUMIFS('Finance Tracker'!U:U,'Finance Tracker'!T:T,">="&DATE(2026,1,1),'Finance Tracker'!T:T,"<="&DATE(2026,12,31),'Finance Tracker'!F:F,"C&I-PV") +SUMIFS('Finance Tracker'!Y:Y,'Finance Tracker'!X:X,">="&DATE(2026,1,1),'Finance Tracker'!X:X,"<="&DATE(2026,12,31),'Finance Tracker'!F:F,"C&I-PV") +SUMIFS('Finance Tracker'!AC:AC,'Finance Tracker'!AB:AB,">="&DATE(2026,1,1),'Finance Tracker'!AB:AB,"<="&DATE(2026,12,31),'Finance Tracker'!F:F,"C&I-PV") +SUMIFS('Finance Tracker'!AG:AG,'Finance Tracker'!AF:AF,">="&DATE(2026,1,1),'Finance Tracker'!AF:AF,"<="&DATE(2026,12,31),'Finance Tracker'!F:F,"C&I-PV") -> 0 | T38: =SUM(U38:X38) -> 5420201.4 | U38: =SUMIFS('Finance Tracker'!O:O,'Finance Tracker'!N:N,">="&DATE(2023,1,1),'Finance Tracker'!N:N,"<="&DATE(2023,12,31),'Finance Tracker'!F:F,"C&I-PV") +SUMIFS('Finance Tracker'!S:S,'Finance Tracker'!R:R,">="&DATE(2023,1,1),'Finance Tracker'!R:R,"<="&DATE(2023,12,31),'Finance Tracker'!F:F,"C&I-PV") +SUMIFS('Finance Tracker'!W:W,'Finance Tracker'!V:V,">="&DATE(2023,1,1),'Finance Tracker'!V:V,"<="&DATE(2023,12,31),'Finance Tracker'!F:F,"C&I-PV") +SUMIFS('Finance Tracker'!AA:AA,'Finance Tracker'!Z:Z,">="&DATE(2023,1,1),'Finance Tracker'!Z:Z,"<="&DATE(2023,12,31),'Finance Tracker'!F:F,"C&I-PV") +SUMIFS('Finance Tracker'!AD:AD,'Finance Tracker'!AE:AE,">="&DATE(2023,1,1),'Finance Tracker'!AE:AE,"<="&DATE(2023,12,31),'Finance Tracker'!F:F,"C&I-PV") +SUMIFS('Finance Tracker'!AI:AI,'Finance Tracker'!AH:AH,">="&DATE(2023,1,1),'Finance Tracker'!AH:AH,"<="&DATE(2023,12,31),'Finance Tracker'!F:F,"C&I-PV") -> 278820 | V38: =SUMIFS('Finance Tracker'!O:O,'Finance Tracker'!N:N,">="&DATE(2024,1,1),'Finance Tracker'!N:N,"<="&DATE(2024,12,31),'Finance Tracker'!F:F,"C&I-PV") +SUMIFS('Finance Tracker'!S:S,'Finance Tracker'!R:R,">="&DATE(2024,1,1),'Finance Tracker'!R:R,"<="&DATE(2024,12,31),'Finance Tracker'!F:F,"C&I-PV") +SUMIFS('Finance Tracker'!W:W,'Finance Tracker'!V:V,">="&DATE(2024,1,1),'Finance Tracker'!V:V,"<="&DATE(2024,12,31),'Finance Tracker'!F:F,"C&I-PV") +SUMIFS('Finance Tracker'!AA:AA,'Finance Tracker'!Z:Z,">="&DATE(2024,1,1),'Finance Tracker'!Z:Z,"<="&DATE(2024,12,31),'Finance Tracker'!F:F,"C&I-PV") +SUMIFS('Finance Tracker'!AD:AD,'Finance Tracker'!AE:AE,">="&DATE(2024,1,1),'Finance Tracker'!AE:AE,"<="&DATE(2024,12,31),'Finance Tracker'!F:F,"C&I-PV") +SUMIFS('Finance Tracker'!AI:AI,'Finance Tracker'!AH:AH,">="&DATE(2024,1,1),'Finance Tracker'!AH:AH,"<="&DATE(2024,12,31),'Finance Tracker'!F:F,"C&I-PV") -> 2422890 | W38: =SUMIFS('Finance Tracker'!O:O,'Finance Tracker'!N:N,">="&DATE(2025,1,1),'Finance Tracker'!N:N,"<="&DATE(2025,12,31),'Finance Tracker'!F:F,"C&I-PV") +SUMIFS('Finance Tracker'!S:S,'Finance Tracker'!R:R,">="&DATE(2025,1,1),'Finance Tracker'!R:R,"<="&DATE(2025,12,31),'Finance Tracker'!F:F,"C&I-PV") +SUMIFS('Finance Tracker'!W:W,'Finance Tracker'!V:V,">="&DATE(2025,1,1),'Finance Tracker'!V:V,"<="&DATE(2025,12,31),'Finance Tracker'!F:F,"C&I-PV") +SUMIFS('Finance Tracker'!AA:AA,'Finance Tracker'!Z:Z,">="&DATE(2025,1,1),'Finance Tracker'!Z:Z,"<="&DATE(2025,12,31),'Finance Tracker'!F:F,"C&I-PV") +SUMIFS('Finance Tracker'!AD:AD,'Finance Tracker'!AE:AE,">="&DATE(2025,1,1),'Finance Tracker'!AE:AE,"<="&DATE(2025,12,31),'Finance Tracker'!F:F,"C&I-PV") +SUMIFS('Finance Tracker'!AI:AI,'Finance Tracker'!AH:AH,">="&DATE(2025,1,1),'Finance Tracker'!AH:AH,"<="&DATE(2025,12,31),'Finance Tracker'!F:F,"C&I-PV") -> 2718491.4 | X38: =SUMIFS('Finance Tracker'!O:O,'Finance Tracker'!N:N,">="&DATE(2026,1,1),'Finance Tracker'!N:N,"<="&DATE(2026,12,31),'Finance Tracker'!F:F,"C&I-PV") +SUMIFS('Finance Tracker'!S:S,'Finance Tracker'!R:R,">="&DATE(2026,1,1),'Finance Tracker'!R:R,"<="&DATE(2026,12,31),'Finance Tracker'!F:F,"C&I-PV") +SUMIFS('Finance Tracker'!W:W,'Finance Tracker'!V:V,">="&DATE(2026,1,1),'Finance Tracker'!V:V,"<="&DATE(2026,12,31),'Finance Tracker'!F:F,"C&I-PV") +SUMIFS('Finance Tracker'!AA:AA,'Finance Tracker'!Z:Z,">="&DATE(2026,1,1),'Finance Tracker'!Z:Z,"<="&DATE(2026,12,31),'Finance Tracker'!F:F,"C&I-PV") +SUMIFS('Finance Tracker'!AD:AD,'Finance Tracker'!AE:AE,">="&DATE(2026,1,1),'Finance Tracker'!AE:AE,"<="&DATE(2026,12,31),'Finance Tracker'!F:F,"C&I-PV") +SUMIFS('Finance Tracker'!AI:AI,'Finance Tracker'!AH:AH,">="&DATE(2026,1,1),'Finance Tracker'!AH:AH,"<="&DATE(2026,12,31),'Finance Tracker'!F:F,"C&I-PV") -> 0 | Z38: =COUNTIF(Table1[Category],"C&I-PV") -> 33 | AA38: =COUNTIFS(Table1[Category],"C&I-PV",Table1[Closed Date],">="&DATE(2023,1,1),Table1[Closed Date],"<="&DATE(2023,12,31)) -> 3 | AB38: =COUNTIFS(Table1[Category],"C&I-PV",Table1[Closed Date],">="&DATE(2024,1,1),Table1[Closed Date],"<="&DATE(2024,12,31)) -> 18 | AC38: =COUNTIFS(Table1[Category],"C&I-PV",Table1[Closed Date],">="&DATE(2025,1,1),Table1[Closed Date],"<="&DATE(2025,12,31)) -> 12 | AD38: =COUNTIFS(Table1[Category],"C&I-PV",Table1[Closed Date],">="&DATE(2026,1,1),Table1[Closed Date],"<="&DATE(2026,12,31)) -> 0
A39: Residential BESS | B39: =SUMIFS(Table1[BESS Capacity],Table1[Category],"R-BESS") -> 287.4 | C39: =SUMIFS(Table1[BESS Capacity],Table1[Category],"R-BESS",Table1[Closed Date],">="&DATE(2023,1,1),Table1[Closed Date],"<="&DATE(2023,12,31)) -> 287.4 | D39: =SUMIFS(Table1[BESS Capacity],Table1[Category],"R-BESS",Table1[Closed Date],">="&DATE(2024,1,1),Table1[Closed Date],"<="&DATE(2024,12,31)) -> 0 | E39: =SUMIFS(Table1[BESS Capacity],Table1[Category],"R-BESS",Table1[Closed Date],">="&DATE(2025,1,1),Table1[Closed Date],"<="&DATE(2025,12,31)) -> 0 | F39: =SUMIFS(Table1[BESS Capacity],Table1[Category],"R-BESS",Table1[Closed Date],">="&DATE(2026,1,1),Table1[Closed Date],"<="&DATE(2026,12,31)) -> 0 | H39: =SUMIFS(Table1[Project Value (RM)],Table1[Category],"R-BESS") -> 720000 | I39: =SUMIFS(Table1[Project Value (RM)],Table1[Category],"R-BESS",Table1[Closed Date],">="&DATE(2023,1,1),Table1[Closed Date],"<="&DATE(2023,12,31)) -> 720000 | J39: =SUMIFS(Table1[Project Value (RM)],Table1[Category],"R-BESS",Table1[Closed Date],">="&DATE(2024,1,1),Table1[Closed Date],"<="&DATE(2024,12,31)) -> 0 | K39: =SUMIFS(Table1[Project Value (RM)],Table1[Category],"R-BESS",Table1[Closed Date],">="&DATE(2025,1,1),Table1[Closed Date],"<="&DATE(2025,12,31)) -> 0 | L39: =SUMIFS(Table1[Project Value (RM)],Table1[Category],"R-BESS",Table1[Closed Date],">="&DATE(2026,1,1),Table1[Closed Date],"<="&DATE(2026,12,31)) -> 0 | N39: =SUM(O39:R39) -> 720000 | O39: =SUMIFS('Finance Tracker'!M:M,'Finance Tracker'!L:L,">="&DATE(2023,1,1),'Finance Tracker'!L:L,"<="&DATE(2023,12,31),'Finance Tracker'!F:F,"R-BESS") +SUMIFS('Finance Tracker'!Q:Q,'Finance Tracker'!P:P,">="&DATE(2023,1,1),'Finance Tracker'!P:P,"<="&DATE(2023,12,31),'Finance Tracker'!F:F,"R-BESS") +SUMIFS('Finance Tracker'!U:U,'Finance Tracker'!T:T,">="&DATE(2023,1,1),'Finance Tracker'!T:T,"<="&DATE(2023,12,31),'Finance Tracker'!F:F,"R-BESS") +SUMIFS('Finance Tracker'!Y:Y,'Finance Tracker'!X:X,">="&DATE(2023,1,1),'Finance Tracker'!X:X,"<="&DATE(2023,12,31),'Finance Tracker'!F:F,"R-BESS") +SUMIFS('Finance Tracker'!AC:AC,'Finance Tracker'!AB:AB,">="&DATE(2023,1,1),'Finance Tracker'!AB:AB,"<="&DATE(2023,12,31),'Finance Tracker'!F:F,"R-BESS") +SUMIFS('Finance Tracker'!AG:AG,'Finance Tracker'!AF:AF,">="&DATE(2023,1,1),'Finance Tracker'!AF:AF,"<="&DATE(2023,12,31),'Finance Tracker'!F:F,"R-BESS") -> 432000 | P39: =SUMIFS('Finance Tracker'!M:M,'Finance Tracker'!L:L,">="&DATE(2024,1,1),'Finance Tracker'!L:L,"<="&DATE(2024,12,31),'Finance Tracker'!F:F,"R-BESS") +SUMIFS('Finance Tracker'!Q:Q,'Finance Tracker'!P:P,">="&DATE(2024,1,1),'Finance Tracker'!P:P,"<="&DATE(2024,12,31),'Finance Tracker'!F:F,"R-BESS") +SUMIFS('Finance Tracker'!U:U,'Finance Tracker'!T:T,">="&DATE(2024,1,1),'Finance Tracker'!T:T,"<="&DATE(2024,12,31),'Finance Tracker'!F:F,"R-BESS") +SUMIFS('Finance Tracker'!Y:Y,'Finance Tracker'!X:X,">="&DATE(2024,1,1),'Finance Tracker'!X:X,"<="&DATE(2024,12,31),'Finance Tracker'!F:F,"R-BESS") +SUMIFS('Finance Tracker'!AC:AC,'Finance Tracker'!AB:AB,">="&DATE(2024,1,1),'Finance Tracker'!AB:AB,"<="&DATE(2024,12,31),'Finance Tracker'!F:F,"R-BESS") +SUMIFS('Finance Tracker'!AG:AG,'Finance Tracker'!AF:AF,">="&DATE(2024,1,1),'Finance Tracker'!AF:AF,"<="&DATE(2024,12,31),'Finance Tracker'!F:F,"R-BESS") -> 288000 | Q39: =SUMIFS('Finance Tracker'!M:M,'Finance Tracker'!L:L,">="&DATE(2025,1,1),'Finance Tracker'!L:L,"<="&DATE(2025,12,31),'Finance Tracker'!F:F,"R-BESS") +SUMIFS('Finance Tracker'!Q:Q,'Finance Tracker'!P:P,">="&DATE(2025,1,1),'Finance Tracker'!P:P,"<="&DATE(2025,12,31),'Finance Tracker'!F:F,"R-BESS") +SUMIFS('Finance Tracker'!U:U,'Finance Tracker'!T:T,">="&DATE(2025,1,1),'Finance Tracker'!T:T,"<="&DATE(2025,12,31),'Finance Tracker'!F:F,"R-BESS") +SUMIFS('Finance Tracker'!Y:Y,'Finance Tracker'!X:X,">="&DATE(2025,1,1),'Finance Tracker'!X:X,"<="&DATE(2025,12,31),'Finance Tracker'!F:F,"R-BESS") +SUMIFS('Finance Tracker'!AC:AC,'Finance Tracker'!AB:AB,">="&DATE(2025,1,1),'Finance Tracker'!AB:AB,"<="&DATE(2025,12,31),'Finance Tracker'!F:F,"R-BESS") +SUMIFS('Finance Tracker'!AG:AG,'Finance Tracker'!AF:AF,">="&DATE(2025,1,1),'Finance Tracker'!AF:AF,"<="&DATE(2025,12,31),'Finance Tracker'!F:F,"R-BESS") -> 0 | R39: =SUMIFS('Finance Tracker'!M:M,'Finance Tracker'!L:L,">="&DATE(2026,1,1),'Finance Tracker'!L:L,"<="&DATE(2026,12,31),'Finance Tracker'!F:F,"R-BESS") +SUMIFS('Finance Tracker'!Q:Q,'Finance Tracker'!P:P,">="&DATE(2026,1,1),'Finance Tracker'!P:P,"<="&DATE(2026,12,31),'Finance Tracker'!F:F,"R-BESS") +SUMIFS('Finance Tracker'!U:U,'Finance Tracker'!T:T,">="&DATE(2026,1,1),'Finance Tracker'!T:T,"<="&DATE(2026,12,31),'Finance Tracker'!F:F,"R-BESS") +SUMIFS('Finance Tracker'!Y:Y,'Finance Tracker'!X:X,">="&DATE(2026,1,1),'Finance Tracker'!X:X,"<="&DATE(2026,12,31),'Finance Tracker'!F:F,"R-BESS") +SUMIFS('Finance Tracker'!AC:AC,'Finance Tracker'!AB:AB,">="&DATE(2026,1,1),'Finance Tracker'!AB:AB,"<="&DATE(2026,12,31),'Finance Tracker'!F:F,"R-BESS") +SUMIFS('Finance Tracker'!AG:AG,'Finance Tracker'!AF:AF,">="&DATE(2026,1,1),'Finance Tracker'!AF:AF,"<="&DATE(2026,12,31),'Finance Tracker'!F:F,"R-BESS") -> 0 | T39: =SUM(U39:X39) -> 720000 | U39: =SUMIFS('Finance Tracker'!O:O,'Finance Tracker'!N:N,">="&DATE(2023,1,1),'Finance Tracker'!N:N,"<="&DATE(2023,12,31),'Finance Tracker'!F:F,"R-BESS") +SUMIFS('Finance Tracker'!S:S,'Finance Tracker'!R:R,">="&DATE(2023,1,1),'Finance Tracker'!R:R,"<="&DATE(2023,12,31),'Finance Tracker'!F:F,"R-BESS") +SUMIFS('Finance Tracker'!W:W,'Finance Tracker'!V:V,">="&DATE(2023,1,1),'Finance Tracker'!V:V,"<="&DATE(2023,12,31),'Finance Tracker'!F:F,"R-BESS") +SUMIFS('Finance Tracker'!AA:AA,'Finance Tracker'!Z:Z,">="&DATE(2023,1,1),'Finance Tracker'!Z:Z,"<="&DATE(2023,12,31),'Finance Tracker'!F:F,"R-BESS") +SUMIFS('Finance Tracker'!AD:AD,'Finance Tracker'!AE:AE,">="&DATE(2023,1,1),'Finance Tracker'!AE:AE,"<="&DATE(2023,12,31),'Finance Tracker'!F:F,"R-BESS") +SUMIFS('Finance Tracker'!AI:AI,'Finance Tracker'!AH:AH,">="&DATE(2023,1,1),'Finance Tracker'!AH:AH,"<="&DATE(2023,12,31),'Finance Tracker'!F:F,"R-BESS") -> 432000 | V39: =SUMIFS('Finance Tracker'!O:O,'Finance Tracker'!N:N,">="&DATE(2024,1,1),'Finance Tracker'!N:N,"<="&DATE(2024,12,31),'Finance Tracker'!F:F,"R-BESS") +SUMIFS('Finance Tracker'!S:S,'Finance Tracker'!R:R,">="&DATE(2024,1,1),'Finance Tracker'!R:R,"<="&DATE(2024,12,31),'Finance Tracker'!F:F,"R-BESS") +SUMIFS('Finance Tracker'!W:W,'Finance Tracker'!V:V,">="&DATE(2024,1,1),'Finance Tracker'!V:V,"<="&DATE(2024,12,31),'Finance Tracker'!F:F,"R-BESS") +SUMIFS('Finance Tracker'!AA:AA,'Finance Tracker'!Z:Z,">="&DATE(2024,1,1),'Finance Tracker'!Z:Z,"<="&DATE(2024,12,31),'Finance Tracker'!F:F,"R-BESS") +SUMIFS('Finance Tracker'!AD:AD,'Finance Tracker'!AE:AE,">="&DATE(2024,1,1),'Finance Tracker'!AE:AE,"<="&DATE(2024,12,31),'Finance Tracker'!F:F,"R-BESS") +SUMIFS('Finance Tracker'!AI:AI,'Finance Tracker'!AH:AH,">="&DATE(2024,1,1),'Finance Tracker'!AH:AH,"<="&DATE(2024,12,31),'Finance Tracker'!F:F,"R-BESS") -> 288000 | W39: =SUMIFS('Finance Tracker'!O:O,'Finance Tracker'!N:N,">="&DATE(2025,1,1),'Finance Tracker'!N:N,"<="&DATE(2025,12,31),'Finance Tracker'!F:F,"R-BESS") +SUMIFS('Finance Tracker'!S:S,'Finance Tracker'!R:R,">="&DATE(2025,1,1),'Finance Tracker'!R:R,"<="&DATE(2025,12,31),'Finance Tracker'!F:F,"R-BESS") +SUMIFS('Finance Tracker'!W:W,'Finance Tracker'!V:V,">="&DATE(2025,1,1),'Finance Tracker'!V:V,"<="&DATE(2025,12,31),'Finance Tracker'!F:F,"R-BESS") +SUMIFS('Finance Tracker'!AA:AA,'Finance Tracker'!Z:Z,">="&DATE(2025,1,1),'Finance Tracker'!Z:Z,"<="&DATE(2025,12,31),'Finance Tracker'!F:F,"R-BESS") +SUMIFS('Finance Tracker'!AD:AD,'Finance Tracker'!AE:AE,">="&DATE(2025,1,1),'Finance Tracker'!AE:AE,"<="&DATE(2025,12,31),'Finance Tracker'!F:F,"R-BESS") +SUMIFS('Finance Tracker'!AI:AI,'Finance Tracker'!AH:AH,">="&DATE(2025,1,1),'Finance Tracker'!AH:AH,"<="&DATE(2025,12,31),'Finance Tracker'!F:F,"R-BESS") -> 0 | X39: =SUMIFS('Finance Tracker'!O:O,'Finance Tracker'!N:N,">="&DATE(2026,1,1),'Finance Tracker'!N:N,"<="&DATE(2026,12,31),'Finance Tracker'!F:F,"R-BESS") +SUMIFS('Finance Tracker'!S:S,'Finance Tracker'!R:R,">="&DATE(2026,1,1),'Finance Tracker'!R:R,"<="&DATE(2026,12,31),'Finance Tracker'!F:F,"R-BESS") +SUMIFS('Finance Tracker'!W:W,'Finance Tracker'!V:V,">="&DATE(2026,1,1),'Finance Tracker'!V:V,"<="&DATE(2026,12,31),'Finance Tracker'!F:F,"R-BESS") +SUMIFS('Finance Tracker'!AA:AA,'Finance Tracker'!Z:Z,">="&DATE(2026,1,1),'Finance Tracker'!Z:Z,"<="&DATE(2026,12,31),'Finance Tracker'!F:F,"R-BESS") +SUMIFS('Finance Tracker'!AD:AD,'Finance Tracker'!AE:AE,">="&DATE(2026,1,1),'Finance Tracker'!AE:AE,"<="&DATE(2026,12,31),'Finance Tracker'!F:F,"R-BESS") +SUMIFS('Finance Tracker'!AI:AI,'Finance Tracker'!AH:AH,">="&DATE(2026,1,1),'Finance Tracker'!AH:AH,"<="&DATE(2026,12,31),'Finance Tracker'!F:F,"R-BESS") -> 0 | Z39: =COUNTIF(Table1[Category],"R-BESS") -> 1 | AA39: =COUNTIFS(Table1[Category],"R-BESS",Table1[Closed Date],">="&DATE(2023,1,1),Table1[Closed Date],"<="&DATE(2023,12,31)) -> 1 | AB39: =COUNTIFS(Table1[Category],"R-BESS",Table1[Closed Date],">="&DATE(2024,1,1),Table1[Closed Date],"<="&DATE(2024,12,31)) -> 0 | AC39: =COUNTIFS(Table1[Category],"R-BESS",Table1[Closed Date],">="&DATE(2025,1,1),Table1[Closed Date],"<="&DATE(2025,12,31)) -> 0 | AD39: =COUNTIFS(Table1[Category],"R-BESS",Table1[Closed Date],">="&DATE(2026,1,1),Table1[Closed Date],"<="&DATE(2026,12,31)) -> 0
A40: C&I BESS | B40: =SUMIFS(Table1[BESS Capacity],Table1[Category],"C&I-BESS") -> 0 | C40: =SUMIFS(Table1[BESS Capacity],Table1[Category],"C&I-BESS",Table1[Closed Date],">="&DATE(2023,1,1),Table1[Closed Date],"<="&DATE(2023,12,31)) -> 0 | D40: =SUMIFS(Table1[BESS Capacity],Table1[Category],"C&I-BESS",Table1[Closed Date],">="&DATE(2024,1,1),Table1[Closed Date],"<="&DATE(2024,12,31)) -> 0 | E40: =SUMIFS(Table1[BESS Capacity],Table1[Category],"C&I-BESS",Table1[Closed Date],">="&DATE(2025,1,1),Table1[Closed Date],"<="&DATE(2025,12,31)) -> 0 | F40: =SUMIFS(Table1[BESS Capacity],Table1[Category],"C&I-BESS",Table1[Closed Date],">="&DATE(2026,1,1),Table1[Closed Date],"<="&DATE(2026,12,31)) -> 0 | H40: =SUMIFS(Table1[Project Value (RM)],Table1[Category],"C&I-BESS") -> 0 | I40: =SUMIFS(Table1[Project Value (RM)],Table1[Category],"C&I-BESS",Table1[Closed Date],">="&DATE(2023,1,1),Table1[Closed Date],"<="&DATE(2023,12,31)) -> 0 | J40: =SUMIFS(Table1[Project Value (RM)],Table1[Category],"C&I-BESS",Table1[Closed Date],">="&DATE(2024,1,1),Table1[Closed Date],"<="&DATE(2024,12,31)) -> 0 | K40: =SUMIFS(Table1[Project Value (RM)],Table1[Category],"C&I-BESS",Table1[Closed Date],">="&DATE(2025,1,1),Table1[Closed Date],"<="&DATE(2025,12,31)) -> 0 | L40: =SUMIFS(Table1[Project Value (RM)],Table1[Category],"C&I-BESS",Table1[Closed Date],">="&DATE(2026,1,1),Table1[Closed Date],"<="&DATE(2026,12,31)) -> 0 | N40: =SUM(O40:R40) -> 0 | O40: =SUMIFS('Finance Tracker'!M:M,'Finance Tracker'!L:L,">="&DATE(2023,1,1),'Finance Tracker'!L:L,"<="&DATE(2023,12,31),'Finance Tracker'!F:F,"C&I-BESS") +SUMIFS('Finance Tracker'!Q:Q,'Finance Tracker'!P:P,">="&DATE(2023,1,1),'Finance Tracker'!P:P,"<="&DATE(2023,12,31),'Finance Tracker'!F:F,"C&I-BESS") +SUMIFS('Finance Tracker'!U:U,'Finance Tracker'!T:T,">="&DATE(2023,1,1),'Finance Tracker'!T:T,"<="&DATE(2023,12,31),'Finance Tracker'!F:F,"C&I-BESS") +SUMIFS('Finance Tracker'!Y:Y,'Finance Tracker'!X:X,">="&DATE(2023,1,1),'Finance Tracker'!X:X,"<="&DATE(2023,12,31),'Finance Tracker'!F:F,"C&I-BESS") +SUMIFS('Finance Tracker'!AC:AC,'Finance Tracker'!AB:AB,">="&DATE(2023,1,1),'Finance Tracker'!AB:AB,"<="&DATE(2023,12,31),'Finance Tracker'!F:F,"C&I-BESS") +SUMIFS('Finance Tracker'!AG:AG,'Finance Tracker'!AF:AF,">="&DATE(2023,1,1),'Finance Tracker'!AF:AF,"<="&DATE(2023,12,31),'Finance Tracker'!F:F,"C&I-BESS") -> 0 | P40: =SUMIFS('Finance Tracker'!M:M,'Finance Tracker'!L:L,">="&DATE(2024,1,1),'Finance Tracker'!L:L,"<="&DATE(2024,12,31),'Finance Tracker'!F:F,"C&I-BESS") +SUMIFS('Finance Tracker'!Q:Q,'Finance Tracker'!P:P,">="&DATE(2024,1,1),'Finance Tracker'!P:P,"<="&DATE(2024,12,31),'Finance Tracker'!F:F,"C&I-BESS") +SUMIFS('Finance Tracker'!U:U,'Finance Tracker'!T:T,">="&DATE(2024,1,1),'Finance Tracker'!T:T,"<="&DATE(2024,12,31),'Finance Tracker'!F:F,"C&I-BESS") +SUMIFS('Finance Tracker'!Y:Y,'Finance Tracker'!X:X,">="&DATE(2024,1,1),'Finance Tracker'!X:X,"<="&DATE(2024,12,31),'Finance Tracker'!F:F,"C&I-BESS") +SUMIFS('Finance Tracker'!AC:AC,'Finance Tracker'!AB:AB,">="&DATE(2024,1,1),'Finance Tracker'!AB:AB,"<="&DATE(2024,12,31),'Finance Tracker'!F:F,"C&I-BESS") +SUMIFS('Finance Tracker'!AG:AG,'Finance Tracker'!AF:AF,">="&DATE(2024,1,1),'Finance Tracker'!AF:AF,"<="&DATE(2024,12,31),'Finance Tracker'!F:F,"C&I-BESS") -> 0 | Q40: =SUMIFS('Finance Tracker'!M:M,'Finance Tracker'!L:L,">="&DATE(2025,1,1),'Finance Tracker'!L:L,"<="&DATE(2025,12,31),'Finance Tracker'!F:F,"C&I-BESS") +SUMIFS('Finance Tracker'!Q:Q,'Finance Tracker'!P:P,">="&DATE(2025,1,1),'Finance Tracker'!P:P,"<="&DATE(2025,12,31),'Finance Tracker'!F:F,"C&I-BESS") +SUMIFS('Finance Tracker'!U:U,'Finance Tracker'!T:T,">="&DATE(2025,1,1),'Finance Tracker'!T:T,"<="&DATE(2025,12,31),'Finance Tracker'!F:F,"C&I-BESS") +SUMIFS('Finance Tracker'!Y:Y,'Finance Tracker'!X:X,">="&DATE(2025,1,1),'Finance Tracker'!X:X,"<="&DATE(2025,12,31),'Finance Tracker'!F:F,"C&I-BESS") +SUMIFS('Finance Tracker'!AC:AC,'Finance Tracker'!AB:AB,">="&DATE(2025,1,1),'Finance Tracker'!AB:AB,"<="&DATE(2025,12,31),'Finance Tracker'!F:F,"C&I-BESS") +SUMIFS('Finance Tracker'!AG:AG,'Finance Tracker'!AF:AF,">="&DATE(2025,1,1),'Finance Tracker'!AF:AF,"<="&DATE(2025,12,31),'Finance Tracker'!F:F,"C&I-BESS") -> 0 | R40: =SUMIFS('Finance Tracker'!M:M,'Finance Tracker'!L:L,">="&DATE(2026,1,1),'Finance Tracker'!L:L,"<="&DATE(2026,12,31),'Finance Tracker'!F:F,"C&I-BESS") +SUMIFS('Finance Tracker'!Q:Q,'Finance Tracker'!P:P,">="&DATE(2026,1,1),'Finance Tracker'!P:P,"<="&DATE(2026,12,31),'Finance Tracker'!F:F,"C&I-BESS") +SUMIFS('Finance Tracker'!U:U,'Finance Tracker'!T:T,">="&DATE(2026,1,1),'Finance Tracker'!T:T,"<="&DATE(2026,12,31),'Finance Tracker'!F:F,"C&I-BESS") +SUMIFS('Finance Tracker'!Y:Y,'Finance Tracker'!X:X,">="&DATE(2026,1,1),'Finance Tracker'!X:X,"<="&DATE(2026,12,31),'Finance Tracker'!F:F,"C&I-BESS") +SUMIFS('Finance Tracker'!AC:AC,'Finance Tracker'!AB:AB,">="&DATE(2026,1,1),'Finance Tracker'!AB:AB,"<="&DATE(2026,12,31),'Finance Tracker'!F:F,"C&I-BESS") +SUMIFS('Finance Tracker'!AG:AG,'Finance Tracker'!AF:AF,">="&DATE(2026,1,1),'Finance Tracker'!AF:AF,"<="&DATE(2026,12,31),'Finance Tracker'!F:F,"C&I-BESS") -> 0 | T40: =SUM(U40:X40) -> 0 | U40: =SUMIFS('Finance Tracker'!O:O,'Finance Tracker'!N:N,">="&DATE(2023,1,1),'Finance Tracker'!N:N,"<="&DATE(2023,12,31),'Finance Tracker'!F:F,"C&I-BESS") +SUMIFS('Finance Tracker'!S:S,'Finance Tracker'!R:R,">="&DATE(2023,1,1),'Finance Tracker'!R:R,"<="&DATE(2023,12,31),'Finance Tracker'!F:F,"C&I-BESS") +SUMIFS('Finance Tracker'!W:W,'Finance Tracker'!V:V,">="&DATE(2023,1,1),'Finance Tracker'!V:V,"<="&DATE(2023,12,31),'Finance Tracker'!F:F,"C&I-BESS") +SUMIFS('Finance Tracker'!AA:AA,'Finance Tracker'!Z:Z,">="&DATE(2023,1,1),'Finance Tracker'!Z:Z,"<="&DATE(2023,12,31),'Finance Tracker'!F:F,"C&I-BESS") +SUMIFS('Finance Tracker'!AD:AD,'Finance Tracker'!AE:AE,">="&DATE(2023,1,1),'Finance Tracker'!AE:AE,"<="&DATE(2023,12,31),'Finance Tracker'!F:F,"C&I-BESS") +SUMIFS('Finance Tracker'!AI:AI,'Finance Tracker'!AH:AH,">="&DATE(2023,1,1),'Finance Tracker'!AH:AH,"<="&DATE(2023,12,31),'Finance Tracker'!F:F,"C&I-BESS") -> 0 | V40: =SUMIFS('Finance Tracker'!O:O,'Finance Tracker'!N:N,">="&DATE(2024,1,1),'Finance Tracker'!N:N,"<="&DATE(2024,12,31),'Finance Tracker'!F:F,"C&I-BESS") +SUMIFS('Finance Tracker'!S:S,'Finance Tracker'!R:R,">="&DATE(2024,1,1),'Finance Tracker'!R:R,"<="&DATE(2024,12,31),'Finance Tracker'!F:F,"C&I-BESS") +SUMIFS('Finance Tracker'!W:W,'Finance Tracker'!V:V,">="&DATE(2024,1,1),'Finance Tracker'!V:V,"<="&DATE(2024,12,31),'Finance Tracker'!F:F,"C&I-BESS") +SUMIFS('Finance Tracker'!AA:AA,'Finance Tracker'!Z:Z,">="&DATE(2024,1,1),'Finance Tracker'!Z:Z,"<="&DATE(2024,12,31),'Finance Tracker'!F:F,"C&I-BESS") +SUMIFS('Finance Tracker'!AD:AD,'Finance Tracker'!AE:AE,">="&DATE(2024,1,1),'Finance Tracker'!AE:AE,"<="&DATE(2024,12,31),'Finance Tracker'!F:F,"C&I-BESS") +SUMIFS('Finance Tracker'!AI:AI,'Finance Tracker'!AH:AH,">="&DATE(2024,1,1),'Finance Tracker'!AH:AH,"<="&DATE(2024,12,31),'Finance Tracker'!F:F,"C&I-BESS") -> 0 | W40: =SUMIFS('Finance Tracker'!O:O,'Finance Tracker'!N:N,">="&DATE(2025,1,1),'Finance Tracker'!N:N,"<="&DATE(2025,12,31),'Finance Tracker'!F:F,"C&I-BESS") +SUMIFS('Finance Tracker'!S:S,'Finance Tracker'!R:R,">="&DATE(2025,1,1),'Finance Tracker'!R:R,"<="&DATE(2025,12,31),'Finance Tracker'!F:F,"C&I-BESS") +SUMIFS('Finance Tracker'!W:W,'Finance Tracker'!V:V,">="&DATE(2025,1,1),'Finance Tracker'!V:V,"<="&DATE(2025,12,31),'Finance Tracker'!F:F,"C&I-BESS") +SUMIFS('Finance Tracker'!AA:AA,'Finance Tracker'!Z:Z,">="&DATE(2025,1,1),'Finance Tracker'!Z:Z,"<="&DATE(2025,12,31),'Finance Tracker'!F:F,"C&I-BESS") +SUMIFS('Finance Tracker'!AD:AD,'Finance Tracker'!AE:AE,">="&DATE(2025,1,1),'Finance Tracker'!AE:AE,"<="&DATE(2025,12,31),'Finance Tracker'!F:F,"C&I-BESS") +SUMIFS('Finance Tracker'!AI:AI,'Finance Tracker'!AH:AH,">="&DATE(2025,1,1),'Finance Tracker'!AH:AH,"<="&DATE(2025,12,31),'Finance Tracker'!F:F,"C&I-BESS") -> 0 | X40: =SUMIFS('Finance Tracker'!O:O,'Finance Tracker'!N:N,">="&DATE(2026,1,1),'Finance Tracker'!N:N,"<="&DATE(2026,12,31),'Finance Tracker'!F:F,"C&I-BESS") +SUMIFS('Finance Tracker'!S:S,'Finance Tracker'!R:R,">="&DATE(2026,1,1),'Finance Tracker'!R:R,"<="&DATE(2026,12,31),'Finance Tracker'!F:F,"C&I-BESS") +SUMIFS('Finance Tracker'!W:W,'Finance Tracker'!V:V,">="&DATE(2026,1,1),'Finance Tracker'!V:V,"<="&DATE(2026,12,31),'Finance Tracker'!F:F,"C&I-BESS") +SUMIFS('Finance Tracker'!AA:AA,'Finance Tracker'!Z:Z,">="&DATE(2026,1,1),'Finance Tracker'!Z:Z,"<="&DATE(2026,12,31),'Finance Tracker'!F:F,"C&I-BESS") +SUMIFS('Finance Tracker'!AD:AD,'Finance Tracker'!AE:AE,">="&DATE(2026,1,1),'Finance Tracker'!AE:AE,"<="&DATE(2026,12,31),'Finance Tracker'!F:F,"C&I-BESS") +SUMIFS('Finance Tracker'!AI:AI,'Finance Tracker'!AH:AH,">="&DATE(2026,1,1),'Finance Tracker'!AH:AH,"<="&DATE(2026,12,31),'Finance Tracker'!F:F,"C&I-BESS") -> 0 | Z40: =COUNTIF(Table1[Category],"C&I-BESS") -> 0 | AA40: =COUNTIFS(Table1[Category],"C&I-BESS",Table1[Closed Date],">="&DATE(2023,1,1),Table1[Closed Date],"<="&DATE(2023,12,31)) -> 0 | AB40: =COUNTIFS(Table1[Category],"C&I-BESS",Table1[Closed Date],">="&DATE(2024,1,1),Table1[Closed Date],"<="&DATE(2024,12,31)) -> 0 | AC40: =COUNTIFS(Table1[Category],"C&I-BESS",Table1[Closed Date],">="&DATE(2025,1,1),Table1[Closed Date],"<="&DATE(2025,12,31)) -> 0 | AD40: =COUNTIFS(Table1[Scheme],"C&I-BESS",Table1[Sales PIC],">="&DATE(2026,1,1),Table1[Sales PIC],"<="&DATE(2026,12,31)) -> 0
A41: EV Chargers | B41: =SUMIFS(Table1[EV Charger Capacity],Table1[Category],"EV Charger") -> 1786 | C41: =SUMIFS(Table1[EV Charger Capacity],Table1[Category],"EV Charger",Table1[Closed Date],">="&DATE(2023,1,1),Table1[Closed Date],"<="&DATE(2023,12,31)) -> 100 | D41: =SUMIFS(Table1[EV Charger Capacity],Table1[Category],"EV Charger",Table1[Closed Date],">="&DATE(2024,1,1),Table1[Closed Date],"<="&DATE(2024,12,31)) -> 789 | E41: =SUMIFS(Table1[EV Charger Capacity],Table1[Category],"EV Charger",Table1[Closed Date],">="&DATE(2025,1,1),Table1[Closed Date],"<="&DATE(2025,12,31)) -> 897 | F41: =SUMIFS(Table1[EV Charger Capacity],Table1[Category],"EV Charger",Table1[Closed Date],">="&DATE(2026,1,1),Table1[Closed Date],"<="&DATE(2026,12,31)) -> 0 | H41: =SUMIFS(Table1[Project Value (RM)],Table1[Category],"EV Charger") -> 1430963 | I41: =SUMIFS(Table1[Project Value (RM)],Table1[Category],"EV Charger",Table1[Closed Date],">="&DATE(2023,1,1),Table1[Closed Date],"<="&DATE(2023,12,31)) -> 93380 | J41: =SUMIFS(Table1[Project Value (RM)],Table1[Category],"EV Charger",Table1[Closed Date],">="&DATE(2024,1,1),Table1[Closed Date],"<="&DATE(2024,12,31)) -> 355363 | K41: =SUMIFS(Table1[Project Value (RM)],Table1[Category],"EV Charger",Table1[Closed Date],">="&DATE(2025,1,1),Table1[Closed Date],"<="&DATE(2025,12,31)) -> 982220 | L41: =SUMIFS(Table1[Project Value (RM)],Table1[Category],"EV Charger",Table1[Closed Date],">="&DATE(2026,1,1),Table1[Closed Date],"<="&DATE(2026,12,31)) -> 0 | N41: =SUM(O41:R41) -> 957823 | O41: =SUMIFS('Finance Tracker'!M:M,'Finance Tracker'!L:L,">="&DATE(2023,1,1),'Finance Tracker'!L:L,"<="&DATE(2023,12,31),'Finance Tracker'!F:F,"EV Charger") +SUMIFS('Finance Tracker'!Q:Q,'Finance Tracker'!P:P,">="&DATE(2023,1,1),'Finance Tracker'!P:P,"<="&DATE(2023,12,31),'Finance Tracker'!F:F,"EV Charger") +SUMIFS('Finance Tracker'!U:U,'Finance Tracker'!T:T,">="&DATE(2023,1,1),'Finance Tracker'!T:T,"<="&DATE(2023,12,31),'Finance Tracker'!F:F,"EV Charger") +SUMIFS('Finance Tracker'!Y:Y,'Finance Tracker'!X:X,">="&DATE(2023,1,1),'Finance Tracker'!X:X,"<="&DATE(2023,12,31),'Finance Tracker'!F:F,"EV Charger") +SUMIFS('Finance Tracker'!AC:AC,'Finance Tracker'!AB:AB,">="&DATE(2023,1,1),'Finance Tracker'!AB:AB,"<="&DATE(2023,12,31),'Finance Tracker'!F:F,"EV Charger") +SUMIFS('Finance Tracker'!AG:AG,'Finance Tracker'!AF:AF,">="&DATE(2023,1,1),'Finance Tracker'!AF:AF,"<="&DATE(2023,12,31),'Finance Tracker'!F:F,"EV Charger") -> 46690 | P41: =SUMIFS('Finance Tracker'!M:M,'Finance Tracker'!L:L,">="&DATE(2024,1,1),'Finance Tracker'!L:L,"<="&DATE(2024,12,31),'Finance Tracker'!F:F,"EV Charger") +SUMIFS('Finance Tracker'!Q:Q,'Finance Tracker'!P:P,">="&DATE(2024,1,1),'Finance Tracker'!P:P,"<="&DATE(2024,12,31),'Finance Tracker'!F:F,"EV Charger") +SUMIFS('Finance Tracker'!U:U,'Finance Tracker'!T:T,">="&DATE(2024,1,1),'Finance Tracker'!T:T,"<="&DATE(2024,12,31),'Finance Tracker'!F:F,"EV Charger") +SUMIFS('Finance Tracker'!Y:Y,'Finance Tracker'!X:X,">="&DATE(2024,1,1),'Finance Tracker'!X:X,"<="&DATE(2024,12,31),'Finance Tracker'!F:F,"EV Charger") +SUMIFS('Finance Tracker'!AC:AC,'Finance Tracker'!AB:AB,">="&DATE(2024,1,1),'Finance Tracker'!AB:AB,"<="&DATE(2024,12,31),'Finance Tracker'!F:F,"EV Charger") +SUMIFS('Finance Tracker'!AG:AG,'Finance Tracker'!AF:AF,">="&DATE(2024,1,1),'Finance Tracker'!AF:AF,"<="&DATE(2024,12,31),'Finance Tracker'!F:F,"EV Charger") -> 342903 | Q41: =SUMIFS('Finance Tracker'!M:M,'Finance Tracker'!L:L,">="&DATE(2025,1,1),'Finance Tracker'!L:L,"<="&DATE(2025,12,31),'Finance Tracker'!F:F,"EV Charger") +SUMIFS('Finance Tracker'!Q:Q,'Finance Tracker'!P:P,">="&DATE(2025,1,1),'Finance Tracker'!P:P,"<="&DATE(2025,12,31),'Finance Tracker'!F:F,"EV Charger") +SUMIFS('Finance Tracker'!U:U,'Finance Tracker'!T:T,">="&DATE(2025,1,1),'Finance Tracker'!T:T,"<="&DATE(2025,12,31),'Finance Tracker'!F:F,"EV Charger") +SUMIFS('Finance Tracker'!Y:Y,'Finance Tracker'!X:X,">="&DATE(2025,1,1),'Finance Tracker'!X:X,"<="&DATE(2025,12,31),'Finance Tracker'!F:F,"EV Charger") +SUMIFS('Finance Tracker'!AC:AC,'Finance Tracker'!AB:AB,">="&DATE(2025,1,1),'Finance Tracker'!AB:AB,"<="&DATE(2025,12,31),'Finance Tracker'!F:F,"EV Charger") +SUMIFS('Finance Tracker'!AG:AG,'Finance Tracker'!AF:AF,">="&DATE(2025,1,1),'Finance Tracker'!AF:AF,"<="&DATE(2025,12,31),'Finance Tracker'!F:F,"EV Charger") -> 568230 | R41: =SUMIFS('Finance Tracker'!M:M,'Finance Tracker'!L:L,">="&DATE(2026,1,1),'Finance Tracker'!L:L,"<="&DATE(2026,12,31),'Finance Tracker'!F:F,"EV Charger") +SUMIFS('Finance Tracker'!Q:Q,'Finance Tracker'!P:P,">="&DATE(2026,1,1),'Finance Tracker'!P:P,"<="&DATE(2026,12,31),'Finance Tracker'!F:F,"EV Charger") +SUMIFS('Finance Tracker'!U:U,'Finance Tracker'!T:T,">="&DATE(2026,1,1),'Finance Tracker'!T:T,"<="&DATE(2026,12,31),'Finance Tracker'!F:F,"EV Charger") +SUMIFS('Finance Tracker'!Y:Y,'Finance Tracker'!X:X,">="&DATE(2026,1,1),'Finance Tracker'!X:X,"<="&DATE(2026,12,31),'Finance Tracker'!F:F,"EV Charger") +SUMIFS('Finance Tracker'!AC:AC,'Finance Tracker'!AB:AB,">="&DATE(2026,1,1),'Finance Tracker'!AB:AB,"<="&DATE(2026,12,31),'Finance Tracker'!F:F,"EV Charger") +SUMIFS('Finance Tracker'!AG:AG,'Finance Tracker'!AF:AF,">="&DATE(2026,1,1),'Finance Tracker'!AF:AF,"<="&DATE(2026,12,31),'Finance Tracker'!F:F,"EV Charger") -> 0 | T41: =SUM(U41:X41) -> 735522.5 | U41: =SUMIFS('Finance Tracker'!O:O,'Finance Tracker'!N:N,">="&DATE(2023,1,1),'Finance Tracker'!N:N,"<="&DATE(2023,12,31),'Finance Tracker'!F:F,"EV Charger") +SUMIFS('Finance Tracker'!S:S,'Finance Tracker'!R:R,">="&DATE(2023,1,1),'Finance Tracker'!R:R,"<="&DATE(2023,12,31),'Finance Tracker'!F:F,"EV Charger") +SUMIFS('Finance Tracker'!W:W,'Finance Tracker'!V:V,">="&DATE(2023,1,1),'Finance Tracker'!V:V,"<="&DATE(2023,12,31),'Finance Tracker'!F:F,"EV Charger") +SUMIFS('Finance Tracker'!AA:AA,'Finance Tracker'!Z:Z,">="&DATE(2023,1,1),'Finance Tracker'!Z:Z,"<="&DATE(2023,12,31),'Finance Tracker'!F:F,"EV Charger") +SUMIFS('Finance Tracker'!AD:AD,'Finance Tracker'!AE:AE,">="&DATE(2023,1,1),'Finance Tracker'!AE:AE,"<="&DATE(2023,12,31),'Finance Tracker'!F:F,"EV Charger") +SUMIFS('Finance Tracker'!AI:AI,'Finance Tracker'!AH:AH,">="&DATE(2023,1,1),'Finance Tracker'!AH:AH,"<="&DATE(2023,12,31),'Finance Tracker'!F:F,"EV Charger") -> 46690 | V41: =SUMIFS('Finance Tracker'!O:O,'Finance Tracker'!N:N,">="&DATE(2024,1,1),'Finance Tracker'!N:N,"<="&DATE(2024,12,31),'Finance Tracker'!F:F,"EV Charger") +SUMIFS('Finance Tracker'!S:S,'Finance Tracker'!R:R,">="&DATE(2024,1,1),'Finance Tracker'!R:R,"<="&DATE(2024,12,31),'Finance Tracker'!F:F,"EV Charger") +SUMIFS('Finance Tracker'!W:W,'Finance Tracker'!V:V,">="&DATE(2024,1,1),'Finance Tracker'!V:V,"<="&DATE(2024,12,31),'Finance Tracker'!F:F,"EV Charger") +SUMIFS('Finance Tracker'!AA:AA,'Finance Tracker'!Z:Z,">="&DATE(2024,1,1),'Finance Tracker'!Z:Z,"<="&DATE(2024,12,31),'Finance Tracker'!F:F,"EV Charger") +SUMIFS('Finance Tracker'!AD:AD,'Finance Tracker'!AE:AE,">="&DATE(2024,1,1),'Finance Tracker'!AE:AE,"<="&DATE(2024,12,31),'Finance Tracker'!F:F,"EV Charger") +SUMIFS('Finance Tracker'!AI:AI,'Finance Tracker'!AH:AH,">="&DATE(2024,1,1),'Finance Tracker'!AH:AH,"<="&DATE(2024,12,31),'Finance Tracker'!F:F,"EV Charger") -> 321025 | W41: =SUMIFS('Finance Tracker'!O:O,'Finance Tracker'!N:N,">="&DATE(2025,1,1),'Finance Tracker'!N:N,"<="&DATE(2025,12,31),'Finance Tracker'!F:F,"EV Charger") +SUMIFS('Finance Tracker'!S:S,'Finance Tracker'!R:R,">="&DATE(2025,1,1),'Finance Tracker'!R:R,"<="&DATE(2025,12,31),'Finance Tracker'!F:F,"EV Charger") +SUMIFS('Finance Tracker'!W:W,'Finance Tracker'!V:V,">="&DATE(2025,1,1),'Finance Tracker'!V:V,"<="&DATE(2025,12,31),'Finance Tracker'!F:F,"EV Charger") +SUMIFS('Finance Tracker'!AA:AA,'Finance Tracker'!Z:Z,">="&DATE(2025,1,1),'Finance Tracker'!Z:Z,"<="&DATE(2025,12,31),'Finance Tracker'!F:F,"EV Charger") +SUMIFS('Finance Tracker'!AD:AD,'Finance Tracker'!AE:AE,">="&DATE(2025,1,1),'Finance Tracker'!AE:AE,"<="&DATE(2025,12,31),'Finance Tracker'!F:F,"EV Charger") +SUMIFS('Finance Tracker'!AI:AI,'Finance Tracker'!AH:AH,">="&DATE(2025,1,1),'Finance Tracker'!AH:AH,"<="&DATE(2025,12,31),'Finance Tracker'!F:F,"EV Charger") -> 367807.5 | X41: =SUMIFS('Finance Tracker'!O:O,'Finance Tracker'!N:N,">="&DATE(2026,1,1),'Finance Tracker'!N:N,"<="&DATE(2026,12,31),'Finance Tracker'!F:F,"EV Charger") +SUMIFS('Finance Tracker'!S:S,'Finance Tracker'!R:R,">="&DATE(2026,1,1),'Finance Tracker'!R:R,"<="&DATE(2026,12,31),'Finance Tracker'!F:F,"EV Charger") +SUMIFS('Finance Tracker'!W:W,'Finance Tracker'!V:V,">="&DATE(2026,1,1),'Finance Tracker'!V:V,"<="&DATE(2026,12,31),'Finance Tracker'!F:F,"EV Charger") +SUMIFS('Finance Tracker'!AA:AA,'Finance Tracker'!Z:Z,">="&DATE(2026,1,1),'Finance Tracker'!Z:Z,"<="&DATE(2026,12,31),'Finance Tracker'!F:F,"EV Charger") +SUMIFS('Finance Tracker'!AD:AD,'Finance Tracker'!AE:AE,">="&DATE(2026,1,1),'Finance Tracker'!AE:AE,"<="&DATE(2026,12,31),'Finance Tracker'!F:F,"EV Charger") +SUMIFS('Finance Tracker'!AI:AI,'Finance Tracker'!AH:AH,">="&DATE(2026,1,1),'Finance Tracker'!AH:AH,"<="&DATE(2026,12,31),'Finance Tracker'!F:F,"EV Charger") -> 0 | Z41: =COUNTIF(Table1[Category],"EV Charger") -> 18 | AA41: =COUNTIFS(Table1[Category],"EV Charger",Table1[Closed Date],">="&DATE(2023,1,1),Table1[Closed Date],"<="&DATE(2023,12,31)) -> 1 | AB41: =COUNTIFS(Table1[Category],"EV Charger",Table1[Closed Date],">="&DATE(2024,1,1),Table1[Closed Date],"<="&DATE(2024,12,31)) -> 7 | AC41: =COUNTIFS(Table1[Category],"EV Charger",Table1[Closed Date],">="&DATE(2025,1,1),Table1[Closed Date],"<="&DATE(2025,12,31)) -> 10 | AD41: =COUNTIFS(Table1[Category],"EV Charger",Table1[Closed Date],">="&DATE(2026,1,1),Table1[Closed Date],"<="&DATE(2026,12,31)) -> 0
A42: Total | H42: =SUM(H37:H41) -> 19651384 | I42: =SUM(I37:I41) -> 2117905 | J42: =SUM(J37:J41) -> 9658840.2 | K42: =SUM(K37:K41) -> 7874639 | L42: =SUM(L37:L41) -> 0 | N42: =SUM(N37:N41) -> 17426694 | O42: =SUM(O37:O41) -> 1136750 | P42: =SUM(P37:P41) -> 7171388.2 | Q42: =SUM(Q37:Q41) -> 9118555.8 | R42: =SUM(R37:R41) -> 0 | T42: =SUM(T37:T41) -> 15462552 | U42: =SUM(U37:U41) -> 1059150 | V42: =SUM(V37:V41) -> 6723226.2 | W42: =SUM(W37:W41) -> 7680175.3 | X42: =SUM(X37:X41) -> 0 | Z42: =SUM(Z37:Z41) -> 365 | AA42: =SUM(AA37:AA41) -> 28 | AB42: =SUM(AB37:AB41) -> 168 | AC42: =SUM(AC37:AC41) -> 169 | AD42: =SUM(AD37:AD41) -> 0
B45: System Capacity (kWp) | H45: System Capacity (kWp) | N45: Project Value (RM) | T45: Project Value (RM)
B46: Residential | H46: C&I | N46: Residential | T46: C&I
B47: Total | C47: 2023 | D47: 2024 | E47: 2025 | F47: 2026 | H47: Total | I47: 2023 | J47: 2024 | K47: 2025 | L47: 2026 | N47: Total | O47: 2023 | P47: 2024 | Q47: 2025 | R47: 2026 | T47: Total | U47: 2023 | V47: 2024 | W47: 2025 | X47: 2026
A48: NEM | B48: =SUMIFS(Table1[PV System Capacity (kWp)],Table1[Scheme],"NEM",Table1[Category],"*R*") -> 3417.375 | C48: =SUMIFS(Table1[PV System Capacity (kWp)],Table1[Scheme],"NEM",Table1[Category],"*R*",Table1[Closed Date],">="&DATE(2023,1,1),Table1[Closed Date],"<="&DATE(2023,12,31)) -> 220.15 | D48: =SUMIFS(Table1[PV System Capacity (kWp)],Table1[Scheme],"NEM",Table1[Category],"*R*",Table1[Closed Date],">="&DATE(2024,1,1),Table1[Closed Date],"<="&DATE(2024,12,31)) -> 1637.165 | E48: =SUMIFS(Table1[PV System Capacity (kWp)],Table1[Scheme],"NEM",Table1[Category],"*R*",Table1[Closed Date],">="&DATE(2025,1,1),Table1[Closed Date],"<="&DATE(2025,12,31)) -> 1560.06 | F48: =SUMIFS(Table1[PV System Capacity (kWp)],Table1[Scheme],"NEM",Table1[Category],"*R*",Table1[Closed Date],">="&DATE(2026,1,1),Table1[Closed Date],"<="&DATE(2026,12,31)) -> 0 | H48: =SUMIFS(Table1[PV System Capacity (kWp)],Table1[Scheme],"NEM",Table1[Category],"*C&I*") -> 3286.685 | I48: =SUMIFS(Table1[PV System Capacity (kWp)],Table1[Scheme],"NEM",Table1[Category],"*C&I*",Table1[Closed Date],">="&DATE(2023,1,1),Table1[Closed Date],"<="&DATE(2023,12,31)) -> 428.695 | J48: =SUMIFS(Table1[PV System Capacity (kWp)],Table1[Scheme],"NEM",Table1[Category],"*C&I*",Table1[Closed Date],">="&DATE(2024,1,1),Table1[Closed Date],"<="&DATE(2024,12,31)) -> 1675 | K48: =SUMIFS(Table1[PV System Capacity (kWp)],Table1[Scheme],"NEM",Table1[Category],"*C&I*",Table1[Closed Date],">="&DATE(2025,1,1),Table1[Closed Date],"<="&DATE(2025,12,31)) -> 1182.99 | L48: =SUMIFS(Table1[PV System Capacity (kWp)],Table1[Scheme],"NEM",Table1[Category],"*C&I*",Table1[Closed Date],">="&DATE(2026,1,1),Table1[Closed Date],"<="&DATE(2026,12,31)) -> 0 | N48: =SUMIFS(Table1[Project Value (RM)],Table1[Scheme],"NEM",Table1[Category],"*R*") -> 9838567.6 | O48: =SUMIFS(Table1[Project Value (RM)],Table1[Scheme],"NEM",Table1[Category],"*R*",Table1[Closed Date],">="&DATE(2023,1,1),Table1[Closed Date],"<="&DATE(2023,12,31)) -> 751725 | P48: =SUMIFS(Table1[Project Value (RM)],Table1[Scheme],"NEM",Table1[Category],"*R*",Table1[Closed Date],">="&DATE(2024,1,1),Table1[Closed Date],"<="&DATE(2024,12,31)) -> 5036797.2 | Q48: =SUMIFS(Table1[Project Value (RM)],Table1[Scheme],"NEM",Table1[Category],"*R*",Table1[Closed Date],">="&DATE(2025,1,1),Table1[Closed Date],"<="&DATE(2025,12,31)) -> 4050045.4 | R48: =SUMIFS(Table1[Project Value (RM)],Table1[Scheme],"NEM",Table1[Category],"*R*",Table1[Closed Date],">="&DATE(2026,1,1),Table1[Closed Date],"<="&DATE(2026,12,31)) -> 0 | T48: =SUMIFS(Table1[Project Value (RM)],Table1[Scheme],"NEM",Table1[Category],"*C&I*") -> 6721700 | U48: =SUMIFS(Table1[Project Value (RM)],Table1[Scheme],"NEM",Table1[Category],"*C&I*",Table1[Closed Date],">="&DATE(2023,1,1),Table1[Closed Date],"<="&DATE(2023,12,31)) -> 521800 | V48: =SUMIFS(Table1[Project Value (RM)],Table1[Scheme],"NEM",Table1[Category],"*C&I*",Table1[Closed Date],">="&DATE(2024,1,1),Table1[Closed Date],"<="&DATE(2024,12,31)) -> 3866600 | W48: =SUMIFS(Table1[Project Value (RM)],Table1[Scheme],"NEM",Table1[Category],"*C&I*",Table1[Closed Date],">="&DATE(2025,1,1),Table1[Closed Date],"<="&DATE(2025,12,31)) -> 2333300 | X48: =SUMIFS(Table1[Project Value (RM)],Table1[Scheme],"NEM",Table1[Category],"*C&I*",Table1[Closed Date],">="&DATE(2026,1,1),Table1[Closed Date],"<="&DATE(2026,12,31)) -> 0
A49: SELCO | B49: =SUMIFS(Table1[PV System Capacity (kWp)],Table1[Scheme],"SELCO",Table1[Category],"*R*") -> 217.77 | C49: =SUMIFS(Table1[PV System Capacity (kWp)],Table1[Scheme],"SELCO",Table1[Category],"*R*",Table1[Closed Date],">="&DATE(2023,1,1),Table1[Closed Date],"<="&DATE(2023,12,31)) -> 93.15 | D49: =SUMIFS(Table1[PV System Capacity (kWp)],Table1[Scheme],"SELCO",Table1[Category],"*R*",Table1[Closed Date],">="&DATE(2024,1,1),Table1[Closed Date],"<="&DATE(2024,12,31)) -> 0 | E49: =SUMIFS(Table1[PV System Capacity (kWp)],Table1[Scheme],"SELCO",Table1[Category],"*R*",Table1[Closed Date],">="&DATE(2025,1,1),Table1[Closed Date],"<="&DATE(2025,12,31)) -> 124.62 | F49: =SUMIFS(Table1[PV System Capacity (kWp)],Table1[Scheme],"SELCO",Table1[Category],"*R*",Table1[Closed Date],">="&DATE(2026,1,1),Table1[Closed Date],"<="&DATE(2026,12,31)) -> 0 | H49: =SUMIFS(Table1[PV System Capacity (kWp)],Table1[Scheme],"SELCO",Table1[Category],"*C&I*") -> 431.325 | I49: =SUMIFS(Table1[PV System Capacity (kWp)],Table1[Scheme],"SELCO",Table1[Category],"*C&I*",Table1[Closed Date],">="&DATE(2023,1,1),Table1[Closed Date],"<="&DATE(2023,12,31)) -> 0 | J49: =SUMIFS(Table1[PV System Capacity (kWp)],Table1[Scheme],"SELCO",Table1[Category],"*C&I*",Table1[Closed Date],">="&DATE(2024,1,1),Table1[Closed Date],"<="&DATE(2024,12,31)) -> 413.345 | K49: =SUMIFS(Table1[PV System Capacity (kWp)],Table1[Scheme],"SELCO",Table1[Category],"*C&I*",Table1[Closed Date],">="&DATE(2025,1,1),Table1[Closed Date],"<="&DATE(2025,12,31)) -> 17.98 | L49: =SUMIFS(Table1[PV System Capacity (kWp)],Table1[Scheme],"SELCO",Table1[Category],"*C&I*",Table1[Closed Date],">="&DATE(2026,1,1),Table1[Closed Date],"<="&DATE(2026,12,31)) -> 0 | N49: =SUMIFS(Table1[Project Value (RM)],Table1[Scheme],"SELCO",Table1[Category],"*R*") -> 1196300 | O49: =SUMIFS(Table1[Project Value (RM)],Table1[Scheme],"SELCO",Table1[Category],"*R*",Table1[Closed Date],">="&DATE(2023,1,1),Table1[Closed Date],"<="&DATE(2023,12,31)) -> 751000 | P49: =SUMIFS(Table1[Project Value (RM)],Table1[Scheme],"SELCO",Table1[Category],"*R*",Table1[Closed Date],">="&DATE(2024,1,1),Table1[Closed Date],"<="&DATE(2024,12,31)) -> 0 | Q49: =SUMIFS(Table1[Project Value (RM)],Table1[Scheme],"SELCO",Table1[Category],"*R*",Table1[Closed Date],">="&DATE(2025,1,1),Table1[Closed Date],"<="&DATE(2025,12,31)) -> 445300 | R49: =SUMIFS(Table1[Project Value (RM)],Table1[Scheme],"SELCO",Table1[Category],"*R*",Table1[Closed Date],">="&DATE(2026,1,1),Table1[Closed Date],"<="&DATE(2026,12,31)) -> 0 | T49: =SUMIFS(Table1[Project Value (RM)],Table1[Scheme],"SELCO",Table1[Category],"*C&I*") -> 463853.58 | U49: =SUMIFS(Table1[Project Value (RM)],Table1[Scheme],"SELCO",Table1[Category],"*C&I*",Table1[Closed Date],">="&DATE(2023,1,1),Table1[Closed Date],"<="&DATE(2023,12,31)) -> 0 | V49: =SUMIFS(Table1[Project Value (RM)],Table1[Scheme],"SELCO",Table1[Category],"*C&I*",Table1[Closed Date],">="&DATE(2024,1,1),Table1[Closed Date],"<="&DATE(2024,12,31)) -> 400080 | W49: =SUMIFS(Table1[Project Value (RM)],Table1[Scheme],"SELCO",Table1[Category],"*C&I*",Table1[Closed Date],">="&DATE(2025,1,1),Table1[Closed Date],"<="&DATE(2025,12,31)) -> 63773.58 | X49: =SUMIFS(Table1[Project Value (RM)],Table1[Scheme],"SELCO",Table1[Category],"*C&I*",Table1[Closed Date],">="&DATE(2026,1,1),Table1[Closed Date],"<="&DATE(2026,12,31)) -> 0
A50: ATAP | B50: =SUMIFS(Table1[PV System Capacity (kWp)],Table1[Scheme],"ATAP",Table1[Category],"*R*") -> 0 | C50: =SUMIFS(Table1[PV System Capacity (kWp)],Table1[Scheme],"ATAP",Table1[Category],"*R*",Table1[Closed Date],">="&DATE(2023,1,1),Table1[Closed Date],"<="&DATE(2023,12,31)) -> 0 | D50: =SUMIFS(Table1[PV System Capacity (kWp)],Table1[Scheme],"ATAP",Table1[Category],"*R*",Table1[Closed Date],">="&DATE(2024,1,1),Table1[Closed Date],"<="&DATE(2024,12,31)) -> 0 | E50: =SUMIFS(Table1[PV System Capacity (kWp)],Table1[Scheme],"ATAP",Table1[Category],"*R*",Table1[Closed Date],">="&DATE(2025,1,1),Table1[Closed Date],"<="&DATE(2025,12,31)) -> 0 | F50: =SUMIFS(Table1[PV System Capacity (kWp)],Table1[Scheme],"SATAP",Table1[Category],"*R*",Table1[Closed Date],">="&DATE(2026,1,1),Table1[Closed Date],"<="&DATE(2026,12,31)) -> 0 | H50: =SUMIFS(Table1[PV System Capacity (kWp)],Table1[Scheme],"ATAP",Table1[Category],"*C&I*") -> 0 | I50: =SUMIFS(Table1[PV System Capacity (kWp)],Table1[Scheme],"ATAP",Table1[Category],"*C&I*",Table1[Closed Date],">="&DATE(2023,1,1),Table1[Closed Date],"<="&DATE(2023,12,31)) -> 0 | J50: =SUMIFS(Table1[PV System Capacity (kWp)],Table1[Scheme],"ATAP",Table1[Category],"*C&I*",Table1[Closed Date],">="&DATE(2024,1,1),Table1[Closed Date],"<="&DATE(2024,12,31)) -> 0 | K50: =SUMIFS(Table1[PV System Capacity (kWp)],Table1[Scheme],"ATAP",Table1[Category],"*C&I*",Table1[Closed Date],">="&DATE(2025,1,1),Table1[Closed Date],"<="&DATE(2025,12,31)) -> 0 | L50: =SUMIFS(Table1[PV System Capacity (kWp)],Table1[Scheme],"ATAP",Table1[Category],"*C&I*",Table1[Closed Date],">="&DATE(2026,1,1),Table1[Closed Date],"<="&DATE(2026,12,31)) -> 0 | N50: =SUMIFS(Table1[Project Value (RM)],Table1[Scheme],"ATAP",Table1[Category],"*R*") -> 0 | O50: =SUMIFS(Table1[Project Value (RM)],Table1[Scheme],"ATAP",Table1[Category],"*R*",Table1[Closed Date],">="&DATE(2023,1,1),Table1[Closed Date],"<="&DATE(2023,12,31)) -> 0 | P50: =SUMIFS(Table1[Project Value (RM)],Table1[Scheme],"ATAP",Table1[Category],"*R*",Table1[Closed Date],">="&DATE(2024,1,1),Table1[Closed Date],"<="&DATE(2024,12,31)) -> 0 | Q50: =SUMIFS(Table1[Project Value (RM)],Table1[Scheme],"ATAP",Table1[Category],"*R*",Table1[Closed Date],">="&DATE(2025,1,1),Table1[Closed Date],"<="&DATE(2025,12,31)) -> 0 | R50: =SUMIFS(Table1[Project Value (RM)],Table1[Scheme],"ATAP",Table1[Category],"*R*",Table1[Closed Date],">="&DATE(2026,1,1),Table1[Closed Date],"<="&DATE(2026,12,31)) -> 0 | T50: =SUMIFS(Table1[Project Value (RM)],Table1[Scheme],"ATAP",Table1[Category],"*C&I*") -> 0 | U50: =SUMIFS(Table1[Project Value (RM)],Table1[Scheme],"ATAP",Table1[Category],"*C&I*",Table1[Closed Date],">="&DATE(2023,1,1),Table1[Closed Date],"<="&DATE(2023,12,31)) -> 0 | V50: =SUMIFS(Table1[Project Value (RM)],Table1[Scheme],"ATAP",Table1[Category],"*C&I*",Table1[Closed Date],">="&DATE(2024,1,1),Table1[Closed Date],"<="&DATE(2024,12,31)) -> 0 | W50: =SUMIFS(Table1[Project Value (RM)],Table1[Scheme],"TAP",Table1[Category],"*C&I*",Table1[Closed Date],">="&DATE(2025,1,1),Table1[Closed Date],"<="&DATE(2025,12,31)) -> 0 | X50: =SUMIFS(Table1[Project Value (RM)],Table1[Scheme],"ATAP",Table1[Category],"*C&I*",Table1[Closed Date],">="&DATE(2026,1,1),Table1[Closed Date],"<="&DATE(2026,12,31)) -> 0
B81: System Capacity (kWp) | H81: Project Value (RM)
B82: Total | H82: Total
B83: Total | C83: 2023 | D83: 2024 | E83: 2025 | F83: 2026 | H83: Total | I83: 2023 | J83: 2024 | K83: 2025 | L83: 2026
A84: Tham | B84: =SUMIF(Table1[Sales PIC],A84,Table1[PV System Capacity (kWp)]) -> 4469.92 | C84: =SUMIFS(Table1[PV System Capacity (kWp)],Table1[Sales PIC],A84,Table1[Closed Date],">="&DATE(2023,1,1),Table1[Closed Date],"<="&DATE(2023,12,31)) -> 5.75 | D84: =SUMIFS(Table1[PV System Capacity (kWp)],Table1[Sales PIC],A84,Table1[Closed Date],">="&DATE(2024,1,1),Table1[Closed Date],"<="&DATE(2024,12,31)) -> 2808.42 | E84: =SUMIFS(Table1[PV System Capacity (kWp)],Table1[Sales PIC],A84,Table1[Closed Date],">="&DATE(2025,1,1),Table1[Closed Date],"<="&DATE(2025,12,31)) -> 1648.73 | F84: - | H84: =SUMIF(Table1[Sales PIC],A84,Table1[Project Value (RM)]) -> 11010153 | I84: =SUMIFS(Table1[Project Value (RM)],Table1[Sales PIC],A84,Table1[Closed Date],">="&DATE(2023,1,1),Table1[Closed Date],"<="&DATE(2023,12,31)) -> 22000 | J84: =SUMIFS(Table1[Project Value (RM)],Table1[Sales PIC],A84,Table1[Closed Date],">="&DATE(2024,1,1),Table1[Closed Date],"<="&DATE(2024,12,31)) -> 7289133.2 | K84: =SUMIFS(Table1[Project Value (RM)],Table1[Sales PIC],A84,Table1[Closed Date],">="&DATE(2025,1,1),Table1[Closed Date],"<="&DATE(2025,12,31)) -> 3673920 | L84: -
A85: Chean Bang | B85: =SUMIF(Table1[Sales PIC],A85,Table1[PV System Capacity (kWp)]) -> 686.555 | C85: =SUMIFS(Table1[PV System Capacity (kWp)],Table1[Sales PIC],A85,Table1[Closed Date],">="&DATE(2023,1,1),Table1[Closed Date],"<="&DATE(2023,12,31)) -> 128.85 | D85: =SUMIFS(Table1[PV System Capacity (kWp)],Table1[Sales PIC],A85,Table1[Closed Date],">="&DATE(2024,1,1),Table1[Closed Date],"<="&DATE(2024,12,31)) -> 333.785 | E85: =SUMIFS(Table1[PV System Capacity (kWp)],Table1[Sales PIC],A85,Table1[Closed Date],">="&DATE(2025,1,1),Table1[Closed Date],"<="&DATE(2025,12,31)) -> 223.92 | F85: =SUMIFS(Table1[PV System Capacity (kWp)],Table1[Sales PIC],A85,Table1[Closed Date],">="&DATE(2026,1,1),Table1[Closed Date],"<="&DATE(2026,12,31)) -> 0 | H85: =SUMIF(Table1[Sales PIC],A85,Table1[Project Value (RM)]) -> 2335898 | I85: =SUMIFS(Table1[Project Value (RM)],Table1[Sales PIC],A85,Table1[Closed Date],">="&DATE(2023,1,1),Table1[Closed Date],"<="&DATE(2023,12,31)) -> 461700 | J85: =SUMIFS(Table1[Project Value (RM)],Table1[Sales PIC],A85,Table1[Closed Date],">="&DATE(2024,1,1),Table1[Closed Date],"<="&DATE(2024,12,31)) -> 1094898 | K85: =SUMIFS(Table1[Project Value (RM)],Table1[Sales PIC],A85,Table1[Closed Date],">="&DATE(2025,1,1),Table1[Closed Date],"<="&DATE(2025,12,31)) -> 779300 | L85: =SUMIFS(Table1[Project Value (RM)],Table1[Sales PIC],A85,Table1[Closed Date],">="&DATE(2026,1,1),Table1[Closed Date],"<="&DATE(2026,12,31)) -> 0
A86: Simon | B86: =SUMIF(Table1[Sales PIC],A86,Table1[PV System Capacity (kWp)]) -> 1185.055 | C86: =SUMIFS(Table1[PV System Capacity (kWp)],Table1[Sales PIC],A86,Table1[Closed Date],">="&DATE(2023,1,1),Table1[Closed Date],"<="&DATE(2023,12,31)) -> 607.395 | D86: =SUMIFS(Table1[PV System Capacity (kWp)],Table1[Sales PIC],A86,Table1[Closed Date],">="&DATE(2024,1,1),Table1[Closed Date],"<="&DATE(2024,12,31)) -> 429.69 | E86: =SUMIFS(Table1[PV System Capacity (kWp)],Table1[Sales PIC],A86,Table1[Closed Date],">="&DATE(2025,1,1),Table1[Closed Date],"<="&DATE(2025,12,31)) -> 147.97 | F86: =SUMIFS(Table1[PV System Capacity (kWp)],Table1[Sales PIC],A86,Table1[Closed Date],">="&DATE(2026,1,1),Table1[Closed Date],"<="&DATE(2026,12,31)) -> 0 | H86: =SUMIF(Table1[Sales PIC],A86,Table1[Project Value (RM)]) -> 3516528 | I86: =SUMIFS(Table1[Project Value (RM)],Table1[Sales PIC],A86,Table1[Closed Date],">="&DATE(2023,1,1),Table1[Closed Date],"<="&DATE(2023,12,31)) -> 1634205 | J86: =SUMIFS(Table1[Project Value (RM)],Table1[Sales PIC],A86,Table1[Closed Date],">="&DATE(2024,1,1),Table1[Closed Date],"<="&DATE(2024,12,31)) -> 783603 | K86: =SUMIFS(Table1[Project Value (RM)],Table1[Sales PIC],A86,Table1[Closed Date],">="&DATE(2025,1,1),Table1[Closed Date],"<="&DATE(2025,12,31)) -> 1098720 | L86: =SUMIFS(Table1[Project Value (RM)],Table1[Sales PIC],A86,Table1[Closed Date],">="&DATE(2026,1,1),Table1[Closed Date],"<="&DATE(2026,12,31)) -> 0
A87: Ong | B87: =SUMIF(Table1[Sales PIC],A87,Table1[PV System Capacity (kWp)]) -> 71.53 | C87: =SUMIFS(Table1[PV System Capacity (kWp)],Table1[Sales PIC],A87,Table1[Closed Date],">="&DATE(2023,1,1),Table1[Closed Date],"<="&DATE(2023,12,31)) -> 0 | D87: =SUMIFS(Table1[PV System Capacity (kWp)],Table1[Sales PIC],A87,Table1[Closed Date],">="&DATE(2024,1,1),Table1[Closed Date],"<="&DATE(2024,12,31)) -> 13.8 | E87: =SUMIFS(Table1[PV System Capacity (kWp)],Table1[Sales PIC],A87,Table1[Closed Date],">="&DATE(2025,1,1),Table1[Closed Date],"<="&DATE(2025,12,31)) -> 57.73 | F87: =SUMIFS(Table1[PV System Capacity (kWp)],Table1[Sales PIC],A87,Table1[Closed Date],">="&DATE(2026,1,1),Table1[Closed Date],"<="&DATE(2026,12,31)) -> 0 | H87: =SUMIF(Table1[Sales PIC],A87,Table1[Project Value (RM)]) -> 273958 | I87: =SUMIFS(Table1[Project Value (RM)],Table1[Sales PIC],A87,Table1[Closed Date],">="&DATE(2023,1,1),Table1[Closed Date],"<="&DATE(2023,12,31)) -> 0 | J87: =SUMIFS(Table1[Project Value (RM)],Table1[Sales PIC],A87,Table1[Closed Date],">="&DATE(2024,1,1),Table1[Closed Date],"<="&DATE(2024,12,31)) -> 54930 | K87: =SUMIFS(Table1[Project Value (RM)],Table1[Sales PIC],A87,Table1[Closed Date],">="&DATE(2025,1,1),Table1[Closed Date],"<="&DATE(2025,12,31)) -> 219028 | L87: =SUMIFS(Table1[Project Value (RM)],Table1[Sales PIC],A87,Table1[Closed Date],">="&DATE(2026,1,1),Table1[Closed Date],"<="&DATE(2026,12,31)) -> 0
A88: Patricia | B88: =SUMIF(Table1[Sales PIC],A88,Table1[PV System Capacity (kWp)]) -> 934.89 | C88: =SUMIFS(Table1[PV System Capacity (kWp)],Table1[Sales PIC],A88,Table1[Closed Date],">="&DATE(2023,1,1),Table1[Closed Date],"<="&DATE(2023,12,31)) -> 0 | D88: =SUMIFS(Table1[PV System Capacity (kWp)],Table1[Sales PIC],A88,Table1[Closed Date],">="&DATE(2024,1,1),Table1[Closed Date],"<="&DATE(2024,12,31)) -> 120.51 | E88: =SUMIFS(Table1[PV System Capacity (kWp)],Table1[Sales PIC],A88,Table1[Closed Date],">="&DATE(2025,1,1),Table1[Closed Date],"<="&DATE(2025,12,31)) -> 807.3 | F88: =SUMIFS(Table1[PV System Capacity (kWp)],Table1[Sales PIC],A88,Table1[Closed Date],">="&DATE(2026,1,1),Table1[Closed Date],"<="&DATE(2026,12,31)) -> 0 | H88: =SUMIF(Table1[Sales PIC],A88,Table1[Project Value (RM)]) -> 2493347 | I88: =SUMIFS(Table1[Project Value (RM)],Table1[Sales PIC],A88,Table1[Closed Date],">="&DATE(2023,1,1),Table1[Closed Date],"<="&DATE(2023,12,31)) -> 0 | J88: =SUMIFS(Table1[Project Value (RM)],Table1[Sales PIC],A88,Table1[Closed Date],">="&DATE(2024,1,1),Table1[Closed Date],"<="&DATE(2024,12,31)) -> 368176 | K88: =SUMIFS(Table1[Project Value (RM)],Table1[Sales PIC],A88,Table1[Closed Date],">="&DATE(2025,1,1),Table1[Closed Date],"<="&DATE(2025,12,31)) -> 2103671 | L88: =SUMIFS(Table1[Project Value (RM)],Table1[Sales PIC],A88,Table1[Closed Date],">="&DATE(2026,1,1),Table1[Closed Date],"<="&DATE(2026,12,31)) -> 0
A89: Reeve | B89: =SUMIF(Table1[Sales PIC],A89,Table1[PV System Capacity (kWp)]) -> 0 | C89: =SUMIFS(Table1[PV System Capacity (kWp)],Table1[Sales PIC],A89,Table1[Closed Date],">="&DATE(2023,1,1),Table1[Closed Date],"<="&DATE(2023,12,31)) -> 0 | D89: =SUMIFS(Table1[PV System Capacity (kWp)],Table1[Sales PIC],A89,Table1[Closed Date],">="&DATE(2024,1,1),Table1[Closed Date],"<="&DATE(2024,12,31)) -> 0 | E89: =SUMIFS(Table1[PV System Capacity (kWp)],Table1[Sales PIC],A89,Table1[Closed Date],">="&DATE(2025,1,1),Table1[Closed Date],"<="&DATE(2025,12,31)) -> 0 | F89: =SUMIFS(Table1[PV System Capacity (kWp)],Table1[Sales PIC],A89,Table1[Closed Date],">="&DATE(2026,1,1),Table1[Closed Date],"<="&DATE(2026,12,31)) -> 0 | H89: =SUMIF(Table1[Sales PIC],A89,Table1[Project Value (RM)]) -> 0 | I89: =SUMIFS(Table1[Project Value (RM)],Table1[Sales PIC],A89,Table1[Closed Date],">="&DATE(2023,1,1),Table1[Closed Date],"<="&DATE(2023,12,31)) -> 0 | J89: =SUMIFS(Table1[Project Value (RM)],Table1[Sales PIC],A89,Table1[Closed Date],">="&DATE(2024,1,1),Table1[Closed Date],"<="&DATE(2024,12,31)) -> 0 | K89: =SUMIFS(Table1[Project Value (RM)],Table1[Sales PIC],A89,Table1[Closed Date],">="&DATE(2025,1,1),Table1[Closed Date],"<="&DATE(2025,12,31)) -> 0 | L89: =SUMIFS(Table1[Project Value (RM)],Table1[Sales PIC],A89,Table1[Closed Date],">="&DATE(2026,1,1),Table1[Closed Date],"<="&DATE(2026,12,31)) -> 0
B90: =SUMIF(Table1[Sales PIC],A90,Table1[PV System Capacity (kWp)]) -> 0 | C90: =SUMIFS(Table1[PV System Capacity (kWp)],Table1[Sales PIC],A90,Table1[Closed Date],">="&DATE(2023,1,1),Table1[Closed Date],"<="&DATE(2023,12,31)) -> 0 | D90: =SUMIFS(Table1[PV System Capacity (kWp)],Table1[Sales PIC],A90,Table1[Closed Date],">="&DATE(2024,1,1),Table1[Closed Date],"<="&DATE(2024,12,31)) -> 0 | E90: =SUMIFS(Table1[PV System Capacity (kWp)],Table1[Sales PIC],A90,Table1[Closed Date],">="&DATE(2025,1,1),Table1[Closed Date],"<="&DATE(2025,12,31)) -> 0 | F90: =SUMIFS(Table1[PV System Capacity (kWp)],Table1[Sales PIC],A90,Table1[Closed Date],">="&DATE(2026,1,1),Table1[Closed Date],"<="&DATE(2026,12,31)) -> 0 | H90: =SUMIF(Table1[Sales PIC],A90,Table1[Project Value (RM)]) -> 0 | I90: =SUMIFS(Table1[Project Value (RM)],Table1[Sales PIC],A90,Table1[Closed Date],">="&DATE(2023,1,1),Table1[Closed Date],"<="&DATE(2023,12,31)) -> 0 | J90: =SUMIFS(Table1[Project Value (RM)],Table1[Sales PIC],A90,Table1[Closed Date],">="&DATE(2024,1,1),Table1[Closed Date],"<="&DATE(2024,12,31)) -> 0 | K90: =SUMIFS(Table1[Project Value (RM)],Table1[Sales PIC],A90,Table1[Closed Date],">="&DATE(2025,1,1),Table1[Closed Date],"<="&DATE(2025,12,31)) -> 0 | L90: =SUMIFS(Table1[Project Value (RM)],Table1[Sales PIC],A90,Table1[Closed Date],">="&DATE(2026,1,1),Table1[Closed Date],"<="&DATE(2026,12,31)) -> 0
A91: Total | B91: =SUM(B84:B90) -> 7347.95 | C91: =SUM(C84:C90) -> 741.995 | D91: =SUM(D84:D90) -> 3706.205 | E91: =SUM(E84:E90) -> 2885.65 | F91: =SUM(F84:F90) -> 0 | H91: =SUM(H84:H90) -> 19629884 | I91: =SUM(I84:I90) -> 2117905 | J91: =SUM(J84:J90) -> 9590740.2 | K91: =SUM(K84:K90) -> 7874639 | L91: =SUM(L84:L90) -> 0
B94: System Capacity (kWp) | H94: System Capacity (kWp) | N94: Project Value (RM) | T94: Project Value (RM)
B95: Residential | H95: C&I | N95: Residential | T95: C&I
B96: Total | C96: 2023 | D96: 2024 | E96: 2025 | F96: 2026 | H96: Total | I96: 2023 | J96: 2024 | K96: 2025 | L96: 2026 | N96: Total | O96: 2023 | P96: 2024 | Q96: 2025 | R96: 2026 | T96: Total | U96: 2023 | V96: 2024 | W96: 2025 | X96: 2026
A97: Tham | B97: =SUMIFS(Table1[PV System Capacity (kWp)],Table1[Sales PIC],A84,Table1[Category],"*R*") -> 1805.1 | C97: =SUMIFS(Table1[PV System Capacity (kWp)],Table1[Sales PIC],A84,Table1[Category],"*R*",Table1[Closed Date],">="&DATE(2023,1,1),Table1[Closed Date],"<="&DATE(2023,12,31)) -> 5.75 | D97: =SUMIFS(Table1[PV System Capacity (kWp)],Table1[Sales PIC],A84,Table1[Category],"*R*",Table1[Closed Date],">="&DATE(2024,1,1),Table1[Closed Date],"<="&DATE(2024,12,31)) -> 1131.85 | E97: =SUMIFS(Table1[PV System Capacity (kWp)],Table1[Sales PIC],A84,Table1[Category],"*R*",Table1[Closed Date],">="&DATE(2025,1,1),Table1[Closed Date],"<="&DATE(2025,12,31)) -> 667.5 | F97: - | H97: =SUMIFS(Table1[PV System Capacity (kWp)],Table1[Sales PIC],A84,Table1[Category],"*C&I*") -> 2657.8 | I97: =SUMIFS(Table1[PV System Capacity (kWp)],Table1[Sales PIC],A84,Table1[Category],"*C&I*",Table1[Closed Date],">="&DATE(2023,1,1),Table1[Closed Date],"<="&DATE(2023,12,31)) -> 0 | J97: =SUMIFS(Table1[PV System Capacity (kWp)],Table1[Sales PIC],A84,Table1[Category],"*C&I*",Table1[Closed Date],">="&DATE(2024,1,1),Table1[Closed Date],"<="&DATE(2024,12,31)) -> 1676.57 | K97: =SUMIFS(Table1[PV System Capacity (kWp)],Table1[Sales PIC],A84,Table1[Category],"*C&I*",Table1[Closed Date],">="&DATE(2025,1,1),Table1[Closed Date],"<="&DATE(2025,12,31)) -> 981.23 | L97: - | N97: =SUMIFS(Table1[Project Value (RM)],Table1[Sales PIC],A84,Table1[Category],"*R*") -> 5183153.2 | O97: =SUMIFS(Table1[Project Value (RM)],Table1[Sales PIC],A84,Table1[Category],"*R*",Table1[Closed Date],">="&DATE(2023,1,1),Table1[Closed Date],"<="&DATE(2023,12,31)) -> 22000 | P97: =SUMIFS(Table1[Project Value (RM)],Table1[Sales PIC],A84,Table1[Category],"*R*",Table1[Closed Date],">="&DATE(2024,1,1),Table1[Closed Date],"<="&DATE(2024,12,31)) -> 3434533.2 | Q97: =SUMIFS(Table1[Project Value (RM)],Table1[Sales PIC],A84,Table1[Category],"*R*",Table1[Closed Date],">="&DATE(2025,1,1),Table1[Closed Date],"<="&DATE(2025,12,31)) -> 1726620 | R97: - | T97: =SUMIFS(Table1[Project Value (RM)],Table1[Sales PIC],A84,Table1[Category],"*C&I*") -> 5801900 | U97: =SUMIFS(Table1[Project Value (RM)],Table1[Sales PIC],A84,Table1[Category],"*C&I*",Table1[Closed Date],">="&DATE(2023,1,1),Table1[Closed Date],"<="&DATE(2023,12,31)) -> 0 | V97: =SUMIFS(Table1[Project Value (RM)],Table1[Sales PIC],A84,Table1[Category],"*C&I*",Table1[Closed Date],">="&DATE(2024,1,1),Table1[Closed Date],"<="&DATE(2024,12,31)) -> 3854600 | W97: =SUMIFS(Table1[Project Value (RM)],Table1[Sales PIC],A84,Table1[Category],"*C&I*",Table1[Closed Date],">="&DATE(2025,1,1),Table1[Closed Date],"<="&DATE(2025,12,31)) -> 1947300 | X97: -
A98: Chean Bang | B98: =SUMIFS(Table1[PV System Capacity (kWp)],Table1[Sales PIC],A85,Table1[Category],"*R*") -> 622.845 | C98: =SUMIFS(Table1[PV System Capacity (kWp)],Table1[Sales PIC],A85,Table1[Category],"*R*",Table1[Closed Date],">="&DATE(2023,1,1),Table1[Closed Date],"<="&DATE(2023,12,31)) -> 128.85 | D98: =SUMIFS(Table1[PV System Capacity (kWp)],Table1[Sales PIC],A85,Table1[Category],"*R*",Table1[Closed Date],">="&DATE(2024,1,1),Table1[Closed Date],"<="&DATE(2024,12,31)) -> 310.785 | E98: =SUMIFS(Table1[PV System Capacity (kWp)],Table1[Sales PIC],A85,Table1[Category],"*R*",Table1[Closed Date],">="&DATE(2025,1,1),Table1[Closed Date],"<="&DATE(2025,12,31)) -> 183.21 | F98: =SUMIFS(Table1[PV System Capacity (kWp)],Table1[Sales PIC],A85,Table1[Category],"*R*",Table1[Closed Date],">="&DATE(2026,1,1),Table1[Closed Date],"<="&DATE(2026,12,31)) -> 0 | H98: =SUMIFS(Table1[PV System Capacity (kWp)],Table1[Sales PIC],A85,Table1[Category],"*C&I*") -> 63.71 | I98: =SUMIFS(Table1[PV System Capacity (kWp)],Table1[Sales PIC],A85,Table1[Category],"*C&I*",Table1[Closed Date],">="&DATE(2023,1,1),Table1[Closed Date],"<="&DATE(2023,12,31)) -> 0 | J98: =SUMIFS(Table1[PV System Capacity (kWp)],Table1[Sales PIC],A85,Table1[Category],"*C&I*",Table1[Closed Date],">="&DATE(2024,1,1),Table1[Closed Date],"<="&DATE(2024,12,31)) -> 23 | K98: =SUMIFS(Table1[PV System Capacity (kWp)],Table1[Sales PIC],A85,Table1[Category],"*C&I*",Table1[Closed Date],">="&DATE(2025,1,1),Table1[Closed Date],"<="&DATE(2025,12,31)) -> 40.71 | L98: =SUMIFS(Table1[PV System Capacity (kWp)],Table1[Sales PIC],A85,Table1[Category],"*C&I*",Table1[Closed Date],">="&DATE(2026,1,1),Table1[Closed Date],"<="&DATE(2026,12,31)) -> 0 | N98: =SUMIFS(Table1[Project Value (RM)],Table1[Sales PIC],A85,Table1[Category],"*R*") -> 2164898 | O98: =SUMIFS(Table1[Project Value (RM)],Table1[Sales PIC],A85,Table1[Category],"*R*",Table1[Closed Date],">="&DATE(2023,1,1),Table1[Closed Date],"<="&DATE(2023,12,31)) -> 461700 | P98: =SUMIFS(Table1[Project Value (RM)],Table1[Sales PIC],A85,Table1[Category],"*R*",Table1[Closed Date],">="&DATE(2024,1,1),Table1[Closed Date],"<="&DATE(2024,12,31)) -> 1014898 | Q98: =SUMIFS(Table1[Project Value (RM)],Table1[Sales PIC],A85,Table1[Category],"*R*",Table1[Closed Date],">="&DATE(2025,1,1),Table1[Closed Date],"<="&DATE(2025,12,31)) -> 688300 | R98: =SUMIFS(Table1[Project Value (RM)],Table1[Sales PIC],A85,Table1[Category],"*R*",Table1[Closed Date],">="&DATE(2026,1,1),Table1[Closed Date],"<="&DATE(2026,12,31)) -> 0 | T98: =SUMIFS(Table1[Project Value (RM)],Table1[Sales PIC],A85,Table1[Category],"*C&I*") -> 171000 | U98: =SUMIFS(Table1[Project Value (RM)],Table1[Sales PIC],A85,Table1[Category],"*C&I*",Table1[Closed Date],">="&DATE(2023,1,1),Table1[Closed Date],"<="&DATE(2023,12,31)) -> 0 | V98: =SUMIFS(Table1[Project Value (RM)],Table1[Sales PIC],A85,Table1[Category],"*C&I*",Table1[Closed Date],">="&DATE(2024,1,1),Table1[Closed Date],"<="&DATE(2024,12,31)) -> 80000 | W98: =SUMIFS(Table1[Project Value (RM)],Table1[Sales PIC],A85,Table1[Category],"*C&I*",Table1[Closed Date],">="&DATE(2025,1,1),Table1[Closed Date],"<="&DATE(2025,12,31)) -> 91000 | X98: =SUMIFS(Table1[Project Value (RM)],Table1[Sales PIC],A85,Table1[Category],"*C&I*",Table1[Closed Date],">="&DATE(2026,1,1),Table1[Closed Date],"<="&DATE(2026,12,31)) -> 0
A99: Simon | B99: =SUMIFS(Table1[PV System Capacity (kWp)],Table1[Sales PIC],A86,Table1[Category],"*R*") -> 293.135 | C99: =SUMIFS(Table1[PV System Capacity (kWp)],Table1[Sales PIC],A86,Table1[Category],"*R*",Table1[Closed Date],">="&DATE(2023,1,1),Table1[Closed Date],"<="&DATE(2023,12,31)) -> 178.7 | D99: =SUMIFS(Table1[PV System Capacity (kWp)],Table1[Sales PIC],A86,Table1[Category],"*R*",Table1[Closed Date],">="&DATE(2024,1,1),Table1[Closed Date],"<="&DATE(2024,12,31)) -> 59.635 | E99: =SUMIFS(Table1[PV System Capacity (kWp)],Table1[Sales PIC],A86,Table1[Category],"*R*",Table1[Closed Date],">="&DATE(2025,1,1),Table1[Closed Date],"<="&DATE(2025,12,31)) -> 54.8 | F99: =SUMIFS(Table1[PV System Capacity (kWp)],Table1[Sales PIC],A86,Table1[Category],"*R*",Table1[Closed Date],">="&DATE(2026,1,1),Table1[Closed Date],"<="&DATE(2026,12,31)) -> 0 | H99: =SUMIFS(Table1[PV System Capacity (kWp)],Table1[Sales PIC],A86,Table1[Category],"*C&I*") -> 891.92 | I99: =SUMIFS(Table1[PV System Capacity (kWp)],Table1[Sales PIC],A86,Table1[Category],"*C&I*",Table1[Closed Date],">="&DATE(2023,1,1),Table1[Closed Date],"<="&DATE(2023,12,31)) -> 428.695 | J99: =SUMIFS(Table1[PV System Capacity (kWp)],Table1[Sales PIC],A86,Table1[Category],"*C&I*",Table1[Closed Date],">="&DATE(2024,1,1),Table1[Closed Date],"<="&DATE(2024,12,31)) -> 370.055 | K99: =SUMIFS(Table1[PV System Capacity (kWp)],Table1[Sales PIC],A86,Table1[Category],"*C&I*",Table1[Closed Date],">="&DATE(2025,1,1),Table1[Closed Date],"<="&DATE(2025,12,31)) -> 93.17 | L99: =SUMIFS(Table1[PV System Capacity (kWp)],Table1[Sales PIC],A86,Table1[Category],"*C&I*",Table1[Closed Date],">="&DATE(2026,1,1),Table1[Closed Date],"<="&DATE(2026,12,31)) -> 0 | N99: =SUMIFS(Table1[Project Value (RM)],Table1[Sales PIC],A86,Table1[Category],"*R*") -> 2559648 | O99: =SUMIFS(Table1[Project Value (RM)],Table1[Sales PIC],A86,Table1[Category],"*R*",Table1[Closed Date],">="&DATE(2023,1,1),Table1[Closed Date],"<="&DATE(2023,12,31)) -> 1112405 | P99: =SUMIFS(Table1[Project Value (RM)],Table1[Sales PIC],A86,Table1[Category],"*R*",Table1[Closed Date],">="&DATE(2024,1,1),Table1[Closed Date],"<="&DATE(2024,12,31)) -> 503523 | Q99: =SUMIFS(Table1[Project Value (RM)],Table1[Sales PIC],A86,Table1[Category],"*R*",Table1[Closed Date],">="&DATE(2025,1,1),Table1[Closed Date],"<="&DATE(2025,12,31)) -> 943720 | R99: =SUMIFS(Table1[Project Value (RM)],Table1[Sales PIC],A86,Table1[Category],"*R*",Table1[Closed Date],">="&DATE(2026,1,1),Table1[Closed Date],"<="&DATE(2026,12,31)) -> 0 | T99: =SUMIFS(Table1[Project Value (RM)],Table1[Sales PIC],A86,Table1[Category],"*C&I*") -> 956880 | U99: =SUMIFS(Table1[Project Value (RM)],Table1[Sales PIC],A86,Table1[Category],"*C&I*",Table1[Closed Date],">="&DATE(2023,1,1),Table1[Closed Date],"<="&DATE(2023,12,31)) -> 521800 | V99: =SUMIFS(Table1[Project Value (RM)],Table1[Sales PIC],A86,Table1[Category],"*C&I*",Table1[Closed Date],">="&DATE(2024,1,1),Table1[Closed Date],"<="&DATE(2024,12,31)) -> 280080 | W99: =SUMIFS(Table1[Project Value (RM)],Table1[Sales PIC],A86,Table1[Category],"*C&I*",Table1[Closed Date],">="&DATE(2025,1,1),Table1[Closed Date],"<="&DATE(2025,12,31)) -> 155000 | X99: =SUMIFS(Table1[Project Value (RM)],Table1[Sales PIC],A86,Table1[Category],"*C&I*",Table1[Closed Date],">="&DATE(2026,1,1),Table1[Closed Date],"<="&DATE(2026,12,31)) -> 0
A100: Ong | B100: =SUMIFS(Table1[PV System Capacity (kWp)],Table1[Sales PIC],A87,Table1[Category],"*R*") -> 71.53 | C100: =SUMIFS(Table1[PV System Capacity (kWp)],Table1[Sales PIC],A87,Table1[Category],"*R*",Table1[Closed Date],">="&DATE(2023,1,1),Table1[Closed Date],"<="&DATE(2023,12,31)) -> 0 | D100: =SUMIFS(Table1[PV System Capacity (kWp)],Table1[Sales PIC],A87,Table1[Category],"*R*",Table1[Closed Date],">="&DATE(2024,1,1),Table1[Closed Date],"<="&DATE(2024,12,31)) -> 13.8 | E100: =SUMIFS(Table1[PV System Capacity (kWp)],Table1[Sales PIC],A87,Table1[Category],"*R*",Table1[Closed Date],">="&DATE(2025,1,1),Table1[Closed Date],"<="&DATE(2025,12,31)) -> 57.73 | F100: =SUMIFS(Table1[PV System Capacity (kWp)],Table1[Sales PIC],A87,Table1[Category],"*R*",Table1[Closed Date],">="&DATE(2026,1,1),Table1[Closed Date],"<="&DATE(2026,12,31)) -> 0 | H100: =SUMIFS(Table1[PV System Capacity (kWp)],Table1[Sales PIC],A87,Table1[Category],"*C&I*") -> 0 | I100: =SUMIFS(Table1[PV System Capacity (kWp)],Table1[Sales PIC],A87,Table1[Category],"*C&I*",Table1[Closed Date],">="&DATE(2023,1,1),Table1[Closed Date],"<="&DATE(2023,12,31)) -> 0 | J100: =SUMIFS(Table1[PV System Capacity (kWp)],Table1[Sales PIC],A87,Table1[Category],"*C&I*",Table1[Closed Date],">="&DATE(2024,1,1),Table1[Closed Date],"<="&DATE(2024,12,31)) -> 0 | K100: =SUMIFS(Table1[PV System Capacity (kWp)],Table1[Sales PIC],A87,Table1[Category],"*C&I*",Table1[Closed Date],">="&DATE(2025,1,1),Table1[Closed Date],"<="&DATE(2025,12,31)) -> 0 | L100: =SUMIFS(Table1[PV System Capacity (kWp)],Table1[Sales PIC],A87,Table1[Category],"*C&I*",Table1[Closed Date],">="&DATE(2026,1,1),Table1[Closed Date],"<="&DATE(2026,12,31)) -> 0 | N100: =SUMIFS(Table1[Project Value (RM)],Table1[Sales PIC],A87,Table1[Category],"*R*") -> 273958 | O100: =SUMIFS(Table1[Project Value (RM)],Table1[Sales PIC],A87,Table1[Category],"*R*",Table1[Closed Date],">="&DATE(2023,1,1),Table1[Closed Date],"<="&DATE(2023,12,31)) -> 0 | P100: =SUMIFS(Table1[Project Value (RM)],Table1[Sales PIC],A87,Table1[Category],"*R*",Table1[Closed Date],">="&DATE(2024,1,1),Table1[Closed Date],"<="&DATE(2024,12,31)) -> 54930 | Q100: =SUMIFS(Table1[Project Value (RM)],Table1[Sales PIC],A87,Table1[Category],"*R*",Table1[Closed Date],">="&DATE(2025,1,1),Table1[Closed Date],"<="&DATE(2025,12,31)) -> 219028 | R100: =SUMIFS(Table1[Project Value (RM)],Table1[Sales PIC],A87,Table1[Category],"*R*",Table1[Closed Date],">="&DATE(2026,1,1),Table1[Closed Date],"<="&DATE(2026,12,31)) -> 0 | T100: =SUMIFS(Table1[Project Value (RM)],Table1[Sales PIC],A87,Table1[Category],"*C&I*") -> 0 | U100: =SUMIFS(Table1[Project Value (RM)],Table1[Sales PIC],A87,Table1[Category],"*C&I*",Table1[Closed Date],">="&DATE(2023,1,1),Table1[Closed Date],"<="&DATE(2023,12,31)) -> 0 | V100: =SUMIFS(Table1[Project Value (RM)],Table1[Sales PIC],A87,Table1[Category],"*C&I*",Table1[Closed Date],">="&DATE(2024,1,1),Table1[Closed Date],"<="&DATE(2024,12,31)) -> 0 | W100: =SUMIFS(Table1[Project Value (RM)],Table1[Sales PIC],A87,Table1[Category],"*C&I*",Table1[Closed Date],">="&DATE(2025,1,1),Table1[Closed Date],"<="&DATE(2025,12,31)) -> 0 | X100: =SUMIFS(Table1[Project Value (RM)],Table1[Sales PIC],A87,Table1[Category],"*C&I*",Table1[Closed Date],">="&DATE(2026,1,1),Table1[Closed Date],"<="&DATE(2026,12,31)) -> 0
A101: Patricia | B101: =SUMIFS(Table1[PV System Capacity (kWp)],Table1[Sales PIC],A88,Table1[Category],"*R*") -> 823.23 | C101: =SUMIFS(Table1[PV System Capacity (kWp)],Table1[Sales PIC],A88,Table1[Category],"*R*",Table1[Closed Date],">="&DATE(2023,1,1),Table1[Closed Date],"<="&DATE(2023,12,31)) -> 0 | D101: =SUMIFS(Table1[PV System Capacity (kWp)],Table1[Sales PIC],A88,Table1[Category],"*R*",Table1[Closed Date],">="&DATE(2024,1,1),Table1[Closed Date],"<="&DATE(2024,12,31)) -> 101.79 | E101: =SUMIFS(Table1[PV System Capacity (kWp)],Table1[Sales PIC],A88,Table1[Category],"*R*",Table1[Closed Date],">="&DATE(2025,1,1),Table1[Closed Date],"<="&DATE(2025,12,31)) -> 721.44 | F101: =SUMIFS(Table1[PV System Capacity (kWp)],Table1[Sales PIC],A88,Table1[Category],"*R*",Table1[Closed Date],">="&DATE(2026,1,1),Table1[Closed Date],"<="&DATE(2026,12,31)) -> 0 | H101: =SUMIFS(Table1[PV System Capacity (kWp)],Table1[Sales PIC],A88,Table1[Category],"*C&I*") -> 104.58 | I101: =SUMIFS(Table1[PV System Capacity (kWp)],Table1[Sales PIC],A88,Table1[Category],"*C&I*",Table1[Closed Date],">="&DATE(2023,1,1),Table1[Closed Date],"<="&DATE(2023,12,31)) -> 0 | J101: =SUMIFS(Table1[PV System Capacity (kWp)],Table1[Sales PIC],A88,Table1[Category],"*C&I*",Table1[Closed Date],">="&DATE(2024,1,1),Table1[Closed Date],"<="&DATE(2024,12,31)) -> 18.72 | K101: =SUMIFS(Table1[PV System Capacity (kWp)],Table1[Sales PIC],A88,Table1[Category],"*C&I*",Table1[Closed Date],">="&DATE(2025,1,1),Table1[Closed Date],"<="&DATE(2025,12,31)) -> 85.86 | L101: =SUMIFS(Table1[PV System Capacity (kWp)],Table1[Sales PIC],A88,Table1[Category],"*C&I*",Table1[Closed Date],">="&DATE(2026,1,1),Table1[Closed Date],"<="&DATE(2026,12,31)) -> 0 | N101: =SUMIFS(Table1[Project Value (RM)],Table1[Sales PIC],A88,Table1[Category],"*R*") -> 2216073.4 | O101: =SUMIFS(Table1[Project Value (RM)],Table1[Sales PIC],A88,Table1[Category],"*R*",Table1[Closed Date],">="&DATE(2023,1,1),Table1[Closed Date],"<="&DATE(2023,12,31)) -> 0 | P101: =SUMIFS(Table1[Project Value (RM)],Table1[Sales PIC],A88,Table1[Category],"*R*",Table1[Closed Date],">="&DATE(2024,1,1),Table1[Closed Date],"<="&DATE(2024,12,31)) -> 316176 | Q101: =SUMIFS(Table1[Project Value (RM)],Table1[Sales PIC],A88,Table1[Category],"*R*",Table1[Closed Date],">="&DATE(2025,1,1),Table1[Closed Date],"<="&DATE(2025,12,31)) -> 1899897.4 | R101: =SUMIFS(Table1[Project Value (RM)],Table1[Sales PIC],A88,Table1[Category],"*R*",Table1[Closed Date],">="&DATE(2026,1,1),Table1[Closed Date],"<="&DATE(2026,12,31)) -> 0 | T101: =SUMIFS(Table1[Project Value (RM)],Table1[Sales PIC],A88,Table1[Category],"*C&I*") -> 255773.58 | U101: =SUMIFS(Table1[Project Value (RM)],Table1[Sales PIC],A88,Table1[Category],"*C&I*",Table1[Closed Date],">="&DATE(2023,1,1),Table1[Closed Date],"<="&DATE(2023,12,31)) -> 0 | V101: =SUMIFS(Table1[Project Value (RM)],Table1[Sales PIC],A88,Table1[Category],"*C&I*",Table1[Closed Date],">="&DATE(2024,1,1),Table1[Closed Date],"<="&DATE(2024,12,31)) -> 52000 | W101: =SUMIFS(Table1[Project Value (RM)],Table1[Sales PIC],A88,Table1[Category],"*C&I*",Table1[Closed Date],">="&DATE(2025,1,1),Table1[Closed Date],"<="&DATE(2025,12,31)) -> 203773.58 | X101: =SUMIFS(Table1[Project Value (RM)],Table1[Sales PIC],A88,Table1[Category],"*C&I*",Table1[Closed Date],">="&DATE(2026,1,1),Table1[Closed Date],"<="&DATE(2026,12,31)) -> 0
A102: Reeve | B102: =SUMIFS(Table1[PV System Capacity (kWp)],Table1[Sales PIC],A89,Table1[Category],"*R*") -> 0 | C102: =SUMIFS(Table1[PV System Capacity (kWp)],Table1[Sales PIC],A89,Table1[Category],"*R*",Table1[Closed Date],">="&DATE(2023,1,1),Table1[Closed Date],"<="&DATE(2023,12,31)) -> 0 | D102: =SUMIFS(Table1[PV System Capacity (kWp)],Table1[Sales PIC],A89,Table1[Category],"*R*",Table1[Closed Date],">="&DATE(2024,1,1),Table1[Closed Date],"<="&DATE(2024,12,31)) -> 0 | E102: =SUMIFS(Table1[PV System Capacity (kWp)],Table1[Sales PIC],A89,Table1[Category],"*R*",Table1[Closed Date],">="&DATE(2025,1,1),Table1[Closed Date],"<="&DATE(2025,12,31)) -> 0 | F102: =SUMIFS(Table1[PV System Capacity (kWp)],Table1[Sales PIC],A89,Table1[Category],"*R*",Table1[Closed Date],">="&DATE(2026,1,1),Table1[Closed Date],"<="&DATE(2026,12,31)) -> 0 | H102: =SUMIFS(Table1[PV System Capacity (kWp)],Table1[Sales PIC],A89,Table1[Category],"*C&I*") -> 0 | I102: =SUMIFS(Table1[PV System Capacity (kWp)],Table1[Sales PIC],A89,Table1[Category],"*C&I*",Table1[Closed Date],">="&DATE(2023,1,1),Table1[Closed Date],"<="&DATE(2023,12,31)) -> 0 | J102: =SUMIFS(Table1[PV System Capacity (kWp)],Table1[Sales PIC],A89,Table1[Category],"*C&I*",Table1[Closed Date],">="&DATE(2024,1,1),Table1[Closed Date],"<="&DATE(2024,12,31)) -> 0 | K102: =SUMIFS(Table1[PV System Capacity (kWp)],Table1[Sales PIC],A89,Table1[Category],"*C&I*",Table1[Closed Date],">="&DATE(2025,1,1),Table1[Closed Date],"<="&DATE(2025,12,31)) -> 0 | L102: =SUMIFS(Table1[PV System Capacity (kWp)],Table1[Sales PIC],A89,Table1[Category],"*C&I*",Table1[Closed Date],">="&DATE(2026,1,1),Table1[Closed Date],"<="&DATE(2026,12,31)) -> 0 | N102: =SUMIFS(Table1[Project Value (RM)],Table1[Sales PIC],A89,Table1[Category],"*R*") -> 0 | O102: =SUMIFS(Table1[Project Value (RM)],Table1[Sales PIC],A89,Table1[Category],"*R*",Table1[Closed Date],">="&DATE(2023,1,1),Table1[Closed Date],"<="&DATE(2023,12,31)) -> 0 | P102: =SUMIFS(Table1[Project Value (RM)],Table1[Sales PIC],A89,Table1[Category],"*R*",Table1[Closed Date],">="&DATE(2024,1,1),Table1[Closed Date],"<="&DATE(2024,12,31)) -> 0 | Q102: =SUMIFS(Table1[Project Value (RM)],Table1[Sales PIC],A89,Table1[Category],"*R*",Table1[Closed Date],">="&DATE(2025,1,1),Table1[Closed Date],"<="&DATE(2025,12,31)) -> 0 | R102: =SUMIFS(Table1[Project Value (RM)],Table1[Sales PIC],A89,Table1[Category],"*R*",Table1[Closed Date],">="&DATE(2026,1,1),Table1[Closed Date],"<="&DATE(2026,12,31)) -> 0 | T102: =SUMIFS(Table1[Project Value (RM)],Table1[Sales PIC],A89,Table1[Category],"*C&I*") -> 0 | U102: =SUMIFS(Table1[Project Value (RM)],Table1[Sales PIC],A89,Table1[Category],"*C&I*",Table1[Closed Date],">="&DATE(2023,1,1),Table1[Closed Date],"<="&DATE(2023,12,31)) -> 0 | V102: =SUMIFS(Table1[Project Value (RM)],Table1[Sales PIC],A89,Table1[Category],"*C&I*",Table1[Closed Date],">="&DATE(2024,1,1),Table1[Closed Date],"<="&DATE(2024,12,31)) -> 0 | W102: =SUMIFS(Table1[Project Value (RM)],Table1[Sales PIC],A89,Table1[Category],"*C&I*",Table1[Closed Date],">="&DATE(2025,1,1),Table1[Closed Date],"<="&DATE(2025,12,31)) -> 0 | X102: =SUMIFS(Table1[Project Value (RM)],Table1[Sales PIC],A89,Table1[Category],"*C&I*",Table1[Closed Date],">="&DATE(2026,1,1),Table1[Closed Date],"<="&DATE(2026,12,31)) -> 0
B103: =SUMIFS(Table1[PV System Capacity (kWp)],Table1[Sales PIC],A90,Table1[Category],"*R*") -> 0 | C103: =SUMIFS(Table1[PV System Capacity (kWp)],Table1[Sales PIC],A90,Table1[Category],"*R*",Table1[Closed Date],">="&DATE(2023,1,1),Table1[Closed Date],"<="&DATE(2023,12,31)) -> 0 | D103: =SUMIFS(Table1[PV System Capacity (kWp)],Table1[Sales PIC],A90,Table1[Category],"*R*",Table1[Closed Date],">="&DATE(2024,1,1),Table1[Closed Date],"<="&DATE(2024,12,31)) -> 0 | E103: =SUMIFS(Table1[PV System Capacity (kWp)],Table1[Sales PIC],A90,Table1[Category],"*R*",Table1[Closed Date],">="&DATE(2025,1,1),Table1[Closed Date],"<="&DATE(2025,12,31)) -> 0 | F103: =SUMIFS(Table1[PV System Capacity (kWp)],Table1[Sales PIC],A90,Table1[Category],"*R*",Table1[Closed Date],">="&DATE(2026,1,1),Table1[Closed Date],"<="&DATE(2026,12,31)) -> 0 | H103: =SUMIFS(Table1[PV System Capacity (kWp)],Table1[Sales PIC],A90,Table1[Category],"*C&I*") -> 0 | I103: =SUMIFS(Table1[PV System Capacity (kWp)],Table1[Sales PIC],A90,Table1[Category],"*C&I*",Table1[Closed Date],">="&DATE(2023,1,1),Table1[Closed Date],"<="&DATE(2023,12,31)) -> 0 | J103: =SUMIFS(Table1[PV System Capacity (kWp)],Table1[Sales PIC],A90,Table1[Category],"*C&I*",Table1[Closed Date],">="&DATE(2024,1,1),Table1[Closed Date],"<="&DATE(2024,12,31)) -> 0 | K103: =SUMIFS(Table1[PV System Capacity (kWp)],Table1[Sales PIC],A90,Table1[Category],"*C&I*",Table1[Closed Date],">="&DATE(2025,1,1),Table1[Closed Date],"<="&DATE(2025,12,31)) -> 0 | L103: =SUMIFS(Table1[PV System Capacity (kWp)],Table1[Sales PIC],A90,Table1[Category],"*C&I*",Table1[Closed Date],">="&DATE(2026,1,1),Table1[Closed Date],"<="&DATE(2026,12,31)) -> 0 | N103: =SUMIFS(Table1[Project Value (RM)],Table1[Sales PIC],A90,Table1[Category],"*R*") -> 0 | O103: =SUMIFS(Table1[Project Value (RM)],Table1[Sales PIC],A90,Table1[Category],"*R*",Table1[Closed Date],">="&DATE(2023,1,1),Table1[Closed Date],"<="&DATE(2023,12,31)) -> 0 | P103: =SUMIFS(Table1[Project Value (RM)],Table1[Sales PIC],A90,Table1[Category],"*R*",Table1[Closed Date],">="&DATE(2024,1,1),Table1[Closed Date],"<="&DATE(2024,12,31)) -> 0 | Q103: =SUMIFS(Table1[Project Value (RM)],Table1[Sales PIC],A90,Table1[Category],"*R*",Table1[Closed Date],">="&DATE(2025,1,1),Table1[Closed Date],"<="&DATE(2025,12,31)) -> 0 | R103: =SUMIFS(Table1[Project Value (RM)],Table1[Sales PIC],A90,Table1[Category],"*R*",Table1[Closed Date],">="&DATE(2026,1,1),Table1[Closed Date],"<="&DATE(2026,12,31)) -> 0 | T103: =SUMIFS(Table1[Project Value (RM)],Table1[Sales PIC],A90,Table1[Category],"*C&I*") -> 0 | U103: =SUMIFS(Table1[Project Value (RM)],Table1[Sales PIC],A90,Table1[Category],"*C&I*",Table1[Closed Date],">="&DATE(2023,1,1),Table1[Closed Date],"<="&DATE(2023,12,31)) -> 0 | V103: =SUMIFS(Table1[Project Value (RM)],Table1[Sales PIC],A90,Table1[Category],"*C&I*",Table1[Closed Date],">="&DATE(2024,1,1),Table1[Closed Date],"<="&DATE(2024,12,31)) -> 0 | W103: =SUMIFS(Table1[Project Value (RM)],Table1[Sales PIC],A90,Table1[Category],"*C&I*",Table1[Closed Date],">="&DATE(2025,1,1),Table1[Closed Date],"<="&DATE(2025,12,31)) -> 0 | X103: =SUMIFS(Table1[Project Value (RM)],Table1[Sales PIC],A90,Table1[Category],"*C&I*",Table1[Closed Date],">="&DATE(2026,1,1),Table1[Closed Date],"<="&DATE(2026,12,31)) -> 0
A139: Malaysia | B139: Total
A140: #VALUE! | B140: =COUNTIF(Table1[Location],A140) -> 0
A141: #VALUE! | B141: =COUNTIF(Table1[Location],A141) -> 1
A142: #VALUE! | B142: =COUNTIF(Table1[Location],A142) -> 3
A143: #VALUE! | B143: =COUNTIF(Table1[Location],A143) -> 10
A144: #VALUE! | B144: =COUNTIF(Table1[Location],A144) -> 138
A145: #VALUE! | B145: =COUNTIF(Table1[Location],A145) -> 4
A146: #VALUE! | B146: =COUNTIF(Table1[Location],A146) -> 3
A147: #VALUE! | B147: =COUNTIF(Table1[Location],A147) -> 27
A148: #VALUE! | B148: =COUNTIF(Table1[Location],A148) -> 0
A149: #VALUE! | B149: =COUNTIF(Table1[Location],A149) -> 7
A150: #VALUE! | B150: =COUNTIF(Table1[Location],A150) -> 140
A151: #VALUE! | B151: =COUNTIF(Table1[Location],A151) -> 31
... A153: #VALUE! | B153: =COUNTIF(Table1[Location],A153) -> 0
A161: Authority Submission Summary Data
C164: NEM Rakyat | E164: NOVA (C&I)
A166: Max No. of Days for SEDA Approval | C166: =_xlfn.MAXIFS('ECN Master Project Tracker new'!AP5:AP250,'ECN Master Project Tracker new'!E5:E250,"*R*",'ECN Master Project Tracker new'!F5:F250,"NEM",'ECN Master Project Tracker new'!AP5:AP250,">0") -> 109 | E166: =_xlfn.MAXIFS('ECN Master Project Tracker new'!AP5:AP250,'ECN Master Project Tracker new'!E5:E250,"*C&I*",'ECN Master Project Tracker new'!F5:F250,"NEM",'ECN Master Project Tracker new'!AP5:AP250,">0") -> 132
A167: Min No. of Days for SEDA Approval | C167: =_xlfn.MINIFS('ECN Master Project Tracker new'!AP5:AP250,'ECN Master Project Tracker new'!E5:E250,"*R*",'ECN Master Project Tracker new'!F5:F250,"NEM",'ECN Master Project Tracker new'!AP5:AP250,">0") -> 3 | E167: =_xlfn.MINIFS('ECN Master Project Tracker new'!AP5:AP250,'ECN Master Project Tracker new'!E5:E250,"*C&I*",'ECN Master Project Tracker new'!F5:F250,"NEM",'ECN Master Project Tracker new'!AP5:AP250,">0") -> 10
A168: Ave No. of Days for SEDA Approval | C168: =AVERAGEIFS('ECN Master Project Tracker new'!AP5:AP250,'ECN Master Project Tracker new'!E5:E250,"*R*", 'ECN Master Project Tracker new'!F5:F250,"NEM",'ECN Master Project Tracker new'!AP5:AP250,">0") -> 21.557692 | E168: =AVERAGEIFS('ECN Master Project Tracker new'!AP5:AP250,'ECN Master Project Tracker new'!E5:E250,"*C&I*", 'ECN Master Project Tracker new'!F5:F250,"NEM",'ECN Master Project Tracker new'!AP5:AP250,">0") -> 41.714286

Sheet Pivot
A1: Business | B1: Metric | C1: Year | D1: Value | G1: Year | H1: (All) | M1: Year | N1: (All)
A2: Residential (PV System) | B2: System Capacity | C2: 2023 | D2: =Dashboard!C37 -> 313.3
A3: Residential (PV System) | B3: System Capacity | C3: 2024 | D3: =Dashboard!D37 -> 1637.165 | G3: Sum of Value | H3: Column Labels | M3: Sum of Value | N3: Column Labels
A4: Residential (PV System) | B4: System Capacity | C4: 2025 | D4: =Dashboard!E37 -> 1684.68 | G4: Row Labels | H4: Project Value | I4: Revenue | J4: Collection | K4: Grand Total | M4: Row Labels | N4: System Capacity | O4: Grand Total
A5: Residential (PV System) | B5: System Capacity | C5: 2026 | D5: =Dashboard!F37 -> 0 | G5: Residential (PV System) | H5: 10314868 | I5: 8802124.6 | J5: 8586827.6 | K5: 27703820 | M5: Residential (PV System) | N5: 3635.145 | O5: 3635.145
A6: C&I (PV System) | B6: System Capacity | C6: 2023 | D6: =Dashboard!C38 -> 428.695 | G6: C&I (PV System) | H6: 7185553.6 | I6: 6946746.4 | J6: 5420201.4 | K6: 19552501 | M6: C&I (PV System) | N6: 3718.01 | O6: 3718.01
A7: C&I (PV System) | B7: System Capacity | C7: 2024 | D7: =Dashboard!D38 -> 2088.345 | G7: Residential BESS | H7: 720000 | I7: 720000 | J7: 720000 | K7: 2160000 | M7: Residential BESS | N7: 287.4 | O7: 287.4
A8: C&I (PV System) | B8: System Capacity | C8: 2025 | D8: =Dashboard!E38 -> 1200.97 | G8: C&I BESS | H8: 0 | I8: 0 | J8: 0 | K8: 0 | M8: C&I BESS | N8: 0 | O8: 0
A9: C&I (PV System) | B9: System Capacity | C9: 2026 | D9: =Dashboard!F38 -> 0 | G9: EV Chargers | H9: 1430963 | I9: 957823 | J9: 735522.5 | K9: 3124308.5 | M9: EV Chargers | N9: 1786 | O9: 1786
A10: Residential BESS | B10: System Capacity | C10: 2023 | D10: =Dashboard!C39 -> 287.4 | G10: Grand Total | H10: 19651384 | I10: 17426694 | J10: 15462552 | K10: 52540630 | M10: Grand Total | N10: 9426.555 | O10: 9426.555
A11: Residential BESS | B11: System Capacity | C11: 2024 | D11: =Dashboard!D39 -> 0
A12: Residential BESS | B12: System Capacity | C12: 2025 | D12: =Dashboard!E39 -> 0
A13: Residential BESS | B13: System Capacity | C13: 2026 | D13: =Dashboard!F39 -> 0
A14: C&I BESS | B14: System Capacity | C14: 2023 | D14: =Dashboard!C40 -> 0
A15: C&I BESS | B15: System Capacity | C15: 2024 | D15: =Dashboard!D40 -> 0
A16: C&I BESS | B16: System Capacity | C16: 2025 | D16: =Dashboard!E40 -> 0
A17: C&I BESS | B17: System Capacity | C17: 2026 | D17: =Dashboard!F40 -> 0
A18: EV Chargers | B18: System Capacity | C18: 2023 | D18: =Dashboard!C41 -> 100
A19: EV Chargers | B19: System Capacity | C19: 2024 | D19: =Dashboard!D41 -> 789
A20: EV Chargers | B20: System Capacity | C20: 2025 | D20: =Dashboard!E41 -> 897
A21: EV Chargers | B21: System Capacity | C21: 2026 | D21: =Dashboard!F41 -> 0
A22: Residential (PV System) | B22: Project Value | C22: 2023 | D22: =Dashboard!I37 -> 782725
A23: Residential (PV System) | B23: Project Value | C23: 2024 | D23: =Dashboard!J37 -> 5036797.2
A24: Residential (PV System) | B24: Project Value | C24: 2025 | D24: =Dashboard!K37 -> 4495345.4
A25: Residential (PV System) | B25: Project Value | C25: 2026 | D25: =Dashboard!L37 -> 0
A26: C&I (PV System) | B26: Project Value | C26: 2023 | D26: =Dashboard!I38 -> 521800
A27: C&I (PV System) | B27: Project Value | C27: 2024 | D27: =Dashboard!J38 -> 4266680
A28: C&I (PV System) | B28: Project Value | C28: 2025 | D28: =Dashboard!K38 -> 2397073.6
A29: C&I (PV System) | B29: Project Value | C29: 2026 | D29: =Dashboard!L38 -> 0
A30: Residential BESS | B30: Project Value | C30: 2023 | D30: =Dashboard!I39 -> 720000
A31: Residential BESS | B31: Project Value | C31: 2024 | D31: =Dashboard!J39 -> 0
A32: Residential BESS | B32: Project Value | C32: 2025 | D32: =Dashboard!K39 -> 0
A33: Residential BESS | B33: Project Value | C33: 2026 | D33: =Dashboard!L39 -> 0
A34: C&I BESS | B34: Project Value | C34: 2023 | D34: =Dashboard!I40 -> 0
A35: C&I BESS | B35: Project Value | C35: 2024 | D35: =Dashboard!J40 -> 0
A36: C&I BESS | B36: Project Value | C36: 2025 | D36: =Dashboard!K40 -> 0
A37: C&I BESS | B37: Project Value | C37: 2026 | D37: =Dashboard!L40 -> 0
A38: EV Chargers | B38: Project Value | C38: 2023 | D38: =Dashboard!I41 -> 93380
A39: EV Chargers | B39: Project Value | C39: 2024 | D39: =Dashboard!J41 -> 355363
A40: EV Chargers | B40: Project Value | C40: 2025 | D40: =Dashboard!K41 -> 982220
A41: EV Chargers | B41: Project Value | C41: 2026 | D41: =Dashboard!L41 -> 0
A42: Residential (PV System) | B42: Revenue | C42: 2023 | D42: =Dashboard!O37 -> 379240
A43: Residential (PV System) | B43: Revenue | C43: 2024 | D43: =Dashboard!P37 -> 3897315.2
A44: Residential (PV System) | B44: Revenue | C44: 2025 | D44: =Dashboard!Q37 -> 4525569.4
A45: Residential (PV System) | B45: Revenue | C45: 2026 | D45: =Dashboard!R37 -> 0
A46: C&I (PV System) | B46: Revenue | C46: 2023 | D46: =Dashboard!O38 -> 278820
A47: C&I (PV System) | B47: Revenue | C47: 2024 | D47: =Dashboard!P38 -> 2643170
A48: C&I (PV System) | B48: Revenue | C48: 2025 | D48: =Dashboard!Q38 -> 4024756.4
A49: C&I (PV System) | B49: Revenue | C49: 2026 | D49: =Dashboard!R38 -> 0
A50: Residential BESS | B50: Revenue | C50: 2023 | D50: =Dashboard!O39 -> 432000
A51: Residential BESS | B51: Revenue | C51: 2024 | D51: =Dashboard!P39 -> 288000
A52: Residential BESS | B52: Revenue | C52: 2025 | D52: =Dashboard!Q39 -> 0
A53: Residential BESS | B53: Revenue | C53: 2026 | D53: =Dashboard!R39 -> 0
A54: C&I BESS | B54: Revenue | C54: 2023 | D54: =Dashboard!O40 -> 0
A55: C&I BESS | B55: Revenue | C55: 2024 | D55: =Dashboard!P40 -> 0
A56: C&I BESS | B56: Revenue | C56: 2025 | D56: =Dashboard!Q40 -> 0
A57: C&I BESS | B57: Revenue | C57: 2026 | D57: =Dashboard!R40 -> 0
A58: EV Chargers | B58: Revenue | C58: 2023 | D58: =Dashboard!O41 -> 46690
A59: EV Chargers | B59: Revenue | C59: 2024 | D59: =Dashboard!P41 -> 342903
A60: EV Chargers | B60: Revenue | C60: 2025 | D60: =Dashboard!Q41 -> 568230
A61: EV Chargers | B61: Revenue | C61: 2026 | D61: =Dashboard!R41 -> 0
A62: Residential (PV System) | B62: Collection | C62: 2023 | D62: =Dashboard!U37 -> 301640
A63: Residential (PV System) | B63: Collection | C63: 2024 | D63: =Dashboard!V37 -> 3691311.2
A64: Residential (PV System) | B64: Collection | C64: 2025 | D64: =Dashboard!W37 -> 4593876.4
A65: Residential (PV System) | B65: Collection | C65: 2026 | D65: =Dashboard!X37 -> 0
A66: C&I (PV System) | B66: Collection | C66: 2023 | D66: =Dashboard!U38 -> 278820
A67: C&I (PV System) | B67: Collection | C67: 2024 | D67: =Dashboard!V38 -> 2422890
A68: C&I (PV System) | B68: Collection | C68: 2025 | D68: =Dashboard!W38 -> 2718491.4
A69: C&I (PV System) | B69: Collection | C69: 2026 | D69: =Dashboard!X38 -> 0
A70: Residential BESS | B70: Collection | C70: 2023 | D70: =Dashboard!U39 -> 432000
A71: Residential BESS | B71: Collection | C71: 2024 | D71: =Dashboard!V39 -> 288000
A72: Residential BESS | B72: Collection | C72: 2025 | D72: =Dashboard!W39 -> 0
A73: Residential BESS | B73: Collection | C73: 2026 | D73: =Dashboard!X39 -> 0
A74: C&I BESS | B74: Collection | C74: 2023 | D74: =Dashboard!U40 -> 0
A75: C&I BESS | B75: Collection | C75: 2024 | D75: =Dashboard!V40 -> 0
A76: C&I BESS | B76: Collection | C76: 2025 | D76: =Dashboard!W40 -> 0
A77: C&I BESS | B77: Collection | C77: 2026 | D77: =Dashboard!X40 -> 0
A78: EV Chargers | B78: Collection | C78: 2023 | D78: =Dashboard!U41 -> 46690
A79: EV Chargers | B79: Collection | C79: 2024 | D79: =Dashboard!V41 -> 321025
A80: EV Chargers | B80: Collection | C80: 2025 | D80: =Dashboard!W41 -> 367807.5
A81: EV Chargers | B81: Collection | C81: 2026 | D81: =Dashboard!X41 -> 0

Sheet Master Data
A4: Project No | B4: Client Name | C4: Closed Date | D4: Sales PIC | E4: Category | F4: Scheme | G4: Location | H4: PV System Capacity (kWp) | I4: EV Charger Capacity | J4: BESS Capacity | K4: Project Value (RM) | L4: VO (RM) | M4: Payment Method | N4: Outright/PPA | O4: Module | P4: Module Quantity | Q4: Inverter | R4: Inverter Warranty | S4: I/C Number | T4: Installation Address | U4: Phone Number | V4: Email Address | W4: Insurance Warranty | X4: DLP Period | Y4: O&M | Z4: Partner | AA4: Services Exclusion | AB4: Additional Remark
A5: 2303005 | B5: Wong Kim Mei | C5: 45021 | D5: Simon | E5: R-PV | F5: NEM | G5: #VALUE! | H5: 8.05 | I5: - | K5: 32000 | M5: Self finance | N5: Outright | O5: Astronergy 575Wp | P5: 14 | Q5: Solinteg MHT-8K-25 hybrid | S5: 731013-10-5784 | T5: No. 24, Jalan Seri Muka 36/27A, Taman Menegun Indah, 41000 Klang, Selangor. | U5: 016-335 4884 | V5: wongkimmei73@gmail.com | W5: 5 years | X5: 1 year
A6: 2303006 | B6: Ang Ching Ming | C6: 45029 | D6: Simon | E6: R-PV | F6: NEM | G6: #VALUE! | H6: 12.65 | I6: - | K6: 40000 | M6: Self finance | N6: Outright | O6: Astronergy 575Wp | P6: 22 | Q6: Solinteg MHT-10K-25 hybrid | S6: 931003-10-6105 | T6: 1, Jalan Ulek Mayang 2C/KU5, Bandar Bukit Raja, 41050 Klang, Selangpr | U6: 017-9666099 | V6: cmang_02@outlook.com | W6: 1 year | X6: 1 year
A7: 2304016 | B7: Tan Sei Choon | C7: 45048 | D7: Chean Bang | E7: R-PV | F7: SELCO | G7: #VALUE! | H7: 8.05 | I7: - | K7: 31000 | M7: Self finance | N7: Outright | O7: Astronergy 575Wp | P7: 14 | Q7: Solinteg MHT-8K-25 hybrid | S7: 650818-06-5287 | T7: 2, Lorong Bukit Setongkol Perdana 52, Taman Fairmont Jaya, 25200 Kuantan, Pahang. | U7: 016-922 3868 | V7: tesoon12@gmail.com | W7: 5 years | X7: 1 year
A8: 2305021 | B8: Ho Hon Kit | C8: 45058 | D8: Simon | E8: R-PV | F8: NEM | G8: #VALUE! | H8: 4.65 | I8: - | K8: 20000 | M8: Self finance | N8: Outright | O8: Astronergy 575Wp | P8: 8 | Q8: Solinteg MHS-3.6K-30 hybrid | S8: 670422-10-5607 | T8: No 32, Jalan Puteri 12/7, Bandar Puteri, 47100 Puchong, Selangor. | U8: 012-3979968 | V8: hkho@trident-x.com | W8: 5 years | X8: 1 year
A9: 2305026 | B9: Stanley Ang Leng Chuan | C9: 45114 | D9: Simon | E9: R-PV | F9: NEM | G9: #VALUE! | H9: 12.65 | I9: - | K9: 40000 | M9: Self finance | N9: Outright | O9: Astronergy 575Wp | P9: 22 | Q9: Solinteg MHT-10K-25 hybrid | S9: 751007-10-5671 | T9: 5, Jalan Bidara 9, Bandar Botanic, 41200 Klang, Selangor. | U9: 016-6767999 | V9: stanleyang9@gmail.com | W9: 1 year | X9: 1 year
A10: 2306033 | B10: Foo Tuang Lee | C10: 45083 | D10: Chean Bang | E10: R-PV | F10: NEM | G10: #VALUE! | H10: 4.65 | I10: - | K10: 16000 | M10: Self finance | N10: Outright | O10: Astronergy 575Wp | P10: 8 | Q10: Solinteg MHS-3.6K-30 hybrid | S10: 741128-01-5075 | T10: No 20, Jln Pelangi 15, Tmn Pelangi, 86000 Kluang, Johor | U10: 016-2368221 | V10: ericfoo8888@gmail.com | W10: N/A | X10: 1 year
A11: 2306037 | B11: Tan Hong Guan | C11: 45195 | D11: Simon | E11: R-PV | F11: NEM | G11: #VALUE! | H11: 10.925 | I11: - | K11: 36575 | M11: Self finance | N11: Outright | O11: Astronergy 575Wp | P11: 19 | Q11: Huawei SUN2000-10KTL | S11: 680512-07-5359 | T11: No 6, Pinggir Bukit Segar 2, Tmn Bkt Segar, 56100 Cheras, Kuala Lumpur | U11: 012-4380246 | V11: hongguan.tan@gmail.com | W11: N/A | X11: 1 year | Z11: EDCA
A12: 2307040 | B12: Law Soo Chin | C12: 45118 | D12: Chean Bang | E12: R-PV | F12: NEM | G12: #VALUE! | H12: 12.65 | I12: - | K12: 40000 | M12: Self finance | N12: Outright | O12: Astronergy 575Wp | P12: 22 | Q12: Solinteg MHT-10K-25 hybrid | S12: 640407-07-5713 | T12: 6, Jalan BS 3/8, Taman Bukit Serdang, 43300 Seri Kembangan, Selangor. | U12: 016-2013221 | V12: lawsc123@hotmail.com | W12: 3 years | X12: 1 year
A13: 2305011 | B13: Kossan FRP Marketing (M) Sdn Bhd | C13: 45078 | D13: Simon | E13: C&I-PV | F13: NEM | G13: #VALUE! | H13: 283.945 | I13: - | K13: 242000 | M13: Cash | N13: Outright | O13: - | P13: - | Q13: - | S13: - | T13: PT 2019, Jln Keretapi Lama Off, Jln Kapar, BT 4 3/4, Kg Rantau Panjang, 42100 Klang, Selangor | U13: - | V13: - | W13: N/A | X13: 1 year | Y13: N/A | Z13: EDCA
A14: 2304007 | B14: MTJ Development Sdn Bhd (Intercontinental KL) | C14: 45105 | D14: Simon | E14: C&I-PV | F14: NEM | G14: #VALUE! | H14: 51.75 | K14: 188800 | M14: Cash | N14: Outright | O14: Astronergy 575Wp | P14: 90 | Q14: Goodwe 50kW | S14: - | T14: No 165, Jln Ampang, 50450 Kuala Lumpur, WP Kuala Lumpur | U14: - | V14: - | W14: 3 years | X14: 1 year | Y14: N/A
A15: 2307042 | B15: Dato' Sri Ng Chong Keong | C15: 45086 | D15: Chean Bang | E15: R-PV | F15: NEM | G15: #VALUE! | H15: 16.1 | I15: - | K15: 50000 | M15: Self finance | N15: Outright | O15: Astronergy 575Wp | P15: 28 | Q15: Solinteg MHT-12K-25 hybrid | S15: 650309-08-5407 | T15: 9, Lorong Tok Sira 4, Taman Melor, 25050 Kuantan, Pahang. | U15: 016-9907409 | V15: ng_xinnee@hotmail.com | W15: 5 years | X15: 1 year
A16: 2308058 | B16: Cheong Yik Yin | C16: 45144 | D16: Simon | E16: R-PV | F16: NEM | G16: #VALUE! | H16: 6.9 | I16: - | K16: 30000 | M16: Self finance | N16: Outright | O16: Astronergy 575Wp | P16: 12 | Q16: Solinteg MHT-5K-25 hybrid | S16: 950710-14-6004 | T16: No. 18, Jalan Setia Utama U13/39D, Setia Alam, Seksyen U13, 40170 Shah Alam, Selangor. | U16: 016-6530107 | V16: yikyin_cheong@hotmail.com | W16: 3 years | X16: 1 year
A17: 2308062 | B17: Lim Chin Joo | C17: 45247 | D17: Simon | E17: R-PV | F17: NEM | G17: #VALUE! | H17: 12.65 | I17: - | K17: 42300 | M17: Self finance | N17: Outright | O17: Astronergy 575Wp | P17: 22 | Q17: Huawei SUN2000-12KTL | S17: 6905020-02-5211 | T17: 8, Jln BK 6A/2A, Bandar Kinrara, 47100 Puchong, Selangor Darul Ehsan | U17: 012-6151020 | V17: chinjoolim@gmail.com | W17: 3 years | X17: 1 year
A18: 2309068 | B18: Kee Siew Chuan (Ngo Woon Wah) | C18: 45219 | D18: Chean Bang | E18: R-PV | F18: NEM | G18: #VALUE! | H18: 6.9 | I18: - | K18: 28500 | M18: Self finance | N18: Outright | O18: Astronergy 575Wp | P18: 12 | Q18: Solinteg MHT-5K-25 hybrid | S18: 730119-08-5342 | T18: No 12-A, Lrg Bukit Setongkol Jaya 32, Bkt Setongkol, 25200, Kuantan, Pahang Darul Makmur | U18: 019-9631028 | V18: siewchuan639@gmail.com | W18: 5 years | X18: 1 year
A19: 2310078 | B19: Lee Nyok Cheng | C19: 45209 | D19: Chean Bang | E19: R-PV | F19: NEM | G19: #VALUE! | H19: 16.1 | I19: - | K19: 52000 | M19: Self finance | N19: Outright | O19: Astronergy 575Wp | P19: 28 | Q19: Solinteg MHT-12K-25 hybrid | S19: 581227-05-5427 | T19: No. 1, Lorong IM 1/62, Perumahan Indera Mahkota 1, 25200 Kuantan, Pahang. | U19: 016-9221189 | V19: songlee1188@gmail.com | W19: 5 years | X19: 1 year
A20: 2310083 | B20: Ong Eng Guan | C20: 45229 | D20: Chean Bang | E20: R-PV | F20: NEM | G20: #VALUE! | H20: 8.05 | I20: - | K20: 31000 | M20: Self finance | N20: Outright | O20: Astronergy 575Wp | P20: 14 | Q20: Solinteg MHT-8K-25 hybrid | S20: 451011-02-5493 | T20: No. 9 Lorong Im 11/12, Mahkota Heights, 25200 Kuantan, Pahang Darul Makmur | U20: 012-9853289 | V20: daniel_8632@yahoo.com | W20: 5 years | X20: 1 year
A21: 2310084 | B21: Chia Le Chin | C21: 45231 | D21: Chean Bang | E21: R-PV | F21: NEM | G21: #VALUE! | H21: 8.05 | I21: - | K21: 34000 | M21: Cash + instalment | N21: Outright | O21: Astronergy 575Wp | P21: 14 | Q21: Solinteg MHT-8K-25 hybrid | S21: 730219-06-5090 | T21: No 11, Lorong Im 11/12, Mahkota Heights, 25200 Kuantan, Pahang Darul Makmur | U21: 013-9318778 | V21: health_trading@yahoo | W21: 5 years | X21: 1 year
A22: 2305024 | B22: Beh Poh Loh | C22: 45103 | D22: Chean Bang | E22: R-PV | F22: NEM | G22: #VALUE! | H22: 12.65 | I22: - | K22: 42500 | L22: 6000 | M22: Self finance | N22: Outright | O22: Astronergy 575Wp | P22: 22 | Q22: GoodWe GW10KN-ET | S22: 890620-06-5065 | T22: No 10, Lorong Peramu Jaya 1/3, Perumahan Peramu Jaya 1, 26060 Kuantan, Pahang Darul Makmur | U22: 016-9862270 | V22: graybackboy@hotmail.com | W22: 5 years | X22: 1 year
A23: 2307052 | B23: Ngoh Win Nee | C23: 45154 | D23: Chean Bang | E23: R-PV | F23: NEM | G23: #VALUE! | H23: 4.6 | I23: - | K23: 22100 | M23: Credit Card Instalment | N23: Outright | O23: Astronergy 575Wp | P23: 8 | Q23: Solinteg MHS-3.6K-30 hybrid | S23: 851017-06-5456 | T23: No 49, Lrg Tiram Jaya 5, Perumahan Tiram Jaya, 25200 Kuantan, Pahang | U23: 012-9860700 | V23: winneengoh@gmail.com | W23: 5 years | X23: 1 year
A24: 2304010 | B24: Tung Seng Chang | C24: 45061 | D24: Simon | E24: R-PV | F24: NEM | G24: #VALUE! | H24: 13.625 | I24: - | K24: 20650 | M24: Cash | N24: Outright | O24: - | P24: - | Q24: Goodwe GW10K-SDT-20 | S24: 720703-10-5665 | T24: 18, Jalan Setia Perdana U13/29C, Setia Alam, 40170 Shah Alam, Selangor | U24: 019-2933333 | V24: tungsc6@gmail.com | W24: N/A | X24: 1 year | Z24: EDCA
A25: 2308065 | B25: Pua Hock Meng | C25: 45176 | D25: Chean Bang | E25: R-PV | F25: NEM | G25: #VALUE! | H25: 8.625 | I25: - | K25: 33000 | L25: 2500 | M25: Self finance | N25: Outright | O25: Astronergy 575Wp | P25: 15 | Q25: Solinteg MHT-8K-25 hybrid | S25: 830524-06-5271 | T25: No. 18, Lorong Peramu Jaya 1/2, Perumahan Peramu Jaya 1, 26060 Kuantan, Pahang Darul Makmur | U25: 019-9956536 | V25: prinze.pua@gmail.com | W25: 5 years | X25: 1 year
A26: 2306009 | B26: Dato Arif Stephen bin Abdullah | C26: 45193 | D26: Simon | E26: R-BESS | F26: SELCO | G26: #VALUE! | H26: 85.1 | I26: 44 | J26: 287.4 | K26: 720000 | M26: Cash | N26: Outright | O26: Astronergy 575Wp | P26: 148 | Q26: Solax X3-Ultra 20kW x 3 | T26: Lot 12193, Jalan Felcra Semungkis, Batu 14 Hulu Langat, 43100 Hulu Langat, Selangor Darul Ehsan | X26: 1 year
A27: 2303003 | B27: Greenlast Housing Development Sdn Bhd | C27: 45309 | D27: Chean Bang | E27: C&I-PV | F27: NEM | G27: #VALUE! | H27: 23 | I27: - | K27: 80000 | M27: Self finance | N27: Outright | O27: Astronergy 575Wp | P27: 40 | Q27: Goodwe GW20K-SDT-20 | S27: - | T27: Lot 1-5, Jalan Semambu,Kawasan Perindustrian Semambu, Kuantan Pahang 25350 Malaysia | U27: - | V27: - | W27: N/A | X27: 1 year | Y27: Others | AB27: Panel Cleaning 3 years (Once per year)
A28: 2311040 | B28: DBTS Industries Sdn Bhd | C28: 45244 | D28: SImon | E28: C&I-PV | F28: NEM | G28: #VALUE! | H28: 93 | I28: - | K28: 91000 | M28: Cash | N28: Outright | O28: - | P28: - | Q28: - | S28: - | T28: Lot 2199, Jalan Nuri, Kampung Batu 9 Kebun Baru, 42500 Telok Panglima Garang, Selangor | U28: - | V28: - | W28: N/A | X28: 1 year | Y28: Full O&M - 1 year | Z28: EDCA
A29: 2308007 | B29: EV Connection Sdn Bhd (The Pines Melaka) | C29: 45245 | D29: Simon | E29: EV Charger | F29: - | G29: #VALUE! | H29: 0 | I29: 100 | K29: 93380 | M29: Cash | N29: Outright | O29: - | P29: - | Q29: - | T29: 33, Jalan Tun Sri Lanang, 75100 Melaka | W29: N/A | X29: 1 year
A30: 2311094 | B30: Ching Kok Keong | C30: 45260 | D30: Chean Bang | E30: R-PV | F30: NEM | G30: #VALUE! | H30: 9.775 | I30: - | K30: 37000 | M30: Self finance | N30: Outright | O30: Astronergy 575Wp | P30: 17 | Q30: Solinteg MHT-8K-25 hybrid | S30: 670428-11-5021 | T30: Lot 10997, Jln Kenanga, Kg Sura Jeti, 23000 Dungun, Terengganu Darul Iman | U30: 017-9767388 | V30: ckkcsk6666@gmail.com | W30: 3 years | X30: 1 year
A31: 2311095 | B31: Chu Yin Siong | C31: 45255 | D31: Chean Bang | E31: R-PV | F31: NEM | G31: #VALUE! | H31: 12.65 | I31: - | K31: 44600 | M31: Self finance | N31: Outright | O31: Astronergy 575Wp | P31: 22 | Q31: Solinteg MHT-10K-25 hybrid | S31: 620818-11-5371 | T31: No 11, Jln Paka, Tmn Bunga Raya, 23000 Dungun, Terengganu Darul Iman | U31: 019-9836811 | V31: cca6668@gmail.com | W31: 3 years | X31: 1 year
A32: 2311039 | B32: DC Handal EV Charging Hub | C32: 45297 | D32: Simon | E32: C&I-PV | F32: SELCO | G32: #VALUE! | H32: 370.055 | I32: - | K32: 280080 | L32: 46945 | M32: Self finance | N32: Outright | O32: - | P32: - | Q32: - | S32: - | T32: - | U32: - | V32: - | W32: N/A | X32: 1 year | Y32: N/A
A33: 2311012 | B33: EV Connection Sdn Bhd (IOI Citymall, Putrajaya) | C33: 45301 | D33: Simon | E33: EV Charger | F33: - | G33: #VALUE! | H33: 0 | I33: 240 | K33: 109000 | M33: Cash | N33: Outright | O33: - | P33: - | Q33: - | S33: - | T33: - | U33: - | V33: - | W33: N/A | X33: 1 year
A34: 2311089 | B34: Susan Lau Shiew Hung | C34: 45260 | D34: Simon | E34: R-PV | F34: NEM | G34: #VALUE! | H34: 11.5 | I34: - | K34: 37500 | M34: Self finance | N34: Outright | O34: Astronergy 575Wp | P34: 20 | Q34: GoodWe GW10K-SDT-20 | S34: 821226-13-5150 | T34: 27, Jalan SS 22A/8, Damansara Jaya, 47400 Petaling Jaya, Selangor Darul Ehsan | U34: 012-2777019 | V34: san99lau@gmail.com | W34: 3 years | X34: 1 year
A35: 2312118 | B35: Dr Suntheresan A/L Ganapathy | C35: 45296 | D35: Ong | E35: R-PV | F35: NEM | G35: #VALUE! | H35: 13.8 | I35: - | K35: 54930 | M35: Self finance | N35: Outright | O35: Astronergy 575Wp | P35: 24 | Q35: Solinteg MHT-12K-25 hybrid | S35: 680926-02-5351 | T35: No 27, Jalan Aman Elemen 3, Bandar Tropicana Aman, 42500 Telok Panglima Garang, Selangor Darul Ehsan | U35: 019-2262119 | V35: sunthe26@gmail.com | W35: 3 years | X35: 1 year
A36: 2309070 | B36: Saiful Lizan Bin Ibrahim | C36: 45303 | D36: Simon | E36: R-PV | F36: NEM | G36: #VALUE! | H36: 13.8 | I36: - | K36: 48902 | M36: Credit Card Instalment | N36: Outright | O36: Astronergy 575Wp | P36: 24 | Q36: Solinteg MHT-12K-25 hybrid | S36: 731112-06-5749 | T36: 16, Jalan Suadamai 6/2, Bandar Tun Hussein Onn, 43200 Cheras, Selangor Darul Ehsan | U36: 019-2611759 | V36: gunner2490@yahoo.com | W36: 3 years | X36: 1 year
A37: 2310075 | B37: Chong Fong Chin(Jessie) | C37: 45366 | D37: Chean Bang | E37: R-PV | F37: NEM | G37: #VALUE! | H37: 14.625 | I37: - | K37: 45600 | M37: Self finance | N37: Outright | O37: Astronergy 585Wp | P37: 25 | Q37: Solinteg MHT-12K-25 hybrid | S37: 861207-33-5276 | T37: No 11, Lrg Bkt Setongkol Perdana 29, Perkpgn Bkt Setongkol, Tmn Bukit Setongkol, 25200 Kuantan, Pahang Darul Makmur | U37: 019-9351188 | V37: jessie.cfc@gmail.com | X37: 1 year
A38: 2310076 | B38: Loo Thiam Seng | C38: 45707 | D38: Tham | E38: R-PV | F38: NEM | G38: #VALUE! | H38: 8.26 | I38: - | K38: 24000 | M38: Cash | N38: Outright | O38: Astronergy 590Wp | P38: 14 | Q38: Huawei SUN2000-6KTL | S38: 560426-07-5479 | T38: 61, Jln Tasik Indah 2, Tmn Tasik Indah, 51200 WP Kuala Lumpur | U38: 019-2263229 | V38: tsloo1956@gmail.com | W38: 3 years | X38: 1 year
A39: 2310085 | B39: Chew Mei May | C39: 45403 | D39: Simon | E39: R-PV | F39: NEM | G39: #VALUE! | H39: 12.075 | I39: - | K39: 47786 | M39: Credit Card Instalment | N39: Outright | O39: Astronergy 575Wp | P39: 21 | Q39: Solinteg MHT-10K-25 hybrid | S39: 721025-10-5598 | T39: 67, Jln BK 5B/5A, Bdr Kinrara, 47180 Puchong, Selangor Darul Ehsan | U39: 012-2203402 | V39: meimaychew@gmail.com | W39: 3 years | X39: 1 year
A40: 2312113 | B40: Razman Bin Samsudin | C40: 45313 | D40: Simon | E40: R-PV | F40: NEM | G40: #VALUE! | H40: 13.8 | I40: - | K40: 44000 | M40: Self finance | N40: Outright | O40: Astronergy 575Wp | P40: 24 | Q40: Huawei SUN2000-12KTL | S40: 760713-71-5025 | T40: No.8, Jalan SS20/25, Damansara Utama, 47400 Petaling Jaya, Selangor | U40: 019-3371313 | V40: razmanbinsamsudin@gmailcom | W40: 3 years | X40: 1 year
A41: 2401121 | B41: Chen Ah Hin | C41: 45383 | D41: Tham | E41: R-PV | F41: NEM | G41: #VALUE! | H41: 11.7 | I41: - | K41: 40000 | M41: Self finance | N41: Outright | O41: Astronergy 585Wp | P41: 20 | Q41: Solinteg MHT-10K-25 hybrid | S41: 480824-10-5119 | T41: Lot 1325-79B, Jalan Jinjang Damai 7, JinJang Utara, 52000 Kuala Lumpur | U41: 019-3281707 | V41: chen2.luma@gmail.com | W41: 3 years | X41: 1 year
A42: 2401124 | B42: Lim Kok Teong | C42: 45384 | D42: Tham | E42: R-PV | F42: NEM | G42: #VALUE! | H42: 17.55 | I42: - | K42: 53708 | M42: Credit Card Instalment | N42: Outright | O42: Astronergy 585Wp | P42: 30 | Q42: Huawei SUN2000-12KTL | S42: 790418-07-5747 | T42: 3 Jalan Kenyalang 11/4E, PJU 5, Kota Damansara, 47810 Petaling Jaya, Selangor Darul Ehsan | U42: 019-4134865 | V42: cmjasonlim311@gmail.com | W42: 3 years | X42: 1 year | Z42: Unitrade
A43: 2401131 | B43: Chan Po Kok (JC Chan KEB) | C43: 45394 | D43: Tham | E43: R-PV | F43: NEM | G43: #VALUE! | H43: 8.19 | I43: - | K43: 29500 | M43: Self finance | N43: Outright | O43: Astronergy 585Wp | P43: 14 | Q43: Huawei SUN2000-6KTL | S43: 830506-14-6019 | T43: 16, Jalan Sunville 4, Taman Sunville, 43000 Kajang, Selangor Darul Ehsan | U43: 017-8786050 | V43: cpokok0506@hotmail.com | W43: 3 years | X43: 1 year
A44: 2401137 | B44: Lim Kok Liang | C44: 45384 | D44: Tham | E44: R-PV | F44: NEM | G44: #VALUE! | H44: 11.7 | I44: - | K44: 40900 | M44: Credit Card Instalment | N44: Outright | O44: Astronergy 585Wp | P44: 20 | Q44: Huawei SUN2000-10KTL | S44: 830112-02-5169 | T44: 1, Jalan Metafasa, U16/160. Elmina West, Seksyen U16, 40160, Shah Alam , Selangor Darul Ehsan | U44: 016-2173777 | V44: steelmerchantssb@gmail.com | W44: 3 years | X44: 1 year
A45: 2401147 | B45: Susan Sung Fong Thieng | C45: 45384 | D45: Tham | E45: R-PV | F45: NEM | G45: #VALUE! | H45: 11.7 | I45: - | K45: 40440 | M45: Credit Card Instalment | N45: Outright | O45: Astronergy 585Wp | P45: 20 | Q45: Huawei SUN2000-10KTL | S45: 691205-12-5030 | T45: 37, Southlake Terraces, Jalan Denai Selatan 5, Desa Parkcity. 52200 Kuala Lumpur | U45: 012-2393003 | V45: susansung37@gmail.com | W45: 3 years | X45: 1 year | Z45: Unitrade
A46: 2403165 | B46: Lee Boon Huet | C46: 45383 | D46: Tham | E46: R-PV | F46: NEM | G46: #VALUE! | H46: 7.02 | I46: - | K46: 24600 | M46: Cash | N46: Outright | O46: Astronergy 585Wp | P46: 12 | Q46: Huawei SUN2000-5KTL-L1 | S46: 720825-05-5109 | T46: 31, Jln Cassia 4, Bdr Botanic, 41200 Klang, Selangor Darul Ehsan | U46: 012-2045618 | V46: blee@fp-group.com | W46: 3 years | X46: 1 year
A47: 2403167 | B47: Ng Yunn Chong | C47: 45375 | D47: Tham | E47: R-PV | F47: NEM | G47: #VALUE! | H47: 17.55 | I47: - | K47: 47500 | M47: Self finance | N47: Outright | O47: Astronergy 585Wp | P47: 30 | Q47: Huawei SUN2000-12KTL | S47: 620205-08-6037 | T47: 97, Jalan Selasar Rokam 11, Kampung Sri Ampang, 31350 Ipoh, Perak Darul Ridzuan | U47: 012-5127295 | V47: ngyunnchong123@gmail.com | W47: 3 years | X47: 1 year
A48: 2403170 | B48: Wong Hoon Sang | C48: 45367 | D48: Tham | E48: R-PV | F48: NEM | G48: #VALUE! | H48: 10.53 | I48: - | K48: 35600 | M48: Self finance | N48: Outright | O48: Astronergy 585Wp | P48: 18 | Q48: Solinteg MHT-8K-25 hybrid | S48: 630220-10-7149 | T48: 75, Jalan Uranus U5/122B, Seksyen U5, 40150 Shah Alam. Selangor Darul Ehsan | U48: 014-9159789 | V48: wonghoonsang@gmail.com | W48: 3 years | X48: 1 year
A49: 2403177 | B49: Nor Aini binti Mohd Ashari | C49: 45376 | D49: Tham | E49: R-PV | F49: NEM | G49: #VALUE! | H49: 4.68 | I49: - | K49: 20000 | M49: Self finance | N49: Outright | O49: Astronergy 585Wp | P49: 8 | Q49: Huawei SUN2000-4KTL-L1 | S49: 731105-08-6402 | T49: No 61, Jln Sigma U6/16A, Sek U6 (Taman Subang Permata), 40150 Subang, Selangor Darul Ehsan | U49: 011-28584486 | V49: norazam4446@yahoo.com.sg | W49: 3 years | X49: 1 year | Z49: Bioserasi
A50: 2403189 | B50: Lai Kim Soon (Stella) | C50: 45380 | D50: Chean Bang | E50: R-PV | F50: NEM | G50: #VALUE! | H50: 7.02 | I50: - | K50: 27500 | M50: Self finance | N50: Outright | O50: Astronergy 585Wp | P50: 12 | Q50: Solinteg MHS-5K-30 hybrid | S50: 910301-06-5675 | T50: No 36, Lrg Seri Teruntum 13, Tmn Sri Teru, Tanah Putih, 25200 Kuantan. Pahang Darul Makmur | U50: 011-55090155 | V50: miiao_maomao520@hotmail.com | W50: 3 years | X50: 1 year
A51: 2403190 | B51: Tan Poh Poh | C51: 45378 | D51: Chean Bang | E51: R-PV | F51: NEM | G51: #VALUE! | H51: 7.02 | I51: - | K51: 21000 | M51: Self finance | N51: Outright | O51: Astronergy 585Wp | P51: 12 | Q51: Solinteg MHS-5K-30 hybrid | S51: 710625-08-5224 | T51: 6, Lrg Seri Setali, 115 Off Jln Air Putih, Air Putih, 25300 Kuantan, Pahang Darul Makmur | U51: 012-9831939 | V51: may014215@gmail.com | W51: 3 years | X51: 1 year
A52: 2403197 | B52: Leau Koo Sien (Eric) | C52: 45380 | D52: Chean Bang | E52: R-PV | F52: NEM | G52: #VALUE! | H52: 16.38 | I52: - | K52: 48600 | M52: Self finance | N52: Outright | O52: Astronergy 585Wp | P52: 28 | Q52: Solinteg MHT-12K-25 hybrid | S52: 740722-06-5097 | T52: No 12A, Lorong Pelindung 95, Perumahan Pelindung, 25050 Kuantan, Pahang Darul makmur | U52: 019-9270778 | V52: Leaueric@gmail.com | W52: 3 years | X52: 1 year
A53: 2403197-1 | B53: Koon Kok Leong | C53: 45383 | D53: Tham | E53: R-PV | F53: NEM | G53: #VALUE! | H53: 7.02 | I53: - | K53: 27237.2 | M53: Credit Card Instalment | N53: Outright | O53: Astronergy 585Wp | P53: 12 | Q53: Huawei SUN2000-5KTL-L1 | S53: 741008-01-5759 | T53: No 80, Lrg Delima 5/KS6, Bdr Parklands, Pandamar, 42000 Klang, Selangor Darul Ehsan | U53: 012-3988909 | V53: klkoon8882@gmail.com | W53: 3 years | X53: 1 year
A54: 2404206 | B54: Wong Wai Kwong | C54: 45386 | D54: Chean Bang | E54: R-PV | F54: NEM | G54: #VALUE! | H54: 8.19 | I54: - | K54: 31000 | M54: Cash + instalment | N54: Outright | O54: Astronergy 585Wp | P54: 14 | Q54: Huawei SUN2000-6KTL | S54: 790114-06-5467 | T54: No 55, Lrg Im 1/41, Tmn Putra Aman, 25200 Bandar Indera Mahkota, Pahang Darul Makmur | U54: 016-9233066 | V54: ww_kwong@yahoo.com.sg | W54: 3 years | X54: 1 year
A55: 2404226 | B55: Jimmy Kok Aik Lim | C55: 45396 | D55: Tham | E55: R-PV | F55: NEM | G55: #VALUE! | H55: 7.02 | I55: - | K55: 25100 | M55: Self finance | N55: Outright | O55: Astronergy 585Wp | P55: 12 | Q55: Huawei SUN2000-5KTL-L1 | S55: 621013-11-5109 | T55: 3 Jalan Telawi 7, Bangsar Baru, Bangsar,59100 Kuala Lumpur, WP Kuala Lumpur | U55: 012-3709905 | V55: lytan63@hotmail.com | W55: 3 years | X55: 1 year
A56: 2401063 | B56: Weller Air-Cond Parts Enterprise Sdn Bhd | C56: 45363 | D56: Tham | E56: C&I-PV | F56: NEM | G56: #VALUE! | H56: 26.91 | I56: - | K56: 82000 | M56: Self finance | N56: Outright | O56: Astronergy 585Wp | P56: 46 | Q56: Huawei SUN2000-20KTL | T56: Lot 8324, Kg Makau Bt 1, 43100 Hulu Langat, Selangor | W56: 3 years | X56: 1 year
A57: 2401069 | B57: Enviri Industries Sdn Bhd | C57: 45380 | D57: Tham | E57: C&I-PV | F57: NEM | G57: #VALUE! | H57: 290.4 | I57: - | K57: 668000 | L57: 2610 | M57: Self finance | N57: Outright | O57: Jinko Solar 575Wp | P57: 505 | Q57: Huawei SUN2000-100KTL x 2 Huawei SUN2000-36KTL x 1 | T57: PT71179, Jalan Lapis 2, 42100 Klang, Selangor | W57: 3 years | X57: 1 year
A58: 2402079 | B58: Intergreen Holdings Sdn Bhd | C58: 45394 | D58: Tham | E58: C&I-PV | F58: NEM | G58: #VALUE! | H58: 46.8 | I58: - | K58: 194600 | M58: Self finance | N58: Outright | O58: Astronergy 585Wp | P58: 80 | Q58: Huawei SUN2000-12KTL-M5 x 2 Huawei SUN2000-12KTL-MB0 x 1 | T58: Pusat Perdagangan Amcorp, 3, Jalan Timur, Seksyen 9, 46000 Petaling Jaya, Selangor | W58: 3 years | X58: 1 year
A59: 2402080 | B59: CK Fresh Sdn Bhd | C59: 45357 | D59: Tham | E59: C&I-PV | F59: SELCO | G59: #VALUE! | H59: 43.29 | I59: - | K59: 120000 | L59: 1500 | M59: Self finance | N59: Outright | O59: Astronergy 585Wp | P59: 74 | Q59: Huawei SUN2000-30KTL | T59: Lot 8393, Jln Air Hitam, Kelapa Sawit, 81000 Kulai, Johor | W59: 3 years | X59: 1 year
A60: 2312120 | B60: Ling Duon Kwan | C60: 45390 | D60: Tham | E60: R-PV | F60: NEM | G60: #VALUE! | H60: 7.605 | I60: - | K60: 27500 | M60: Self finance | N60: Outright | O60: Astronergy 585Wp | P60: 13 | Q60: Huawei SUN2000-6KTL | S60: 780817-13--5437 | T60: No 58, Jln TP 1/3, Tiara Putra, 47000 Sungai Buloh, Selangor Darul Ehsan | U60: 012-3799638 | V60: duncanling@yahoo.com | W60: 3 years | X60: 1 year
A61: 2311092 | B61: Tham Chee Man | C61: 45253 | D61: Tham | E61: R-PV | F61: NEM | G61: #VALUE! | H61: 5.75 | I61: - | K61: 22000 | M61: Self finance | N61: Outright | O61: Astronergy 575Wp | P61: 10 | Q61: Solinteg MHS-5K-30 hybrid | S61: 590601-06-5153 | T61: 33, Jalan Flora 3, Saujana Utama, 47000 Sungai Buloh, Selangor Darul Ehsan | U61: 017-9034540 | V61: thamcheongsheng@gmail.com | W61: 3 years | X61: 1 year
A62: 2404230 | B62: Yap Bee Im Marianne | C62: 45402 | D62: Tham | E62: R-PV | F62: NEM | G62: #VALUE! | H62: 8.775 | I62: - | K62: 32500 | L62: -2000 | M62: Self finance | N62: Outright | O62: Astronergy 585Wp | P62: 15 | Q62: Huawei SUN2000-8KTL | S62: 831021-14-6242 | T62: No 8, Jln Hijau Alam U9/14C, Cahaya SPK, Sek U9, 40150 Shah Alam, Selangor Darul Ehsan | U62: 012-3050288 | V62: marianneyap21@gmail.com | W62: 3 years | X62: 1 year
A63: 2401133 | B63: Cheong Sau Ling | C63: 45404 | D63: Tham | E63: R-PV | F63: NEM | G63: #VALUE! | H63: 8.775 | I63: - | K63: 34460 | M63: Credit Card Instalment | N63: Outright | O63: Astronergy 585Wp | P63: 15 | Q63: Huawei SUN2000-8KTL | S63: 740823-02-5825 | T63: 15, Jalan Kemuning Bayu 33/32L, Kemuning Utama,40400 Shah Alam, Selangor Darul Ehsan | U63: 013-7274135 | V63: lingling822@hotmail.my | W63: 3 years | X63: 1 year
A64: 2403171 | B64: Sim Keng Chor | C64: 45404 | D64: Tham | E64: R-PV | F64: NEM | G64: #VALUE! | H64: 17.55 | I64: - | K64: 52400 | M64: Credit Card Instalment | N64: Outright | O64: Astronergy 585Wp | P64: 30 | Q64: Huawei SUN2000-12KTL | S64: 470725-01-5629 | T64: 8, Lorong Kemaris 6, Bangsar Baru, 59100 Kuala Lumpur, WP Kuala Lumpur | U64: 012-2789488 | V64: simson@unitrade.com.my | W64: 3 years | X64: 1 year | Z64: Unitrade
A65: 2403176 | B65: Nor Hana binti Supiran @ Soviran | C65: 45406 | D65: Tham | E65: R-PV | F65: NEM | G65: #VALUE! | H65: 6.435 | I65: - | K65: 30500 | M65: Self finance | N65: Outright | O65: Astronergy 585Wp | P65: 11 | Q65: Huawei SUN2000-5KTL-M1 | S65: 801003-08-5944 | T65: Lot 84327, Lorong Merbau 1, Kampung Melayu, 68000 Ampang, Selangor Darul Ehsan | U65: 019-3170725 | V65: hanatrading78@yahoo.com | W65: 3 years | X65: 1 year | Z65: Bioserasi
A66: 2404229 | B66: Ng Lay Ping | C66: 45407 | D66: Tham | E66: R-PV | F66: NEM | G66: #VALUE! | H66: 14.625 | I66: - | K66: 41600 | L66: -1600 | M66: Self finance | N66: Outright | O66: Astronergy 585Wp | P66: 25 | Q66: Huawei SUN2000-12KTL | R66: 15 years | S66: 700919-10-5236 | T66: Lot 27838, Jln BRP 2/2C, Bkt Rahman Putra, 40160 Sungai Buloh, Selangor Darul Ehsan | U66: 012-3999903 | V66: lpng_lew@yahoo.com | W66: 3 years | X66: 1 year | AB66: Inverter Warranty Extend to 15 years
A67: 2404211 | B67: Nor Fadillah | C67: 45408 | D67: Tham | E67: R-PV | F67: NEM | G67: #VALUE! | H67: 17.55 | I67: - | K67: 49600 | M67: Self finance | N67: Outright | O67: Astronergy 585Wp | P67: 30 | Q67: Huawei SUN2000-12KTL | S67: 630327-04-5398 | T67: 17, Jalan Laman Jasmin 5A, Laman Jasmin, 71800 Nilai Negeri Sembilan Darul Khusus | U67: 016-2477797 | V67: drnorfadillah@gmail.com | W67: 3 years | X67: 1 year
A68: 2404111 | B68: Budi Jelas Sdn Bhd | C68: 45407 | D68: Tham | E68: C&I-PV | F68: NEM | G68: #VALUE! | H68: 26.91 | I68: - | K68: 81000 | M68: Self finance | N68: Outright | O68: Astronergy 585Wp | P68: 46 | Q68: Huawei SUN2000-20KTL | T68: PT 12887, Kaw Asan Perindustrian LKNP Benus, 28700 Bentong, Pahang | W68: 3 years | X68: 1 year
A69: 2404219 | B69: Billy Teoh Wee Wei | C69: 45412 | D69: Tham | E69: R-PV | F69: NEM | G69: #VALUE! | H69: 17.55 | I69: - | K69: 52000 | M69: Cash + instalment | N69: Outright | O69: Astronergy 585Wp | P69: 30 | Q69: Huawei SUN2000-12KTL | S69: 830811-07-5405 | T69: No 5082, Lrg Bagan Vista, Jln Telaga Air, 12200 Butterworth Pulau Pinang | U69: 012-4215656 | V69: billyteoh19@hotmail.com | W69: 3 years | X69: 1 year | Z69: Unitrade
A70: 2404214 | B70: Teo En Chie | C70: 45414 | D70: Tham | E70: R-PV | F70: NEM | G70: #VALUE! | H70: 15.795 | I70: - | K70: 48200 | M70: Credit Card Instalment | N70: Outright | O70: Astronergy 585Wp | P70: 27 | Q70: Huawei SUN2000-12KTL | S70: 910530-01-6505 | T70: 18, Jalan Senibong 1, Teluk Senibong, 81750 Masai, Johor Darul Takzim | U70: 010-8820636 | V70: enchie@live.com.my | W70: 3 years | X70: 1 year | Z70: Unitrade
A71: 2403102 | B71: Sleep Matics (Asia) Sdn Bhd | C71: 45415 | D71: Tham | E71: C&I-PV | F71: NEM | G71: #VALUE! | H71: 374.4 | I71: - | K71: 744800 | M71: Self finance | N71: Outright | O71: Astronergy 585Wp | P71: 640 | Q71: Huawei SUN2000-115KTL x 2 Huawei SUN2000-50KTL x 1 | T71: Lot 37133, Kg Baru Sg Buloh, 47000 Sungai Buloh, Selangor | W71: N/A | X71: 1 year | Z71: Unitrade
A72: 2312059 | B72: CHL Foam Industries Sdn Bhd | C72: 45415 | D72: Tham | E72: C&I-PV | F72: NEM | G72: #VALUE! | H72: 345.15 | I72: - | K72: 690300 | L72: 130000 | M72: Self finance | N72: Outright | O72: Astronergy 585Wp | P72: 590 | Q72: Huawei SUN2000-115KTL x 2 Huawei SUN2000-30KTL x 1 | T72: Lot 37174, Kg Baru Sg Buloh, 47000 Sungai Buloh, Selangor | W72: N/A | X72: 1 year | Z72: Unitrade
A73: 2404255 | B73: Ong Pui Fen | C73: 45424 | D73: Tham | E73: R-PV | F73: NEM | G73: #VALUE! | H73: 7.605 | I73: - | K73: 30260 | M73: Credit Card Instalment | N73: Outright | O73: Astronergy 585Wp | P73: 13 | Q73: Huawei SUN2000-6KTL | S73: 760801-04-5180 | T73: 51, Jalan USJ 2/5H, USJ 2, 47600 Subang Jaya, Selangor Darul Ehsan | U73: 016-2100039 | V73: tattmun@gmail.com | W73: 3 years | X73: 1 year
A74: 2404242 | B74: Chua Boon Seng | C74: 45408 | D74: Azra | E74: R-PV | F74: NEM | G74: #VALUE! | H74: 10.53 | I74: - | K74: 35000 | M74: Credit Card Instalment | N74: Outright | O74: Astronergy 585Wp | P74: 21 | Q74: Huawei SUN2000-8KTL | S74: 750927-06-5137 | T74: No 1B, Lrg Seri Kuantan 28/1, Kuantan Garden, 25300 Kuantan, Pahang Darul Makmur | U74: 018-9094538 | V74: cboonhuang@gmail.com | W74: 3 years | X74: 1 year
A75: 2405272 | B75: Chan Hui Li | C75: 45427 | D75: Tham | E75: R-PV | F75: NEM | G75: #VALUE! | H75: 9.36 | I75: - | K75: 32180 | M75: Self finance | N75: Outright | O75: Astronergy 585Wp | P75: 16 | Q75: Huawei SUN2000-8KTL | S75: 700521-06--5318 | T75: No 111, Lrg Air Putih 21, Jln Air Putih, Tmn Dahlia Astana, 25350 Kuantan, Pahang Darul Makmur | U75: 012-2392000 | V75: conniechan2105@yahoo.com | W75: 3 years | X75: 1 year | Z75: Unitrade
A76: 2405266 | B76: Goh Wee Bang (Goh Swee Teng) | C76: 45432 | D76: Tham | E76: R-PV | F76: NEM | G76: #VALUE! | H76: 13.455 | I76: - | K76: 41000 | M76: Self finance | N76: Outright | O76: Astronergy 585Wp | P76: 23 | Q76: Huawei SUN2000-10KTL | S76: 750605-10-5255 | T76: No 12A, Jln Cokmar 2 K, Tmn Mutiara Bkt Raja, 41050 Klang, Selangor Darul Ehsan | U76: 012-2313922 | V76: vbangoh1975@gmail.com | W76: 3 years | X76: 1 year
A77: 2405280 | B77: Teoh Kah Ming | C77: 45422 | D77: Tham | E77: R-PV | F77: NEM | G77: #VALUE! | H77: 9.36 | I77: - | K77: 34600 | M77: Credit Card Instalment | N77: Outright | O77: Astronergy 585Wp | P77: 16 | Q77: Huawei SUN2000-8KTL | S77: 880326-14-5807 | T77: No 5, Jln Kemuning Indah 32/141J, Kemuning Utama, 40460 Shah Alam, Selangor Darul Ehsan | U77: 012-6777309 | V77: kahming.teoh@gmail.com | W77: 3 years | X77: 1 year
A78: 2405294 | B78: Gan Wei Kuan | C78: Cancelled | D78: Tham | H78: 7.02 | I78: - | K78: 25100 | M78: Self finance | N78: Outright | O78: Astronergy 585Wp | P78: 12 | Q78: Huawei SUN2000-5KTL-L1 | W78: 3 years | X78: 1 year
A79: 2405296 | B79: Haiu Chan Lai | C79: 45414 | D79: Tham | E79: R-PV | F79: NEM | G79: #VALUE! | H79: 8.775 | I79: - | K79: 32000 | M79: Self finance | N79: Outright | O79: Astronergy 585Wp | P79: 15 | Q79: Huawei SUN2000-8KTL | S79: 670120-11-5324 | T79: 41, Jln Daun Inai 7, Sunway SPK Damansara, 52200 Kuala Lumpur, WP Kuala Lumpur | U79: 012-3760333 | V79: jacquelinehaiu@gmail.com | W79: 3 years | X79: 1 year | Z79: Unitrade
A80: 2405307 | B80: Shreeram Nadarajah | C80: 45434 | D80: Tham | E80: R-PV | F80: NEM | G80: #VALUE! | H80: 8.19 | I80: - | K80: 28000 | L80: 4600 | M80: Self finance | N80: Outright | O80: Astronergy 585Wp | P80: 14 | Q80: Huawei SUN2000-6KTL | S80: 760726-14-5391 | T80: 123, Jalan Terasek 1, Bangsar Baru, Bangsar, 59100 Kuala Lumpur, WP Kuala Lumpur | U80: 019-2619729 | V80: shreeram.nadarajah@gmail.com | W80: 1 year | X80: 1 year | Z80: Unitrade
A81: 2404227 | B81: Datin Tai Bee Choon | C81: 45442 | D81: Tham | E81: R-PV | F81: NEM | G81: #VALUE! | H81: 17.55 | I81: - | K81: 52400 | M81: Self finance | N81: Outright | O81: Astronergy 585Wp | P81: 30 | Q81: Huawei SUN2000-12KTL | S81: 760817-01-5584 | T81: No 16, Jln Setia Tropika 15/1, Tmn Setia Tropika, 81200 Johor Bahru. Johor Darul Takzim | U81: 013-8222255 | V81: datoivan@ungguhgroup.com | W81: 3 years | X81: 1 year | Z81: Unitrade
A82: 2405315 | B82: Yeap Say Woei | C82: 45446 | D82: Tham | E82: R-PV | F82: NEM | G82: #VALUE! | H82: 13.455 | I82: - | K82: 40000 | M82: Self finance | N82: Outright | O82: Astronergy 585Wp | P82: 23 | Q82: Huawei SUN2000-10KTL | S82: 800117-02-5697 | T82: 10, Bukit Dumbar Residences, Lorong Batu Gajah, 11600 Jelutong, Pulau Pinang | U82: 012-4776246 | V82: saywoei@yahoo.com | W82: 3 years | X82: 1 year | Z82: Unitrade
A83: 2405319 | B83: Tan Zhi Cheng | C83: 45445 | D83: Tham | E83: R-PV | F83: NEM | G83: #VALUE! | H83: 7.02 | I83: - | K83: 26240 | M83: Self finance | N83: Outright | O83: Astronergy 585Wp | P83: 12 | Q83: Huawei SUN2000-5KTL-L1 | S83: 840518-09-5203 | T83: 15, Jalan BK 2/7, Bandar Kinrara, 47180 Puchong, Selangor Darul Ehsan | U83: 016-4010372 | V83: tzcheng07@gmail.com | W83: 3 years | X83: 1 year | Z83: Unitrade
A84: 2405288 | B84: Teh Siew Eng | C84: 45440 | D84: Tham | E84: R-PV | F84: NEM | G84: #VALUE! | H84: 12.285 | I84: - | K84: 41840 | M84: Self finance | N84: Outright | O84: Astronergy 585Wp | P84: 21 | Q84: Huawei SUN2000-10KTL | S84: 531030-08-5440 | T84: No 49, Jln Kasipillay, 51200 Kuala Lumpur, WP Kuala Lumpur | U84: 012-2290951 | V84: fattychuah@gmail.com | W84: 3 years | X84: 1 year | Z84: Unitrade
A85: 2404256 | B85: Lai Chun Wai | C85: 45464 | D85: Azra | E85: R-PV | F85: NEM | G85: #VALUE! | H85: 8.775 | I85: - | K85: 33100 | M85: Self finance | N85: Outright | O85: Astronergy 585Wp | P85: 14 | Q85: Solinteg MHT-8K-25 hybrid | S85: 711015-14-5159 | T85: No 31, Lrg Sri Kuantan 55, Tmn Timur, 25150 Kuantan, Pahang Darul Makmur | U85: 012-3879932 | V85: chunwai103@gmail.com | W85: 3 years | X85: 1 year
A86: 2406323 | B86: Tay Poh Chai | C86: 45457 | D86: Tham | E86: R-PV | F86: NEM | G86: #VALUE! | H86: 14.04 | I86: - | K86: 40000 | M86: Self finance | N86: Outright | O86: Astronergy 585Wp | P86: 24 | Q86: Huawei SUN2000-12KTL | S86: 730209-04-5037 | T86: 53, Jalan Saujana Duta 7, Saujana Duta, Seremban 2 Heights, 70300 Seremban, Negeri Sembilan Darul Khusus | U86: 019-6616826 | V86: alextaypohchai@hotmail.com | W86: 3 years | X86: 1 year
A87: 2406336 | B87: Alex How Chee Keong | C87: 45462 | D87: Tham | E87: R-PV | F87: NEM | G87: #VALUE! | H87: 11.7 | I87: - | K87: 31000 | M87: Self finance | N87: Outright | O87: Astronergy 585Wp | P87: 20 | Q87: Huawei SUN2000-10KTL | S87: 770202-14-5437 | T87: Unit 16, Zenia Jalan Residen 2, Desa Parkcity, 52200 Kuala Lumpur, WP Kuala Lumpur | U87: 012-3453457 | V87: keongko@hotmail.com | W87: 1 year | X87: 1 year | Z87: Unitrade
A88: 2406340 | B88: How Mei Cheng | C88: 45464 | D88: Tham | E88: R-PV | F88: NEM | G88: #VALUE! | H88: 7.02 | I88: - | K88: 24100 | M88: Self finance | N88: Outright | O88: Astronergy 585Wp | P88: 12 | Q88: Huawei SUN2000-5KTL-L1 | S88: 811203-14-5656 | T88: 2-134, Jalan Udang Ketak, Taman Sri Segambut, 52000 Kuala Lumpur, WP Kuala Lumpur | U88: 012-2012123 | V88: joe_hmc@hotmail.com | W88: 3 years | X88: 1 year | Z88: Unitrade
A89: 2406355 | B89: Windy Ng | C89: 45471 | D89: Tham | E89: R-PV | F89: NEM | G89: #VALUE! | H89: 9.36 | I89: - | K89: 27000 | L89: -1872 | M89: Self finance | N89: Outright | O89: Astronergy 585Wp | P89: 16 | Q89: Huawei SUN2000-8KTL | S89: 820717-01-5204 | T89: 13, Jalan U13/53H, Eco Ardence, Seksyen U13, 40170 Shah Alam, Selangor Darul Ehsan | U89: 017-7753119 | V89: yellowwindy@hotmail.com | W89: N/A | X89: 1 year
A90: 2406357 | B90: Zainuddin Zin | C90: 45471 | D90: Patricia | E90: R-PV | F90: NEM | G90: #VALUE! | H90: 12.285 | I90: - | K90: 38000 | M90: Self finance | N90: Outright | O90: Astronergy 585Wp | P90: 21 | Q90: Huawei SUN2000-10KTL | S90: 590911-06-5319 | T90: 8, Lrg Kg Panching 10, Kg Panching, 26090 Kuantan, Pahang Darul Makmur | U90: 019-9774850 | V90: zainudinzin@gmail.com | W90: 5 years | X90: 1 year
A91: 2405019 | B91: Handal Green Mobility Sdn Bhd (Encore Melaka) | C91: 45463 | D91: Simon | E91: EV Charger | F91: - | G91: #VALUE! | H91: 0 | I91: 240 | K91: 90800 | M91: Cash | N91: Outright | O91: - | P91: - | Q91: - | S91: - | T91: No 3, Jalan KSB - Impression 8, Impression City @ Kota Syahbandar, 75200 Melaka | U91: - | V91: - | W91: N/A | X91: 1 year
A92: 2406358 | B92: Kwan Li Shan | C92: 45474 | D92: Tham | E92: R-PV | F92: NEM | G92: #VALUE! | H92: 9.36 | I92: - | K92: 30000 | M92: Self finance | N92: Outright | O92: Astronergy 585Wp | P92: 16 | Q92: Huawei SUN2000-8KTL | S92: 800718-08-5978 | T92: Lot 387509, Laluan Sri Ampang 2, Kampung Sri Ampang, 31350 Ipoh, Perak Darul Ridzuan | U92: 012-5142483 | V92: lishankwan@gmail.com | W92: 3 years | X92: 1 year
A93: 2407360 | B93: Liau Hui Kiem | C93: 45491 | D93: Tham | E93: R-PV | F93: NEM | G93: #VALUE! | H93: 14.04 | I93: - | K93: 45020 | M93: Credit Card Instalment | N93: Outright | O93: Astronergy 585Wp | P93: 24 | Q93: Huawei SUN2000-12KTL | S93: 780419-10-5734 | T93: 20, Jalan Setia Damai U13/15F, Setia Alam 40170 Shah Alam, Selangor Darul Ehsan | U93: 019-2338688 | V93: hkliau8688@gmail.com | W93: 3 years | X93: 1 year
A94: 2407364 | B94: Mohd Nasir Man | C94: 45481 | D94: Patricia | E94: R-PV | F94: NEM | G94: #VALUE! | H94: 8.19 | I94: - | K94: 25000 | M94: Self finance | N94: Outright | O94: Astronergy 585Wp | P94: 14 | Q94: Huawei SUN2000-6KTL | S94: 640103-09-5029 | T94: No B3075, Jln Beserah, Tmn Multiply, 25300 Kuantan, Pahang Darul Makmur | U94: 012-9003767 | V94: mnasirman17@gmail.com | W94: N/A | X94: 1 year
A95: 2407375 | B95: Tan Ger Ber | C95: 45485 | D95: Tham | E95: R-PV | F95: NEM | G95: #VALUE! | H95: 14.04 | I95: - | K95: 39980 | M95: Credit Card Instalment | N95: Outright | O95: Astronergy 585Wp | P95: 24 | Q95: Huawei SUN2000-12KTL | S95: 560608-01-6090 | T95: 10, Jalan Kenyalang 11/15G, Seksyen 11, Kota Damansara, 47810, Petaling Jaya, Selangor Darul Ehsan | U95: 012-5273664 | V95: tangerber@gmail.com | W95: 3 years | X95: 1 year | Z95: Unitrade
A96: 2407379 | B96: Ng Boon Kiat (Daniel) | C96: 45484 | D96: Chean Bang | E96: R-PV | F96: NEM | G96: #VALUE! | H96: 5.265 | I96: - | K96: 22860 | M96: Cash + Credit Card Instalment | N96: Outright | O96: Astronergy 585Wp | P96: 9 | Q96: Solinteg MHS-5K-30 hybrid | S96: 840903-01-5679 | T96: No 4, Jalan KS 14/12, Kota Sultan Ahmad Shah, 25200 Kuantan, Pahang | U96: 012-6121112 | V96: danielngbk84@gmail.com | W96: N/A | X96: 1 year
A97: 2407380 | B97: How Yee Seun | C97: 45486 | D97: Tham | E97: R-PV | F97: NEM | G97: #VALUE! | H97: 12.87 | I97: - | K97: 38000 | M97: Self finance | N97: Outright | O97: Astronergy 585Wp | P97: 22 | Q97: Huawei SUN2000-10KTL | S97: 840202-06-5008 | T97: 32A, Jalan Aman Arahsia 7, Bandar Tropicana Aman, 42500 Telok Panglima Garang, Selangor Darul Ehsan | U97: 012-9370766 | V97: yeesuen02@yahoo.com | W97: 3 years | X97: 1 year | Z97: Unitrade
A98: 2407381 | B98: Lau Ah Leng | C98: 45486 | D98: Tham | E98: R-PV | F98: NEM | G98: #VALUE! | H98: 12.285 | I98: - | K98: 36680 | M98: Self finance | N98: Outright | O98: Astronergy 585Wp | P98: 21 | Q98: Huawei SUN2000-10KTL | S98: 550425-02-5403 | T98: 19, Jln Kenyalang 11/15I, Seksyen 11, Kota Damansara, 47810 Petaling Jaya, Selangor Darul Ehsan | U98: 019-3128863 | V98: allan@gmail.com | W98: 3 years | X98: 1 year | Z98: Unitrade
A99: 2407382 | B99: Leong Tack Ming | C99: 45488 | D99: Tham | E99: R-PV | F99: NEM | G99: #VALUE! | H99: 8.775 | I99: - | K99: 29840 | M99: Credit Card Instalment | N99: Outright | O99: Astronergy 585Wp | P99: 15 | Q99: Huawei SUN2000-8KTL | S99: 530501-05-5607 | T99: 3, Jalan SS 22/24, Damansara jaya. 47400 Petaling Jaya, Selangor | U99: 012-2011132 | W99: 3 years | X99: 1 year | Z99: Unitrade
A100: 2407383 | B100: Charles Lew Chow Leng | C100: 45488 | D100: Tham | E100: R-PV | F100: NEM | G100: #VALUE! | H100: 14.04 | I100: - | K100: 39980 | M100: Self finance | N100: Outright | O100: Astronergy 585Wp | P100: 24 | Q100: Huawei SUN2000-12KTL | S100: 620529-07-5406 | T100: 6, Jalan Kenyalang 11/15A, Seksyen 11, Kota Damansara, 47810 Petaling Jaya, Selangor Darul Ehsan | U100: 012-3999189 | V100: clew62@gmail.com | W100: 3 years | X100: 1 year | Z100: Unitrade
A101: 2407384 | B101: Loh Fook Khew | C101: 45488 | D101: Tham | E101: R-PV | F101: NEM | G101: #VALUE! | H101: 12.285 | I101: - | K101: 36800 | M101: Self finance | N101: Outright | O101: Astronergy 585Wp | P101: 21 | Q101: Huawei SUN2000-10KTL | S101: 560512-08-5307 | T101: 8, Jalan Kenyalang 11/15A, Seksyen 11, Kota Damansara, 47810 Petaling Jaya, Selangor Darul Ehsan | U101: 012-3351801 | V101: chinmei_fashion@hotmail.com | W101: 3 years | X101: 1 year | Z101: Unitrade
A102: 2407385 | B102: Cheong Chin Meng | C102: 45488 | D102: Chean Bang | E102: R-PV | F102: NEM | G102: #VALUE! | H102: 15.21 | I102: - | K102: 45600 | M102: Self finance | N102: Outright | O102: Astronergy 585Wp | P102: 26 | Q102: Solinteg MHT-12K-25 hybrid | S102: 730422-06-5301 | T102: 145, Jln Bkt Setongkol 3, Tmn Muhibah FAS, Bukit Setongkol, 25200 Kuantan, Pahang Darul Makmur | U102: 012-9103893 | V102: ioienterprisektn@gmail.com | W102: 3 years | X102: 1 year
A103: 2310035 | B103: Advantic Nutraceuticals | C103: 45793 | D103: Tham | E103: C&I-PV | F103: NEM | G103: #VALUE! | H103: 87.84 | I103: - | K103: 188000 | M103: Self finance | N103: Outright | O103: Astronergy 610Wp | P103: 144 | Q103: Huawei SUN2000-30KTL + Huawei SUN2000-36KTL | W103: 3 years | X103: 1 year | Y103: Full O&M - 3 years
...

Sheet Data
A2: Sales PIC | B2: Category | C2: Scheme | D2: Payment Method | E2: Location | F2: Finance | G2: DLP | H2: O&M | I2: Insurance
A3: Chean Bang | B3: R-PV | C3: NEM | D3: Cash | E3: #VALUE! | F3: Outright | G3: 1 year | H3: N/A | I3: N/A
A4: Simon | B4: C&I-PV | C4: SELCO | D4: Credit Card Instalment | E4: #VALUE! | F4: PPA | G4: 2 years | H4: On site checking - 1 year | I4: 1 year
A5: Tham | B5: R-BESS | C5: ATAP | D5: Cash + CC Instalment | E5: #VALUE! | G5: 3 years | H5: On site checking - 2 years | I5: 2 years
A6: Patricia | B6: C&I-BESS | E6: #VALUE! | G6: 4 years | H6: On site checking - 3 years | I6: 3 years
A7: Ong | B7: EV Charger | E7: #VALUE! | G7: 5 years | H7: Full O&M - 1 year | I7: 4 years
A8: Reeve | E8: #VALUE! | G8: 6 years | H8: Full O&M - 2 years | I8: 5 years
E9: #VALUE! | G9: 7 years | H9: Full O&M - 3 years | I9: 6 years
E10: #VALUE! | G10: 8 years | H10: Full O&M - 4 years | I10: 7 years
E11: #VALUE! | G11: 9 years | H11: Full O&M - 5 years | I11: 8 years
E12: #VALUE! | G12: 10 years | H12: Full O&M - 6 years | I12: 9 years
E13: #VALUE! | H13: Full O&M - 7 years | I13: 10 years
E14: #VALUE! | H14: Full O&M - 8 years
E15: #VALUE! | H15: Full O&M - 9 years
E16: #VALUE! | H16: Full O&M - 10 years
H17: Others
A26: SEDA Status
A27: Documents Provided
A28: Waiting for Fee Payment
A29: Waiting for Verification
A30: Waiting for Verification (Update)
A31: Waiting for TNB Confirmation
A32: Approved - Waiting for Certificate
A33: Certificate Generated
A34: Application Withdrawal
A35: Application Rejected
A36: Completed Project Milestones
A37: NEM Commencement Date

Sheet ECN Master Project Tracker new
O3: TNB-CAS | R3: SEDA | AB3: TNB (NEM Meter Change )
A4: Project No | B4: Client Name | C4: Location | D4: Sales PIC | E4: Category | F4: Scheme | G4: System Capacity | H4: Module | I4: Module Quantity | J4: Inverter | L4: Project Status | M4: Payment Status | O4: CAS Application | P4: CAS Approval | R4: NEM Quota Submission | S4: NEM Quota Approval | T4: NEM Quota Status | U4: NEMCD | V4: Site Survey | W4: Material Readiness | X4: RSA Result | Y4: Engineering Design | Z4: Installer | AA4: Installation Date | AB4: NEM Meter Change/ Contract Submission | AC4: TNB Portal Status | AD4: Status Date | AE4: Meter Change Payment | AF4: NEM Meter Change | AG4: NEM Welcome Letter | AH4: NEM Term End Date | AJ4: ST License Application | AK4: ST License Approval | AL4: GITA Application | AM4: GITA Approval | AQ4: Close to Instaallation
A5: =Table1[[#This Row],[Project No]] -> 2303005 | B5: =VLOOKUP(A:A,Table1[[Project No]:[Additional Remark]],2,FALSE) -> Wong Kim Mei | C5: =VLOOKUP(A:A,Table1[[#All],[Project No]:[Additional Remark]],7,FALSE) -> #VALUE! | D5: =VLOOKUP(A:A,Table1[[#All],[Project No]:[Additional Remark]],4,FALSE) -> Simon | E5: =VLOOKUP(A:A,Table1[[#All],[Project No]:[Additional Remark]],5,FALSE) -> R-PV | F5: =VLOOKUP(A:A,Table1[[Project No]:[Additional Remark]],6,FALSE) -> NEM | G5: =VLOOKUP(A:A,Table1[[Project No]:[Additional Remark]],8,FALSE) -> 8.05 | H5: =VLOOKUP(A:A,Table1[[Project No]:[Additional Remark]],15,FALSE) -> Astronergy 575Wp | I5: =VLOOKUP(A:A,Table1[[Project No]:[Additional Remark]],16,FALSE) -> 14 | J5: =VLOOKUP(A:A,Table1[[Project No]:[Additional Remark]],17,FALSE) -> Solinteg MHT-8K-25 hybrid | L5: =IF(ISBLANK(R5),"Pending NEM Qouta Submission",IF(ISBLANK(S5),"Pending NEM Qouta Approval",IF(ISBLANK(AA5),"Pending Site Installation",IF(ISBLANK(AJ5),"Pending ST License Application",IF(ISBLANK(AK5),"Pending ST License Approval", IF(ISBLANK(AB5),"Pending Meter Change Application",IF(AND(ISBLANK(AG5),ISBLANK(AF5)),"Pending Meter Change",IF(ISBLANK(AG5),"Pending NEM Welcome Letter",IF(ISBLANK(AL5),"Pending GITA Application",IF(ISBLANK(AM5),"Pending GITA Approval","Completed")))))))))) -> Completed | M5: =VLOOKUP(A:A,'Finance Tracker'!A3:K249,8,FALSE) -> Invoice Completed | O5: N/A | P5: N/A | R5: 45113 | S5: 45143 | T5: Completed Project Milestones | U5: 45441 | V5: Completed | W5: Completed | X5: N/A | Y5: Completed | Z5: Completed | AA5: Completed | AB5: Completed | AC5: Completed | AD5: Completed | AE5: Completed | AF5: 45175 | AG5: 45175 | AH5: 48852 | AJ5: N/A | AK5: N/A | AL5: N/A | AM5: N/A | AP5: =S5-R5 -> 30 | AQ5: =AA5-Table1[[#This Row],[Closed Date]] -> #VALUE!
A6: =Table1[[#This Row],[Project No]] -> 2303006 | B6: =VLOOKUP(A:A,Table1[[Project No]:[Additional Remark]],2,FALSE) -> Ang Ching Ming | C6: =VLOOKUP(A:A,Table1[[#All],[Project No]:[Additional Remark]],7,FALSE) -> #VALUE! | D6: =VLOOKUP(A:A,Table1[[#All],[Project No]:[Additional Remark]],4,FALSE) -> Simon | E6: =VLOOKUP(A:A,Table1[[#All],[Project No]:[Additional Remark]],5,FALSE) -> R-PV | F6: =VLOOKUP(A:A,Table1[[Project No]:[Additional Remark]],6,FALSE) -> NEM | G6: =VLOOKUP(A:A,Table1[[Project No]:[Additional Remark]],8,FALSE) -> 12.65 | H6: =VLOOKUP(A:A,Table1[[Project No]:[Additional Remark]],15,FALSE) -> Astronergy 575Wp | I6: =VLOOKUP(A:A,Table1[[Project No]:[Additional Remark]],16,FALSE) -> 22 | J6: =VLOOKUP(A:A,Table1[[Project No]:[Additional Remark]],17,FALSE) -> Solinteg MHT-10K-25 hybrid | L6: =IF(ISBLANK(R6),"Pending NEM Qouta Submission",IF(ISBLANK(S6),"Pending NEM Qouta Approval",IF(ISBLANK(AA6),"Pending Site Installation",IF(ISBLANK(AJ6),"Pending ST License Application",IF(ISBLANK(AK6),"Pending ST License Approval", IF(ISBLANK(AB6),"Pending Meter Change Application",IF(AND(ISBLANK(AG6),ISBLANK(AF6)),"Pending Meter Change",IF(ISBLANK(AG6),"Pending NEM Welcome Letter",IF(ISBLANK(AL6),"Pending GITA Application",IF(ISBLANK(AM6),"Pending GITA Approval","Completed")))))))))) -> Completed | M6: =VLOOKUP(A:A,'Finance Tracker'!A4:K250,8,FALSE) -> Pending 1st Invoice | O6: N/A | P6: N/A | R6: 45086 | S6: 45104 | T6: NEM Commencement Date | U6: 45451 | V6: Completed | W6: Completed | X6: N/A | Y6: Completed | Z6: Completed | AA6: Completed | AB6: Completed | AC6: Completed | AD6: Completed | AE6: Completed | AF6: 45226 | AG6: 45226 | AH6: 48883 | AJ6: N/A | AK6: N/A | AL6: N/A | AM6: N/A | AP6: =S6-R6 -> 18 | AQ6: =AA6-Table1[[#This Row],[Closed Date]] -> #VALUE!
A7: =Table1[[#This Row],[Project No]] -> 2304016 | B7: =VLOOKUP(A:A,Table1[[Project No]:[Additional Remark]],2,FALSE) -> Tan Sei Choon | C7: =VLOOKUP(A:A,Table1[[#All],[Project No]:[Additional Remark]],7,FALSE) -> #VALUE! | D7: =VLOOKUP(A:A,Table1[[#All],[Project No]:[Additional Remark]],4,FALSE) -> Chean Bang | E7: =VLOOKUP(A:A,Table1[[#All],[Project No]:[Additional Remark]],5,FALSE) -> R-PV | F7: =VLOOKUP(A:A,Table1[[Project No]:[Additional Remark]],6,FALSE) -> SELCO | G7: =VLOOKUP(A:A,Table1[[Project No]:[Additional Remark]],8,FALSE) -> 8.05 | H7: =VLOOKUP(A:A,Table1[[Project No]:[Additional Remark]],15,FALSE) -> Astronergy 575Wp | I7: =VLOOKUP(A:A,Table1[[Project No]:[Additional Remark]],16,FALSE) -> 14 | J7: =VLOOKUP(A:A,Table1[[Project No]:[Additional Remark]],17,FALSE) -> Solinteg MHT-8K-25 hybrid | L7: =IF(ISBLANK(R7),"Pending NEM Qouta Submission",IF(ISBLANK(S7),"Pending NEM Qouta Approval",IF(ISBLANK(AA7),"Pending Site Installation",IF(ISBLANK(AJ7),"Pending ST License Application",IF(ISBLANK(AK7),"Pending ST License Approval", IF(ISBLANK(AB7),"Pending Meter Change Application",IF(AND(ISBLANK(AG7),ISBLANK(AF7)),"Pending Meter Change",IF(ISBLANK(AG7),"Pending NEM Welcome Letter",IF(ISBLANK(AL7),"Pending GITA Application",IF(ISBLANK(AM7),"Pending GITA Approval","Completed")))))))))) -> Completed | M7: =VLOOKUP(A:A,'Finance Tracker'!A5:K251,8,FALSE) -> Invoice Completed | O7: N/A | P7: N/A | R7: N/A | S7: N/A | T7: N/A | U7: N/A | V7: Completed | W7: Completed | X7: N/A | Y7: Completed | Z7: Completed | AA7: Completed | AB7: N/A | AC7: N/A | AD7: N/A | AE7: N/A | AF7: N/A | AG7: N/A | AH7: N/A | AJ7: N/A | AK7: N/A | AL7: N/A | AM7: N/A | AP7: =S7-R7 -> #VALUE! | AQ7: =AA7-Table1[[#This Row],[Closed Date]] -> #VALUE!
A8: =Table1[[#This Row],[Project No]] -> 2305021 | B8: =VLOOKUP(A:A,Table1[[Project No]:[Additional Remark]],2,FALSE) -> Ho Hon Kit | C8: =VLOOKUP(A:A,Table1[[#All],[Project No]:[Additional Remark]],7,FALSE) -> #VALUE! | D8: =VLOOKUP(A:A,Table1[[#All],[Project No]:[Additional Remark]],4,FALSE) -> Simon | E8: =VLOOKUP(A:A,Table1[[#All],[Project No]:[Additional Remark]],5,FALSE) -> R-PV | F8: =VLOOKUP(A:A,Table1[[Project No]:[Additional Remark]],6,FALSE) -> NEM | G8: =VLOOKUP(A:A,Table1[[Project No]:[Additional Remark]],8,FALSE) -> 4.65 | H8: =VLOOKUP(A:A,Table1[[Project No]:[Additional Remark]],15,FALSE) -> Astronergy 575Wp | I8: =VLOOKUP(A:A,Table1[[Project No]:[Additional Remark]],16,FALSE) -> 8 | J8: =VLOOKUP(A:A,Table1[[Project No]:[Additional Remark]],17,FALSE) -> Solinteg MHS-3.6K-30 hybrid | L8: =IF(ISBLANK(R8),"Pending NEM Qouta Submission",IF(ISBLANK(S8),"Pending NEM Qouta Approval",IF(ISBLANK(AA8),"Pending Site Installation",IF(ISBLANK(AJ8),"Pending ST License Application",IF(ISBLANK(AK8),"Pending ST License Approval", IF(ISBLANK(AB8),"Pending Meter Change Application",IF(AND(ISBLANK(AG8),ISBLANK(AF8)),"Pending Meter Change",IF(ISBLANK(AG8),"Pending NEM Welcome Letter",IF(ISBLANK(AL8),"Pending GITA Application",IF(ISBLANK(AM8),"Pending GITA Approval","Completed")))))))))) -> Completed | M8: =VLOOKUP(A:A,'Finance Tracker'!A6:K251,8,FALSE) -> Pending 1st Invoice | O8: N/A | P8: N/A | R8: 45083 | S8: 45104 | T8: NEM Commencement Date | U8: 45451 | V8: Completed | W8: Completed | X8: N/A | Y8: Completed | Z8: Completed | AA8: Completed | AB8: Completed | AC8: Completed | AD8: Completed | AE8: Completed | AF8: 45182 | AG8: 45182 | AH8: 48852 | AJ8: N/A | AK8: N/A | AL8: N/A | AM8: N/A | AP8: =S8-R8 -> 21 | AQ8: =AA8-Table1[[#This Row],[Closed Date]] -> #VALUE!
A9: =Table1[[#This Row],[Project No]] -> 2305026 | B9: =VLOOKUP(A:A,Table1[[Project No]:[Additional Remark]],2,FALSE) -> Stanley Ang Leng Chuan | C9: =VLOOKUP(A:A,Table1[[#All],[Project No]:[Additional Remark]],7,FALSE) -> #VALUE! | D9: =VLOOKUP(A:A,Table1[[#All],[Project No]:[Additional Remark]],4,FALSE) -> Simon | E9: =VLOOKUP(A:A,Table1[[#All],[Project No]:[Additional Remark]],5,FALSE) -> R-PV | F9: =VLOOKUP(A:A,Table1[[Project No]:[Additional Remark]],6,FALSE) -> NEM | G9: =VLOOKUP(A:A,Table1[[Project No]:[Additional Remark]],8,FALSE) -> 12.65 | H9: =VLOOKUP(A:A,Table1[[Project No]:[Additional Remark]],15,FALSE) -> Astronergy 575Wp | I9: =VLOOKUP(A:A,Table1[[Project No]:[Additional Remark]],16,FALSE) -> 22 | J9: =VLOOKUP(A:A,Table1[[Project No]:[Additional Remark]],17,FALSE) -> Solinteg MHT-10K-25 hybrid | L9: =IF(ISBLANK(R9),"Pending NEM Qouta Submission",IF(ISBLANK(S9),"Pending NEM Qouta Approval",IF(ISBLANK(AA9),"Pending Site Installation",IF(ISBLANK(AJ9),"Pending ST License Application",IF(ISBLANK(AK9),"Pending ST License Approval", IF(ISBLANK(AB9),"Pending Meter Change Application",IF(AND(ISBLANK(AG9),ISBLANK(AF9)),"Pending Meter Change",IF(ISBLANK(AG9),"Pending NEM Welcome Letter",IF(ISBLANK(AL9),"Pending GITA Application",IF(ISBLANK(AM9),"Pending GITA Approval","Completed")))))))))) -> Completed | M9: =VLOOKUP(A:A,'Finance Tracker'!A7:K251,8,FALSE) -> Invoice Completed | O9: N/A | P9: N/A | R9: 45115 | S9: 45143 | T9: NEM Commencement Date | U9: 45770 | V9: Completed | W9: Completed | X9: N/A | Y9: Completed | Z9: Completed | AA9: Completed | AB9: Completed | AC9: Completed | AD9: Completed | AE9: Completed | AF9: 45232 | AG9: 45232 | AH9: 48913 | AJ9: N/A | AK9: N/A | AL9: N/A | AM9: N/A | AP9: =S9-R9 -> 28 | AQ9: =AA9-Table1[[#This Row],[Closed Date]] -> #VALUE!
A10: =Table1[[#This Row],[Project No]] -> 2306033 | B10: =VLOOKUP(A:A,Table1[[Project No]:[Additional Remark]],2,FALSE) -> Foo Tuang Lee | C10: =VLOOKUP(A:A,Table1[[#All],[Project No]:[Additional Remark]],7,FALSE) -> #VALUE! | D10: =VLOOKUP(A:A,Table1[[#All],[Project No]:[Additional Remark]],4,FALSE) -> Chean Bang | E10: =VLOOKUP(A:A,Table1[[#All],[Project No]:[Additional Remark]],5,FALSE) -> R-PV | F10: =VLOOKUP(A:A,Table1[[Project No]:[Additional Remark]],6,FALSE) -> NEM | G10: =VLOOKUP(A:A,Table1[[Project No]:[Additional Remark]],8,FALSE) -> 4.65 | H10: =VLOOKUP(A:A,Table1[[Project No]:[Additional Remark]],15,FALSE) -> Astronergy 575Wp | I10: =VLOOKUP(A:A,Table1[[Project No]:[Additional Remark]],16,FALSE) -> 8 | J10: =VLOOKUP(A:A,Table1[[Project No]:[Additional Remark]],17,FALSE) -> Solinteg MHS-3.6K-30 hybrid | L10: =IF(ISBLANK(R10),"Pending NEM Qouta Submission",IF(ISBLANK(S10),"Pending NEM Qouta Approval",IF(ISBLANK(AA10),"Pending Site Installation",IF(ISBLANK(AJ10),"Pending ST License Application",IF(ISBLANK(AK10),"Pending ST License Approval", IF(ISBLANK(AB10),"Pending Meter Change Application",IF(AND(ISBLANK(AG10),ISBLANK(AF10)),"Pending Meter Change",IF(ISBLANK(AG10),"Pending NEM Welcome Letter",IF(ISBLANK(AL10),"Pending GITA Application",IF(ISBLANK(AM10),"Pending GITA Approval","Completed")))))))))) -> Completed | M10: =VLOOKUP(A:A,'Finance Tracker'!A8:K252,8,FALSE) -> Invoice Completed | O10: N/A | P10: N/A | R10: 45086 | S10: 45104 | T10: NEM Commencement Date | U10: 45451 | V10: Completed | W10: Completed | X10: N/A | Y10: Completed | Z10: Completed | AA10: Completed | AB10: Completed | AC10: Completed | AD10: Completed | AE10: Completed | AF10: 45169 | AG10: 45169 | AH10: 48822 | AJ10: N/A | AK10: N/A | AL10: N/A | AM10: N/A | AP10: =S10-R10 -> 18 | AQ10: =AA10-Table1[[#This Row],[Closed Date]] -> #VALUE!
A11: =Table1[[#This Row],[Project No]] -> 2306037 | B11: =VLOOKUP(A:A,Table1[[Project No]:[Additional Remark]],2,FALSE) -> Tan Hong Guan | C11: =VLOOKUP(A:A,Table1[[#All],[Project No]:[Additional Remark]],7,FALSE) -> #VALUE! | D11: =VLOOKUP(A:A,Table1[[#All],[Project No]:[Additional Remark]],4,FALSE) -> Simon | E11: =VLOOKUP(A:A,Table1[[#All],[Project No]:[Additional Remark]],5,FALSE) -> R-PV | F11: =VLOOKUP(A:A,Table1[[Project No]:[Additional Remark]],6,FALSE) -> NEM | G11: =VLOOKUP(A:A,Table1[[Project No]:[Additional Remark]],8,FALSE) -> 10.925 | H11: =VLOOKUP(A:A,Table1[[Project No]:[Additional Remark]],15,FALSE) -> Astronergy 575Wp | I11: =VLOOKUP(A:A,Table1[[Project No]:[Additional Remark]],16,FALSE) -> 19 | J11: =VLOOKUP(A:A,Table1[[Project No]:[Additional Remark]],17,FALSE) -> Huawei SUN2000-10KTL | L11: =IF(ISBLANK(R11),"Pending NEM Qouta Submission",IF(ISBLANK(S11),"Pending NEM Qouta Approval",IF(ISBLANK(AA11),"Pending Site Installation",IF(ISBLANK(AJ11),"Pending ST License Application",IF(ISBLANK(AK11),"Pending ST License Approval", IF(ISBLANK(AB11),"Pending Meter Change Application",IF(AND(ISBLANK(AG11),ISBLANK(AF11)),"Pending Meter Change",IF(ISBLANK(AG11),"Pending NEM Welcome Letter",IF(ISBLANK(AL11),"Pending GITA Application",IF(ISBLANK(AM11),"Pending GITA Approval","Completed")))))))))) -> Completed | M11: =VLOOKUP(A:A,'Finance Tracker'!A9:K253,8,FALSE) -> Invoice Completed | O11: N/A | P11: N/A | R11: 45146 | S11: 45161 | T11: NEM Commencement Date | U11: 45793 | V11: Completed | W11: Completed | X11: N/A | Y11: Completed | Z11: Completed | AA11: Completed | AB11: Completed | AC11: Completed | AD11: Completed | AE11: Completed | AF11: 45208 | AG11: 45208 | AH11: 48883 | AJ11: N/A | AK11: N/A | AL11: N/A | AM11: N/A | AP11: =S11-R11 -> 15 | AQ11: =AA11-Table1[[#This Row],[Closed Date]] -> #VALUE!
A12: =Table1[[#This Row],[Project No]] -> 2307040 | B12: =VLOOKUP(A:A,Table1[[Project No]:[Additional Remark]],2,FALSE) -> Law Soo Chin | C12: =VLOOKUP(A:A,Table1[[#All],[Project No]:[Additional Remark]],7,FALSE) -> #VALUE! | D12: =VLOOKUP(A:A,Table1[[#All],[Project No]:[Additional Remark]],4,FALSE) -> Chean Bang | E12: =VLOOKUP(A:A,Table1[[#All],[Project No]:[Additional Remark]],5,FALSE) -> R-PV | F12: =VLOOKUP(A:A,Table1[[Project No]:[Additional Remark]],6,FALSE) -> NEM | G12: =VLOOKUP(A:A,Table1[[Project No]:[Additional Remark]],8,FALSE) -> 12.65 | H12: =VLOOKUP(A:A,Table1[[Project No]:[Additional Remark]],15,FALSE) -> Astronergy 575Wp | I12: =VLOOKUP(A:A,Table1[[Project No]:[Additional Remark]],16,FALSE) -> 22 | J12: =VLOOKUP(A:A,Table1[[Project No]:[Additional Remark]],17,FALSE) -> Solinteg MHT-10K-25 hybrid | L12: =IF(ISBLANK(R12),"Pending NEM Qouta Submission",IF(ISBLANK(S12),"Pending NEM Qouta Approval",IF(ISBLANK(AA12),"Pending Site Installation",IF(ISBLANK(AJ12),"Pending ST License Application",IF(ISBLANK(AK12),"Pending ST License Approval", IF(ISBLANK(AB12),"Pending Meter Change Application",IF(AND(ISBLANK(AG12),ISBLANK(AF12)),"Pending Meter Change",IF(ISBLANK(AG12),"Pending NEM Welcome Letter",IF(ISBLANK(AL12),"Pending GITA Application",IF(ISBLANK(AM12),"Pending GITA Approval","Completed")))))))))) -> Completed | M12: =VLOOKUP(A:A,'Finance Tracker'!A10:K254,8,FALSE) -> Invoice Completed | O12: N/A | P12: N/A | R12: 45125 | S12: 45143 | T12: NEM Commencement Date | U12: 45770 | V12: Completed | W12: Completed | X12: N/A | Y12: Completed | Z12: Completed | AA12: Completed | AB12: Completed | AC12: Completed | AD12: Completed | AE12: Completed | AF12: 45212 | AG12: 45212 | AH12: 48883 | AJ12: N/A | AK12: N/A | AL12: N/A | AM12: N/A | AP12: =S12-R12 -> 18 | AQ12: =AA12-Table1[[#This Row],[Closed Date]] -> #VALUE!
A13: =Table1[[#This Row],[Project No]] -> 2305011 | B13: =VLOOKUP(A:A,Table1[[Project No]:[Additional Remark]],2,FALSE) -> Kossan FRP Marketing (M) Sdn Bhd | C13: =VLOOKUP(A:A,Table1[[#All],[Project No]:[Additional Remark]],7,FALSE) -> #VALUE! | D13: =VLOOKUP(A:A,Table1[[#All],[Project No]:[Additional Remark]],4,FALSE) -> Simon | E13: =VLOOKUP(A:A,Table1[[#All],[Project No]:[Additional Remark]],5,FALSE) -> C&I-PV | F13: =VLOOKUP(A:A,Table1[[Project No]:[Additional Remark]],6,FALSE) -> NEM | G13: =VLOOKUP(A:A,Table1[[Project No]:[Additional Remark]],8,FALSE) -> 283.945 | H13: =VLOOKUP(A:A,Table1[[Project No]:[Additional Remark]],15,FALSE) -> - | I13: =VLOOKUP(A:A,Table1[[Project No]:[Additional Remark]],16,FALSE) -> - | J13: =VLOOKUP(A:A,Table1[[Project No]:[Additional Remark]],17,FALSE) -> - | L13: =IF(ISBLANK(R13),"Pending NEM Qouta Submission",IF(ISBLANK(S13),"Pending NEM Qouta Approval",IF(ISBLANK(AA13),"Pending Site Installation",IF(ISBLANK(AJ13),"Pending ST License Application",IF(ISBLANK(AK13),"Pending ST License Approval", IF(ISBLANK(AB13),"Pending Meter Change Application",IF(AND(ISBLANK(AG13),ISBLANK(AF13)),"Pending Meter Change",IF(ISBLANK(AG13),"Pending NEM Welcome Letter",IF(ISBLANK(AL13),"Pending GITA Application",IF(ISBLANK(AM13),"Pending GITA Approval","Completed")))))))))) -> Completed | M13: =VLOOKUP(A:A,'Finance Tracker'!A11:K255,8,FALSE) -> 2nd invoice | O13: N/A | P13: N/A | R13: N/A | S13: N/A | T13: N/A | U13: N/A | V13: Completed | W13: Completed | X13: N/A | Y13: Completed | Z13: Completed | AA13: Completed | AB13: Completed | AC13: Completed | AD13: Completed | AE13: Completed | AF13: Completed | AG13: Completed | AH13: Completed | AJ13: N/A | AK13: N/A | AL13: N/A | AM13: N/A | AP13: =S13-R13 -> #VALUE! | AQ13: =AA13-Table1[[#This Row],[Closed Date]] -> #VALUE!
A14: =Table1[[#This Row],[Project No]] -> 2304007 | B14: =VLOOKUP(A:A,Table1[[Project No]:[Additional Remark]],2,FALSE) -> MTJ Development Sdn Bhd (Intercontinental KL) | C14: =VLOOKUP(A:A,Table1[[#All],[Project No]:[Additional Remark]],7,FALSE) -> #VALUE! | D14: =VLOOKUP(A:A,Table1[[#All],[Project No]:[Additional Remark]],4,FALSE) -> Simon | E14: =VLOOKUP(A:A,Table1[[#All],[Project No]:[Additional Remark]],5,FALSE) -> C&I-PV | F14: =VLOOKUP(A:A,Table1[[Project No]:[Additional Remark]],6,FALSE) -> NEM | G14: =VLOOKUP(A:A,Table1[[Project No]:[Additional Remark]],8,FALSE) -> 51.75 | H14: =VLOOKUP(A:A,Table1[[Project No]:[Additional Remark]],15,FALSE) -> Astronergy 575Wp | I14: =VLOOKUP(A:A,Table1[[Project No]:[Additional Remark]],16,FALSE) -> 90 | J14: =VLOOKUP(A:A,Table1[[Project No]:[Additional Remark]],17,FALSE) -> Goodwe 50kW | L14: =IF(ISBLANK(R14),"Pending NEM Qouta Submission",IF(ISBLANK(S14),"Pending NEM Qouta Approval",IF(ISBLANK(AA14),"Pending Site Installation",IF(ISBLANK(AJ14),"Pending ST License Application",IF(ISBLANK(AK14),"Pending ST License Approval", IF(ISBLANK(AB14),"Pending Meter Change Application",IF(AND(ISBLANK(AG14),ISBLANK(AF14)),"Pending Meter Change",IF(ISBLANK(AG14),"Pending NEM Welcome Letter",IF(ISBLANK(AL14),"Pending GITA Application",IF(ISBLANK(AM14),"Pending GITA Approval","Completed")))))))))) -> Completed | M14: =VLOOKUP(A:A,'Finance Tracker'!A12:K256,8,FALSE) -> 4th invoice | O14: N/A | P14: N/A | R14: 45170 | S14: 45238 | T14: Certificate Generated | U14: 45505 | V14: Completed | W14: Completed | X14: N/A | Y14: Completed | Z14: Completed | AA14: Completed | AB14: Completed | AC14: Completed | AD14: Completed | AE14: Completed | AF14: Completed | AG14: Completed | AH14: Completed | AJ14: N/A | AK14: N/A | AL14: N/A | AM14: N/A | AP14: =S14-R14 -> 68 | AQ14: =AA14-Table1[[#This Row],[Closed Date]] -> #VALUE!
A15: =Table1[[#This Row],[Project No]] -> 2307042 | B15: =VLOOKUP(A:A,Table1[[Project No]:[Additional Remark]],2,FALSE) -> Dato' Sri Ng Chong Keong | C15: =VLOOKUP(A:A,Table1[[#All],[Project No]:[Additional Remark]],7,FALSE) -> #VALUE! | D15: =VLOOKUP(A:A,Table1[[#All],[Project No]:[Additional Remark]],4,FALSE) -> Chean Bang | E15: =VLOOKUP(A:A,Table1[[#All],[Project No]:[Additional Remark]],5,FALSE) -> R-PV | F15: =VLOOKUP(A:A,Table1[[Project No]:[Additional Remark]],6,FALSE) -> NEM | G15: =VLOOKUP(A:A,Table1[[Project No]:[Additional Remark]],8,FALSE) -> 16.1 | H15: =VLOOKUP(A:A,Table1[[Project No]:[Additional Remark]],15,FALSE) -> Astronergy 575Wp | I15: =VLOOKUP(A:A,Table1[[Project No]:[Additional Remark]],16,FALSE) -> 28 | J15: =VLOOKUP(A:A,Table1[[Project No]:[Additional Remark]],17,FALSE) -> Solinteg MHT-12K-25 hybrid | L15: =IF(ISBLANK(R15),"Pending NEM Qouta Submission",IF(ISBLANK(S15),"Pending NEM Qouta Approval",IF(ISBLANK(AA15),"Pending Site Installation",IF(ISBLANK(AJ15),"Pending ST License Application",IF(ISBLANK(AK15),"Pending ST License Approval", IF(ISBLANK(AB15),"Pending Meter Change Application",IF(AND(ISBLANK(AG15),ISBLANK(AF15)),"Pending Meter Change",IF(ISBLANK(AG15),"Pending NEM Welcome Letter",IF(ISBLANK(AL15),"Pending GITA Application",IF(ISBLANK(AM15),"Pending GITA Approval","Completed")))))))))) -> Completed | M15: =VLOOKUP(A:A,'Finance Tracker'!A13:K257,8,FALSE) -> Invoice Completed | O15: N/A | P15: N/A | R15: 45188 | S15: 45205 | T15: NEM Commencement Date | U15: 45863 | V15: Completed | W15: Completed | X15: N/A | Y15: Completed | Z15: Completed | AA15: Completed | AB15: Completed | AC15: Completed | AD15: Completed | AE15: Completed | AF15: 45248 | AG15: 45248 | AH15: 48913 | AJ15: N/A | AK15: N/A | AL15: N/A | AM15: N/A | AP15: =S15-R15 -> 17 | AQ15: =AA15-Table1[[#This Row],[Closed Date]] -> #VALUE!
A16: =Table1[[#This Row],[Project No]] -> 2308058 | B16: =VLOOKUP(A:A,Table1[[Project No]:[Additional Remark]],2,FALSE) -> Cheong Yik Yin | C16: =VLOOKUP(A:A,Table1[[#All],[Project No]:[Additional Remark]],7,FALSE) -> #VALUE! | D16: =VLOOKUP(A:A,Table1[[#All],[Project No]:[Additional Remark]],4,FALSE) -> Simon | E16: =VLOOKUP(A:A,Table1[[#All],[Project No]:[Additional Remark]],5,FALSE) -> R-PV | F16: =VLOOKUP(A:A,Table1[[Project No]:[Additional Remark]],6,FALSE) -> NEM | G16: =VLOOKUP(A:A,Table1[[Project No]:[Additional Remark]],8,FALSE) -> 6.9 | H16: =VLOOKUP(A:A,Table1[[Project No]:[Additional Remark]],15,FALSE) -> Astronergy 575Wp | I16: =VLOOKUP(A:A,Table1[[Project No]:[Additional Remark]],16,FALSE) -> 12 | J16: =VLOOKUP(A:A,Table1[[Project No]:[Additional Remark]],17,FALSE) -> Solinteg MHT-5K-25 hybrid | L16: =IF(ISBLANK(R16),"Pending NEM Qouta Submission",IF(ISBLANK(S16),"Pending NEM Qouta Approval",IF(ISBLANK(AA16),"Pending Site Installation",IF(ISBLANK(AJ16),"Pending ST License Application",IF(ISBLANK(AK16),"Pending ST License Approval", IF(ISBLANK(AB16),"Pending Meter Change Application",IF(AND(ISBLANK(AG16),ISBLANK(AF16)),"Pending Meter Change",IF(ISBLANK(AG16),"Pending NEM Welcome Letter",IF(ISBLANK(AL16),"Pending GITA Application",IF(ISBLANK(AM16),"Pending GITA Approval","Completed")))))))))) -> Completed | M16: =VLOOKUP(A:A,'Finance Tracker'!A14:K258,8,FALSE) -> Pending 1st Invoice | O16: N/A | P16: N/A | R16: 45167 | S16: 45182 | T16: NEM Commencement Date | U16: 45813 | V16: Completed | W16: Completed | X16: N/A | Y16: Completed | Z16: Completed | AA16: Completed | AB16: Completed | AC16: Completed | AD16: Completed | AE16: Completed | AF16: 45251 | AG16: 45251 | AH16: 48913 | AJ16: N/A | AK16: N/A | AL16: N/A | AM16: N/A | AP16: =S16-R16 -> 15 | AQ16: =AA16-Table1[[#This Row],[Closed Date]] -> #VALUE!
A17: =Table1[[#This Row],[Project No]] -> 2308062 | B17: =VLOOKUP(A:A,Table1[[Project No]:[Additional Remark]],2,FALSE) -> Lim Chin Joo | C17: =VLOOKUP(A:A,Table1[[#All],[Project No]:[Additional Remark]],7,FALSE) -> #VALUE! | D17: =VLOOKUP(A:A,Table1[[#All],[Project No]:[Additional Remark]],4,FALSE) -> Simon | E17: =VLOOKUP(A:A,Table1[[#All],[Project No]:[Additional Remark]],5,FALSE) -> R-PV | F17: =VLOOKUP(A:A,Table1[[Project No]:[Additional Remark]],6,FALSE) -> NEM | G17: =VLOOKUP(A:A,Table1[[Project No]:[Additional Remark]],8,FALSE) -> 12.65 | H17: =VLOOKUP(A:A,Table1[[Project No]:[Additional Remark]],15,FALSE) -> Astronergy 575Wp | I17: =VLOOKUP(A:A,Table1[[Project No]:[Additional Remark]],16,FALSE) -> 22 | J17: =VLOOKUP(A:A,Table1[[Project No]:[Additional Remark]],17,FALSE) -> Huawei SUN2000-12KTL | L17: =IF(ISBLANK(R17),"Pending NEM Qouta Submission",IF(ISBLANK(S17),"Pending NEM Qouta Approval",IF(ISBLANK(AA17),"Pending Site Installation",IF(ISBLANK(AJ17),"Pending ST License Application",IF(ISBLANK(AK17),"Pending ST License Approval", IF(ISBLANK(AB17),"Pending Meter Change Application",IF(AND(ISBLANK(AG17),ISBLANK(AF17)),"Pending Meter Change",IF(ISBLANK(AG17),"Pending NEM Welcome Letter",IF(ISBLANK(AL17),"Pending GITA Application",IF(ISBLANK(AM17),"Pending GITA Approval","Completed")))))))))) -> Completed | M17: =VLOOKUP(A:A,'Finance Tracker'!A15:K259,8,FALSE) -> Pending 1st Invoice | O17: N/A | P17: N/A | R17: 45259 | S17: 45328 | T17: NEM Commencement Date | U17: 45910 | V17: Completed | W17: Completed | X17: N/A | Y17: Completed | Z17: Completed | AA17: Completed | AB17: Completed | AC17: Completed | AD17: Completed | AE17: Completed | AF17: 45396 | AG17: 45396 | AH17: 49064 | AJ17: N/A | AK17: N/A | AL17: N/A | AM17: N/A | AP17: =S17-R17 -> 69 | AQ17: =AA17-Table1[[#This Row],[Closed Date]] -> #VALUE!
A18: =Table1[[#This Row],[Project No]] -> 2309068 | B18: =VLOOKUP(A:A,Table1[[Project No]:[Additional Remark]],2,FALSE) -> Kee Siew Chuan (Ngo Woon Wah) | C18: =VLOOKUP(A:A,Table1[[#All],[Project No]:[Additional Remark]],7,FALSE) -> #VALUE! | D18: =VLOOKUP(A:A,Table1[[#All],[Project No]:[Additional Remark]],4,FALSE) -> Chean Bang | E18: =VLOOKUP(A:A,Table1[[#All],[Project No]:[Additional Remark]],5,FALSE) -> R-PV | F18: =VLOOKUP(A:A,Table1[[Project No]:[Additional Remark]],6,FALSE) -> NEM | G18: =VLOOKUP(A:A,Table1[[Project No]:[Additional Remark]],8,FALSE) -> 6.9 | H18: =VLOOKUP(A:A,Table1[[Project No]:[Additional Remark]],15,FALSE) -> Astronergy 575Wp | I18: =VLOOKUP(A:A,Table1[[Project No]:[Additional Remark]],16,FALSE) -> 12 | J18: =VLOOKUP(A:A,Table1[[Project No]:[Additional Remark]],17,FALSE) -> Solinteg MHT-5K-25 hybrid | L18: =IF(ISBLANK(R18),"Pending NEM Qouta Submission",IF(ISBLANK(S18),"Pending NEM Qouta Approval",IF(ISBLANK(AA18),"Pending Site Installation",IF(ISBLANK(AJ18),"Pending ST License Application",IF(ISBLANK(AK18),"Pending ST License Approval", IF(ISBLANK(AB18),"Pending Meter Change Application",IF(AND(ISBLANK(AG18),ISBLANK(AF18)),"Pending Meter Change",IF(ISBLANK(AG18),"Pending NEM Welcome Letter",IF(ISBLANK(AL18),"Pending GITA Application",IF(ISBLANK(AM18),"Pending GITA Approval","Completed")))))))))) -> Completed | M18: =VLOOKUP(A:A,'Finance Tracker'!A16:K260,8,FALSE) -> 1st invoice | O18: N/A | P18: N/A | R18: 45272 | S18: 45321 | T18: Completed Project Milestones | U18: 45939 | V18: Completed | W18: Completed | X18: N/A | Y18: Completed | Z18: Completed | AA18: Completed | AB18: Completed | AC18: Completed | AD18: Completed | AE18: 45331 | AF18: 45341 | AG18: 45341 | AH18: 49003 | AJ18: N/A | AK18: N/A | AL18: N/A | AM18: N/A | AP18: =S18-R18 -> 49 | AQ18: =AA18-Table1[[#This Row],[Closed Date]] -> #VALUE!
A19: =Table1[[#This Row],[Project No]] -> 2310078 | B19: =VLOOKUP(A:A,Table1[[Project No]:[Additional Remark]],2,FALSE) -> Lee Nyok Cheng | C19: =VLOOKUP(A:A,Table1[[#All],[Project No]:[Additional Remark]],7,FALSE) -> #VALUE! | D19: =VLOOKUP(A:A,Table1[[#All],[Project No]:[Additional Remark]],4,FALSE) -> Chean Bang | E19: =VLOOKUP(A:A,Table1[[#All],[Project No]:[Additional Remark]],5,FALSE) -> R-PV | F19: =VLOOKUP(A:A,Table1[[Project No]:[Additional Remark]],6,FALSE) -> NEM | G19: =VLOOKUP(A:A,Table1[[Project No]:[Additional Remark]],8,FALSE) -> 16.1 | H19: =VLOOKUP(A:A,Table1[[Project No]:[Additional Remark]],15,FALSE) -> Astronergy 575Wp | I19: =VLOOKUP(A:A,Table1[[Project No]:[Additional Remark]],16,FALSE) -> 28 | J19: =VLOOKUP(A:A,Table1[[Project No]:[Additional Remark]],17,FALSE) -> Solinteg MHT-12K-25 hybrid | L19: =IF(ISBLANK(R19),"Pending NEM Qouta Submission",IF(ISBLANK(S19),"Pending NEM Qouta Approval",IF(ISBLANK(AA19),"Pending Site Installation",IF(ISBLANK(AJ19),"Pending ST License Application",IF(ISBLANK(AK19),"Pending ST License Approval", IF(ISBLANK(AB19),"Pending Meter Change Application",IF(AND(ISBLANK(AG19),ISBLANK(AF19)),"Pending Meter Change",IF(ISBLANK(AG19),"Pending NEM Welcome Letter",IF(ISBLANK(AL19),"Pending GITA Application",IF(ISBLANK(AM19),"Pending GITA Approval","Completed")))))))))) -> Completed | M19: =VLOOKUP(A:A,'Finance Tracker'!A17:K261,8,FALSE) -> Invoice Completed | O19: N/A | P19: N/A | R19: 45211 | S19: 45224 | T19: Completed Project Milestones | U19: 45478 | V19: Completed | W19: Completed | X19: N/A | Y19: Completed | Z19: Completed | AA19: Completed | AB19: Completed | AC19: Completed | AD19: Completed | AE19: Completed | AF19: 45245 | AG19: 45245 | AH19: 48913 | AJ19: N/A | AK19: N/A | AL19: N/A | AM19: N/A | AP19: =S19-R19 -> 13 | AQ19: =AA19-Table1[[#This Row],[Closed Date]] -> #VALUE!
A20: =Table1[[#This Row],[Project No]] -> 2310083 | B20: =VLOOKUP(A:A,Table1[[Project No]:[Additional Remark]],2,FALSE) -> Ong Eng Guan | C20: =VLOOKUP(A:A,Table1[[#All],[Project No]:[Additional Remark]],7,FALSE) -> #VALUE! | D20: =VLOOKUP(A:A,Table1[[#All],[Project No]:[Additional Remark]],4,FALSE) -> Chean Bang | E20: =VLOOKUP(A:A,Table1[[#All],[Project No]:[Additional Remark]],5,FALSE) -> R-PV | F20: =VLOOKUP(A:A,Table1[[Project No]:[Additional Remark]],6,FALSE) -> NEM | G20: =VLOOKUP(A:A,Table1[[Project No]:[Additional Remark]],8,FALSE) -> 8.05 | H20: =VLOOKUP(A:A,Table1[[Project No]:[Additional Remark]],15,FALSE) -> Astronergy 575Wp | I20: =VLOOKUP(A:A,Table1[[Project No]:[Additional Remark]],16,FALSE) -> 14 | J20: =VLOOKUP(A:A,Table1[[Project No]:[Additional Remark]],17,FALSE) -> Solinteg MHT-8K-25 hybrid | L20: =IF(ISBLANK(R20),"Pending NEM Qouta Submission",IF(ISBLANK(S20),"Pending NEM Qouta Approval",IF(ISBLANK(AA20),"Pending Site Installation",IF(ISBLANK(AJ20),"Pending ST License Application",IF(ISBLANK(AK20),"Pending ST License Approval", IF(ISBLANK(AB20),"Pending Meter Change Application",IF(AND(ISBLANK(AG20),ISBLANK(AF20)),"Pending Meter Change",IF(ISBLANK(AG20),"Pending NEM Welcome Letter",IF(ISBLANK(AL20),"Pending GITA Application",IF(ISBLANK(AM20),"Pending GITA Approval","Completed")))))))))) -> Completed | M20: =VLOOKUP(A:A,'Finance Tracker'!A18:K262,8,FALSE) -> 2nd invoice | O20: N/A | P20: N/A | R20: 45230 | S20: 45259 | T20: NEM Commencement Date | U20: 45875 | V20: Completed | W20: Completed | X20: N/A | Y20: Completed | Z20: Completed | AA20: Completed | AB20: Completed | AC20: Completed | AD20: Completed | AE20: Completed | AF20: 45341 | AG20: 45341 | AH20: 49003 | AJ20: N/A | AK20: N/A | AL20: N/A | AM20: N/A | AP20: =S20-R20 -> 29 | AQ20: =AA20-Table1[[#This Row],[Closed Date]] -> #VALUE!
A21: =Table1[[#This Row],[Project No]] -> 2310084 | B21: =VLOOKUP(A:A,Table1[[Project No]:[Additional Remark]],2,FALSE) -> Chia Le Chin | C21: =VLOOKUP(A:A,Table1[[#All],[Project No]:[Additional Remark]],7,FALSE) -> #VALUE! | D21: =VLOOKUP(A:A,Table1[[#All],[Project No]:[Additional Remark]],4,FALSE) -> Chean Bang | E21: =VLOOKUP(A:A,Table1[[#All],[Project No]:[Additional Remark]],5,FALSE) -> R-PV | F21: =VLOOKUP(A:A,Table1[[Project No]:[Additional Remark]],6,FALSE) -> NEM | G21: =VLOOKUP(A:A,Table1[[Project No]:[Additional Remark]],8,FALSE) -> 8.05 | H21: =VLOOKUP(A:A,Table1[[Project No]:[Additional Remark]],15,FALSE) -> Astronergy 575Wp | I21: =VLOOKUP(A:A,Table1[[Project No]:[Additional Remark]],16,FALSE) -> 14 | J21: =VLOOKUP(A:A,Table1[[Project No]:[Additional Remark]],17,FALSE) -> Solinteg MHT-8K-25 hybrid | L21: =IF(ISBLANK(R21),"Pending NEM Qouta Submission",IF(ISBLANK(S21),"Pending NEM Qouta Approval",IF(ISBLANK(AA21),"Pending Site Installation",IF(ISBLANK(AJ21),"Pending ST License Application",IF(ISBLANK(AK21),"Pending ST License Approval", IF(ISBLANK(AB21),"Pending Meter Change Application",IF(AND(ISBLANK(AG21),ISBLANK(AF21)),"Pending Meter Change",IF(ISBLANK(AG21),"Pending NEM Welcome Letter",IF(ISBLANK(AL21),"Pending GITA Application",IF(ISBLANK(AM21),"Pending GITA Approval","Completed")))))))))) -> Completed | M21: =VLOOKUP(A:A,'Finance Tracker'!A19:K263,8,FALSE) -> Invoice Completed | O21: N/A | P21: N/A | R21: 45231 | S21: 45259 | T21: NEM Commencement Date | U21: 45875 | V21: Completed | W21: Completed | X21: N/A | Y21: Completed | Z21: Completed | AA21: Completed | AB21: Completed | AC21: Completed | AD21: Completed | AE21: 45331 | AF21: 45341 | AG21: 45341 | AH21: 49003 | AJ21: N/A | AK21: N/A | AL21: N/A | AM21: N/A | AP21: =S21-R21 -> 28 | AQ21: =AA21-Table1[[#This Row],[Closed Date]] -> #VALUE!
A22: =Table1[[#This Row],[Project No]] -> 2305024 | B22: =VLOOKUP(A:A,Table1[[Project No]:[Additional Remark]],2,FALSE) -> Beh Poh Loh | C22: =VLOOKUP(A:A,Table1[[#All],[Project No]:[Additional Remark]],7,FALSE) -> #VALUE! | D22: =VLOOKUP(A:A,Table1[[#All],[Project No]:[Additional Remark]],4,FALSE) -> Chean Bang | E22: =VLOOKUP(A:A,Table1[[#All],[Project No]:[Additional Remark]],5,FALSE) -> R-PV | F22: =VLOOKUP(A:A,Table1[[Project No]:[Additional Remark]],6,FALSE) -> NEM | G22: =VLOOKUP(A:A,Table1[[Project No]:[Additional Remark]],8,FALSE) -> 12.65 | H22: =VLOOKUP(A:A,Table1[[Project No]:[Additional Remark]],15,FALSE) -> Astronergy 575Wp | I22: =VLOOKUP(A:A,Table1[[Project No]:[Additional Remark]],16,FALSE) -> 22 | J22: =VLOOKUP(A:A,Table1[[Project No]:[Additional Remark]],17,FALSE) -> GoodWe GW10KN-ET | L22: =IF(ISBLANK(R22),"Pending NEM Qouta Submission",IF(ISBLANK(S22),"Pending NEM Qouta Approval",IF(ISBLANK(AA22),"Pending Site Installation",IF(ISBLANK(AJ22),"Pending ST License Application",IF(ISBLANK(AK22),"Pending ST License Approval", IF(ISBLANK(AB22),"Pending Meter Change Application",IF(AND(ISBLANK(AG22),ISBLANK(AF22)),"Pending Meter Change",IF(ISBLANK(AG22),"Pending NEM Welcome Letter",IF(ISBLANK(AL22),"Pending GITA Application",IF(ISBLANK(AM22),"Pending GITA Approval","Completed")))))))))) -> Completed | M22: =VLOOKUP(A:A,'Finance Tracker'!A20:K264,8,FALSE) -> Pending 1st Invoice | O22: N/A | P22: N/A | R22: 45113 | S22: 45127 | T22: Completed Project Milestones | U22: 45939 | V22: Completed | W22: Completed | X22: N/A | Y22: Completed | Z22: Completed | AA22: Completed | AB22: Completed | AC22: Completed | AD22: Completed | AE22: 45449 | AF22: 45463 | AG22: 45463 | AH22: 49125 | AJ22: N/A | AK22: N/A | AL22: N/A | AM22: N/A | AP22: =S22-R22 -> 14 | AQ22: =AA22-Table1[[#This Row],[Closed Date]] -> #VALUE!
A23: =Table1[[#This Row],[Project No]] -> 2307052 | B23: =VLOOKUP(A:A,Table1[[Project No]:[Additional Remark]],2,FALSE) -> Ngoh Win Nee | C23: =VLOOKUP(A:A,Table1[[#All],[Project No]:[Additional Remark]],7,FALSE) -> #VALUE! | D23: =VLOOKUP(A:A,Table1[[#All],[Project No]:[Additional Remark]],4,FALSE) -> Chean Bang | E23: =VLOOKUP(A:A,Table1[[#All],[Project No]:[Additional Remark]],5,FALSE) -> R-PV | F23: =VLOOKUP(A:A,Table1[[Project No]:[Additional Remark]],6,FALSE) -> NEM | G23: =VLOOKUP(A:A,Table1[[Project No]:[Additional Remark]],8,FALSE) -> 4.6 | H23: =VLOOKUP(A:A,Table1[[Project No]:[Additional Remark]],15,FALSE) -> Astronergy 575Wp | I23: =VLOOKUP(A:A,Table1[[Project No]:[Additional Remark]],16,FALSE) -> 8 | J23: =VLOOKUP(A:A,Table1[[Project No]:[Additional Remark]],17,FALSE) -> Solinteg MHS-3.6K-30 hybrid | L23: =IF(ISBLANK(R23),"Pending NEM Qouta Submission",IF(ISBLANK(S23),"Pending NEM Qouta Approval",IF(ISBLANK(AA23),"Pending Site Installation",IF(ISBLANK(AJ23),"Pending ST License Application",IF(ISBLANK(AK23),"Pending ST License Approval", IF(ISBLANK(AB23),"Pending Meter Change Application",IF(AND(ISBLANK(AG23),ISBLANK(AF23)),"Pending Meter Change",IF(ISBLANK(AG23),"Pending NEM Welcome Letter",IF(ISBLANK(AL23),"Pending GITA Application",IF(ISBLANK(AM23),"Pending GITA Approval","Completed")))))))))) -> Completed | M23: =VLOOKUP(A:A,'Finance Tracker'!A21:K265,8,FALSE) -> 1st invoice | O23: N/A | P23: N/A | R23: 45162 | S23: 45182 | T23: Certificate Generated | U23: 45505 | V23: Completed | W23: Completed | X23: N/A | Y23: Completed | Z23: N/A | AA23: N/A | AB23: N/A | AC23: N/A | AD23: N/A | AE23: N/A | AF23: N/A | AG23: N/A | AH23: N/A | AJ23: N/A | AK23: N/A | AL23: N/A | AM23: N/A | AP23: =S23-R23 -> 20 | AQ23: =AA23-Table1[[#This Row],[Closed Date]] -> #VALUE!
A24: =Table1[[#This Row],[Project No]] -> 2304010 | B24: =VLOOKUP(A:A,Table1[[Project No]:[Additional Remark]],2,FALSE) -> Tung Seng Chang | C24: =VLOOKUP(A:A,Table1[[#All],[Project No]:[Additional Remark]],7,FALSE) -> #VALUE! | D24: =VLOOKUP(A:A,Table1[[#All],[Project No]:[Additional Remark]],4,FALSE) -> Simon | E24: =VLOOKUP(A:A,Table1[[#All],[Project No]:[Additional Remark]],5,FALSE) -> R-PV | F24: =VLOOKUP(A:A,Table1[[Project No]:[Additional Remark]],6,FALSE) -> NEM | G24: =VLOOKUP(A:A,Table1[[Project No]:[Additional Remark]],8,FALSE) -> 13.625 | H24: =VLOOKUP(A:A,Table1[[Project No]:[Additional Remark]],15,FALSE) -> - | I24: =VLOOKUP(A:A,Table1[[Project No]:[Additional Remark]],16,FALSE) -> - | J24: =VLOOKUP(A:A,Table1[[Project No]:[Additional Remark]],17,FALSE) -> Goodwe GW10K-SDT-20 | L24: =IF(ISBLANK(R24),"Pending NEM Qouta Submission",IF(ISBLANK(S24),"Pending NEM Qouta Approval",IF(ISBLANK(AA24),"Pending Site Installation",IF(ISBLANK(AJ24),"Pending ST License Application",IF(ISBLANK(AK24),"Pending ST License Approval", IF(ISBLANK(AB24),"Pending Meter Change Application",IF(AND(ISBLANK(AG24),ISBLANK(AF24)),"Pending Meter Change",IF(ISBLANK(AG24),"Pending NEM Welcome Letter",IF(ISBLANK(AL24),"Pending GITA Application",IF(ISBLANK(AM24),"Pending GITA Approval","Completed")))))))))) -> Completed | M24: =VLOOKUP(A:A,'Finance Tracker'!A22:K266,8,FALSE) -> 1st invoice | O24: N/A | P24: N/A | R24: 45107 | S24: 45120 | T24: Certificate Generated | U24: 45474 | V24: Completed | W24: Completed | X24: N/A | Y24: Completed | Z24: N/A | AA24: N/A | AB24: N/A | AC24: N/A | AD24: N/A | AE24: N/A | AF24: N/A | AG24: N/A | AH24: N/A | AJ24: N/A | AK24: N/A | AL24: N/A | AM24: N/A | AP24: =S24-R24 -> 13 | AQ24: =AA24-Table1[[#This Row],[Closed Date]] -> #VALUE!
A25: =Table1[[#This Row],[Project No]] -> 2308065 | B25: =VLOOKUP(A:A,Table1[[Project No]:[Additional Remark]],2,FALSE) -> Pua Hock Meng | C25: =VLOOKUP(A:A,Table1[[#All],[Project No]:[Additional Remark]],7,FALSE) -> #VALUE! | D25: =VLOOKUP(A:A,Table1[[#All],[Project No]:[Additional Remark]],4,FALSE) -> Chean Bang | E25: =VLOOKUP(A:A,Table1[[#All],[Project No]:[Additional Remark]],5,FALSE) -> R-PV | F25: =VLOOKUP(A:A,Table1[[Project No]:[Additional Remark]],6,FALSE) -> NEM | G25: =VLOOKUP(A:A,Table1[[Project No]:[Additional Remark]],8,FALSE) -> 8.625 | H25: =VLOOKUP(A:A,Table1[[Project No]:[Additional Remark]],15,FALSE) -> Astronergy 575Wp | I25: =VLOOKUP(A:A,Table1[[Project No]:[Additional Remark]],16,FALSE) -> 15 | J25: =VLOOKUP(A:A,Table1[[Project No]:[Additional Remark]],17,FALSE) -> Solinteg MHT-8K-25 hybrid | L25: =IF(ISBLANK(R25),"Pending NEM Qouta Submission",IF(ISBLANK(S25),"Pending NEM Qouta Approval",IF(ISBLANK(AA25),"Pending Site Installation",IF(ISBLANK(AJ25),"Pending ST License Application",IF(ISBLANK(AK25),"Pending ST License Approval", IF(ISBLANK(AB25),"Pending Meter Change Application",IF(AND(ISBLANK(AG25),ISBLANK(AF25)),"Pending Meter Change",IF(ISBLANK(AG25),"Pending NEM Welcome Letter",IF(ISBLANK(AL25),"Pending GITA Application",IF(ISBLANK(AM25),"Pending GITA Approval","Completed")))))))))) -> Completed | M25: =VLOOKUP(A:A,'Finance Tracker'!A23:K267,8,FALSE) -> 4th invoice | O25: N/A | P25: N/A | R25: 45190 | S25: 45211 | T25: NEM Commencement Date | U25: 45632 | V25: Completed | W25: Completed | X25: N/A | Y25: Completed | Z25: PJ Plus | AA25: 45566 | AB25: Completed | AC25: Completed | AD25: Completed | AE25: 45600 | AF25: 45601 | AG25: 45601 | AH25: 49278 | AJ25: N/A | AK25: N/A | AL25: N/A | AM25: N/A | AP25: =S25-R25 -> 21 | AQ25: =AA25-Table1[[#This Row],[Closed Date]] -> 390
A26: =Table1[[#This Row],[Project No]] -> 2306009 | B26: =VLOOKUP(A:A,Table1[[Project No]:[Additional Remark]],2,FALSE) -> Dato Arif Stephen bin Abdullah | C26: =VLOOKUP(A:A,Table1[[#All],[Project No]:[Additional Remark]],7,FALSE) -> #VALUE! | D26: =VLOOKUP(A:A,Table1[[#All],[Project No]:[Additional Remark]],4,FALSE) -> Simon | E26: =VLOOKUP(A:A,Table1[[#All],[Project No]:[Additional Remark]],5,FALSE) -> R-BESS | F26: =VLOOKUP(A:A,Table1[[Project No]:[Additional Remark]],6,FALSE) -> SELCO | G26: =VLOOKUP(A:A,Table1[[Project No]:[Additional Remark]],8,FALSE) -> 85.1 | H26: =VLOOKUP(A:A,Table1[[Project No]:[Additional Remark]],15,FALSE) -> Astronergy 575Wp | I26: =VLOOKUP(A:A,Table1[[Project No]:[Additional Remark]],16,FALSE) -> 148 | J26: =VLOOKUP(A:A,Table1[[Project No]:[Additional Remark]],17,FALSE) -> Solax X3-Ultra 20kW x 3 | L26: =IF(ISBLANK(R26),"Pending NEM Qouta Submission",IF(ISBLANK(S26),"Pending NEM Qouta Approval",IF(ISBLANK(AA26),"Pending Site Installation",IF(ISBLANK(AJ26),"Pending ST License Application",IF(ISBLANK(AK26),"Pending ST License Approval", IF(ISBLANK(AB26),"Pending Meter Change Application",IF(AND(ISBLANK(AG26),ISBLANK(AF26)),"Pending Meter Change",IF(ISBLANK(AG26),"Pending NEM Welcome Letter",IF(ISBLANK(AL26),"Pending GITA Application",IF(ISBLANK(AM26),"Pending GITA Approval","Completed")))))))))) -> Completed | M26: =VLOOKUP(A:A,'Finance Tracker'!A24:K268,8,FALSE) -> Invoice Completed | O26: N/A | P26: N/A | R26: N/A | S26: N/A | T26: N/A | U26: N/A | V26: Completed | W26: Completed | X26: N/A | Y26: Completed | Z26: Completed | AA26: Completed | AB26: N/A | AC26: N/A | AD26: N/A | AE26: N/A | AF26: N/A | AG26: N/A | AH26: N/A | AJ26: N/A | AK26: N/A | AL26: N/A | AM26: N/A | AP26: =S26-R26 -> #VALUE! | AQ26: =AA26-Table1[[#This Row],[Closed Date]] -> #VALUE!
A27: =Table1[[#This Row],[Project No]] -> 2303003 | B27: =VLOOKUP(A:A,Table1[[Project No]:[Additional Remark]],2,FALSE) -> Greenlast Housing Development Sdn Bhd | C27: =VLOOKUP(A:A,Table1[[#All],[Project No]:[Additional Remark]],7,FALSE) -> #VALUE! | D27: =VLOOKUP(A:A,Table1[[#All],[Project No]:[Additional Remark]],4,FALSE) -> Chean Bang | E27: =VLOOKUP(A:A,Table1[[#All],[Project No]:[Additional Remark]],5,FALSE) -> C&I-PV | F27: =VLOOKUP(A:A,Table1[[Project No]:[Additional Remark]],6,FALSE) -> NEM | G27: =VLOOKUP(A:A,Table1[[Project No]:[Additional Remark]],8,FALSE) -> 23 | H27: =VLOOKUP(A:A,Table1[[Project No]:[Additional Remark]],15,FALSE) -> Astronergy 575Wp | I27: =VLOOKUP(A:A,Table1[[Project No]:[Additional Remark]],16,FALSE) -> 40 | J27: =VLOOKUP(A:A,Table1[[Project No]:[Additional Remark]],17,FALSE) -> Goodwe GW20K-SDT-20 | L27: =IF(ISBLANK(R27),"Pending NEM Qouta Submission",IF(ISBLANK(S27),"Pending NEM Qouta Approval",IF(ISBLANK(AA27),"Pending Site Installation",IF(ISBLANK(AJ27),"Pending ST License Application",IF(ISBLANK(AK27),"Pending ST License Approval", IF(ISBLANK(AB27),"Pending Meter Change Application",IF(AND(ISBLANK(AG27),ISBLANK(AF27)),"Pending Meter Change",IF(ISBLANK(AG27),"Pending NEM Welcome Letter",IF(ISBLANK(AL27),"Pending GITA Application",IF(ISBLANK(AM27),"Pending GITA Approval","Completed")))))))))) -> Completed | M27: =VLOOKUP(A:A,'Finance Tracker'!A25:K269,8,FALSE) -> Invoice Completed | O27: N/A | P27: N/A | R27: 45275 | S27: 45321 | T27: NEM Commencement Date | U27: 45654 | V27: Completed | W27: Completed | X27: N/A | Y27: Completed | Z27: Completed | AA27: Completed | AB27: Completed | AC27: Completed | AD27: Completed | AE27: Completed | AF27: 45464 | AG27: 45464 | AH27: 49125 | AJ27: N/A | AK27: N/A | AL27: Completed | AM27: Completed | AP27: =S27-R27 -> 46 | AQ27: =AA27-Table1[[#This Row],[Closed Date]] -> #VALUE!
A28: =Table1[[#This Row],[Project No]] -> 2311040 | B28: =VLOOKUP(A:A,Table1[[Project No]:[Additional Remark]],2,FALSE) -> DBTS Industries Sdn Bhd | C28: =VLOOKUP(A:A,Table1[[#All],[Project No]:[Additional Remark]],7,FALSE) -> #VALUE! | D28: =VLOOKUP(A:A,Table1[[#All],[Project No]:[Additional Remark]],4,FALSE) -> SImon | E28: =VLOOKUP(A:A,Table1[[#All],[Project No]:[Additional Remark]],5,FALSE) -> C&I-PV | F28: =VLOOKUP(A:A,Table1[[Project No]:[Additional Remark]],6,FALSE) -> NEM | G28: =VLOOKUP(A:A,Table1[[Project No]:[Additional Remark]],8,FALSE) -> 93 | H28: =VLOOKUP(A:A,Table1[[Project No]:[Additional Remark]],15,FALSE) -> - | I28: =VLOOKUP(A:A,Table1[[Project No]:[Additional Remark]],16,FALSE) -> - | J28: =VLOOKUP(A:A,Table1[[Project No]:[Additional Remark]],17,FALSE) -> - | L28: =IF(ISBLANK(R28),"Pending NEM Qouta Submission",IF(ISBLANK(S28),"Pending NEM Qouta Approval",IF(ISBLANK(AA28),"Pending Site Installation",IF(ISBLANK(AJ28),"Pending ST License Application",IF(ISBLANK(AK28),"Pending ST License Approval", IF(ISBLANK(AB28),"Pending Meter Change Application",IF(AND(ISBLANK(AG28),ISBLANK(AF28)),"Pending Meter Change",IF(ISBLANK(AG28),"Pending NEM Welcome Letter",IF(ISBLANK(AL28),"Pending GITA Application",IF(ISBLANK(AM28),"Pending GITA Approval","Completed")))))))))) -> Completed | M28: =VLOOKUP(A:A,'Finance Tracker'!A26:K270,8,FALSE) -> 1st invoice | O28: N/A | P28: N/A | R28: N/A | S28: N/A | T28: N/A | U28: N/A | V28: Completed | W28: Completed | X28: N/A | Y28: Completed | Z28: Completed | AA28: Completed | AB28: Completed | AC28: Completed | AD28: Completed | AE28: Completed | AF28: Completed | AG28: Completed | AH28: Completed | AJ28: N/A | AK28: N/A | AL28: N/A | AM28: N/A | AP28: =S28-R28 -> #VALUE! | AQ28: =AA28-Table1[[#This Row],[Closed Date]] -> #VALUE!
A29: =Table1[[#This Row],[Project No]] -> 2308007 | B29: =VLOOKUP(A:A,Table1[[Project No]:[Additional Remark]],2,FALSE) -> EV Connection Sdn Bhd (The Pines Melaka) | C29: =VLOOKUP(A:A,Table1[[#All],[Project No]:[Additional Remark]],7,FALSE) -> #VALUE! | D29: =VLOOKUP(A:A,Table1[[#All],[Project No]:[Additional Remark]],4,FALSE) -> Simon | E29: =VLOOKUP(A:A,Table1[[#All],[Project No]:[Additional Remark]],5,FALSE) -> EV Charger | F29: =VLOOKUP(A:A,Table1[[Project No]:[Additional Remark]],6,FALSE) -> - | G29: =VLOOKUP(A:A,Table1[[Project No]:[Additional Remark]],8,FALSE) -> 0 | H29: =VLOOKUP(A:A,Table1[[Project No]:[Additional Remark]],15,FALSE) -> - | I29: =VLOOKUP(A:A,Table1[[Project No]:[Additional Remark]],16,FALSE) -> - | J29: =VLOOKUP(A:A,Table1[[Project No]:[Additional Remark]],17,FALSE) -> - | L29: =IF(ISBLANK(R29),"Pending NEM Qouta Submission",IF(ISBLANK(S29),"Pending NEM Qouta Approval",IF(ISBLANK(AA29),"Pending Site Installation",IF(ISBLANK(AJ29),"Pending ST License Application",IF(ISBLANK(AK29),"Pending ST License Approval", IF(ISBLANK(AB29),"Pending Meter Change Application",IF(AND(ISBLANK(AG29),ISBLANK(AF29)),"Pending Meter Change",IF(ISBLANK(AG29),"Pending NEM Welcome Letter",IF(ISBLANK(AL29),"Pending GITA Application",IF(ISBLANK(AM29),"Pending GITA Approval","Completed")))))))))) -> Completed | M29: =VLOOKUP(A:A,'Finance Tracker'!A27:K271,8,FALSE) -> Invoice Completed | O29: N/A | P29: N/A | R29: N/A | S29: N/A | T29: N/A | U29: N/A | V29: Completed | W29: Completed | X29: N/A | Y29: Completed | Z29: Completed | AA29: Completed | AB29: N/A | AC29: N/A | AD29: N/A | AE29: N/A | AF29: N/A | AG29: N/A | AH29: N/A | AJ29: N/A | AK29: N/A | AL29: N/A | AM29: N/A | AP29: =S29-R29 -> #VALUE! | AQ29: =AA29-Table1[[#This Row],[Closed Date]] -> #VALUE!
A30: =Table1[[#This Row],[Project No]] -> 2311094 | B30: =VLOOKUP(A:A,Table1[[Project No]:[Additional Remark]],2,FALSE) -> Ching Kok Keong | C30: =VLOOKUP(A:A,Table1[[#All],[Project No]:[Additional Remark]],7,FALSE) -> #VALUE! | D30: =VLOOKUP(A:A,Table1[[#All],[Project No]:[Additional Remark]],4,FALSE) -> Chean Bang | E30: =VLOOKUP(A:A,Table1[[#All],[Project No]:[Additional Remark]],5,FALSE) -> R-PV | F30: =VLOOKUP(A:A,Table1[[Project No]:[Additional Remark]],6,FALSE) -> NEM | G30: =VLOOKUP(A:A,Table1[[Project No]:[Additional Remark]],8,FALSE) -> 9.775 | H30: =VLOOKUP(A:A,Table1[[Project No]:[Additional Remark]],15,FALSE) -> Astronergy 575Wp | I30: =VLOOKUP(A:A,Table1[[Project No]:[Additional Remark]],16,FALSE) -> 17 | J30: =VLOOKUP(A:A,Table1[[Project No]:[Additional Remark]],17,FALSE) -> Solinteg MHT-8K-25 hybrid | L30: =IF(ISBLANK(R30),"Pending NEM Qouta Submission",IF(ISBLANK(S30),"Pending NEM Qouta Approval",IF(ISBLANK(AA30),"Pending Site Installation",IF(ISBLANK(AJ30),"Pending ST License Application",IF(ISBLANK(AK30),"Pending ST License Approval", IF(ISBLANK(AB30),"Pending Meter Change Application",IF(AND(ISBLANK(AG30),ISBLANK(AF30)),"Pending Meter Change",IF(ISBLANK(AG30),"Pending NEM Welcome Letter",IF(ISBLANK(AL30),"Pending GITA Application",IF(ISBLANK(AM30),"Pending GITA Approval","Completed")))))))))) -> Completed | M30: =VLOOKUP(A:A,'Finance Tracker'!A28:K272,8,FALSE) -> Invoice Completed | O30: N/A | P30: N/A | R30: 45259 | S30: 45321 | T30: Completed Project Milestones | U30: 45939 | V30: Completed | W30: Completed | X30: N/A | Y30: Completed | Z30: Completed | AA30: Completed | AB30: Completed | AC30: Completed | AD30: Completed | AE30: 45854 | AF30: 45497 | AG30: 45497 | AH30: 49156 | AJ30: N/A | AK30: N/A | AL30: N/A | AM30: N/A | AP30: =S30-R30 -> 62 | AQ30: =AA30-Table1[[#This Row],[Closed Date]] -> #VALUE!
A31: =Table1[[#This Row],[Project No]] -> 2311095 | B31: =VLOOKUP(A:A,Table1[[Project No]:[Additional Remark]],2,FALSE) -> Chu Yin Siong | C31: =VLOOKUP(A:A,Table1[[#All],[Project No]:[Additional Remark]],7,FALSE) -> #VALUE! | D31: =VLOOKUP(A:A,Table1[[#All],[Project No]:[Additional Remark]],4,FALSE) -> Chean Bang | E31: =VLOOKUP(A:A,Table1[[#All],[Project No]:[Additional Remark]],5,FALSE) -> R-PV | F31: =VLOOKUP(A:A,Table1[[Project No]:[Additional Remark]],6,FALSE) -> NEM | G31: =VLOOKUP(A:A,Table1[[Project No]:[Additional Remark]],8,FALSE) -> 12.65 | H31: =VLOOKUP(A:A,Table1[[Project No]:[Additional Remark]],15,FALSE) -> Astronergy 575Wp | I31: =VLOOKUP(A:A,Table1[[Project No]:[Additional Remark]],16,FALSE) -> 22 | J31: =VLOOKUP(A:A,Table1[[Project No]:[Additional Remark]],17,FALSE) -> Solinteg MHT-10K-25 hybrid | L31: =IF(ISBLANK(R31),"Pending NEM Qouta Submission",IF(ISBLANK(S31),"Pending NEM Qouta Approval",IF(ISBLANK(AA31),"Pending Site Installation",IF(ISBLANK(AJ31),"Pending ST License Application",IF(ISBLANK(AK31),"Pending ST License Approval", IF(ISBLANK(AB31),"Pending Meter Change Application",IF(AND(ISBLANK(AG31),ISBLANK(AF31)),"Pending Meter Change",IF(ISBLANK(AG31),"Pending NEM Welcome Letter",IF(ISBLANK(AL31),"Pending GITA Application",IF(ISBLANK(AM31),"Pending GITA Approval","Completed")))))))))) -> Completed | M31: =VLOOKUP(A:A,'Finance Tracker'!A29:K273,8,FALSE) -> Invoice Completed | O31: N/A | P31: N/A | R31: 45258 | S31: 45328 | T31: NEM Commencement Date | U31: 45910 | V31: Completed | W31: Completed | X31: N/A | Y31: Completed | Z31: Completed | AA31: Completed | AB31: Completed | AC31: Completed | AD31: Completed | AE31: Completed | AF31: 45481 | AG31: 45481 | AH31: 49156 | AJ31: N/A | AK31: N/A | AL31: N/A | AM31: N/A | AP31: =S31-R31 -> 70 | AQ31: =AA31-Table1[[#This Row],[Closed Date]] -> #VALUE!
A32: =Table1[[#This Row],[Project No]] -> 2311039 | B32: =VLOOKUP(A:A,Table1[[Project No]:[Additional Remark]],2,FALSE) -> DC Handal EV Charging Hub | C32: =VLOOKUP(A:A,Table1[[#All],[Project No]:[Additional Remark]],7,FALSE) -> #VALUE! | D32: =VLOOKUP(A:A,Table1[[#All],[Project No]:[Additional Remark]],4,FALSE) -> Simon | E32: =VLOOKUP(A:A,Table1[[#All],[Project No]:[Additional Remark]],5,FALSE) -> C&I-PV | F32: =VLOOKUP(A:A,Table1[[Project No]:[Additional Remark]],6,FALSE) -> SELCO | G32: =VLOOKUP(A:A,Table1[[Project No]:[Additional Remark]],8,FALSE) -> 370.055 | H32: =VLOOKUP(A:A,Table1[[Project No]:[Additional Remark]],15,FALSE) -> - | I32: =VLOOKUP(A:A,Table1[[Project No]:[Additional Remark]],16,FALSE) -> - | J32: =VLOOKUP(A:A,Table1[[Project No]:[Additional Remark]],17,FALSE) -> - | L32: =IF(ISBLANK(R32),"Pending NEM Qouta Submission",IF(ISBLANK(S32),"Pending NEM Qouta Approval",IF(ISBLANK(AA32),"Pending Site Installation",IF(ISBLANK(AJ32),"Pending ST License Application",IF(ISBLANK(AK32),"Pending ST License Approval", IF(ISBLANK(AB32),"Pending Meter Change Application",IF(AND(ISBLANK(AG32),ISBLANK(AF32)),"Pending Meter Change",IF(ISBLANK(AG32),"Pending NEM Welcome Letter",IF(ISBLANK(AL32),"Pending GITA Application",IF(ISBLANK(AM32),"Pending GITA Approval","Completed")))))))))) -> Completed | M32: =VLOOKUP(A:A,'Finance Tracker'!A30:K274,8,FALSE) -> Invoice Completed | O32: N/A | P32: N/A | R32: N/A | S32: N/A | T32: N/A | U32: N/A | V32: Completed | W32: Completed | X32: N/A | Y32: Completed | Z32: Completed | AA32: Completed | AB32: N/A | AC32: N/A | AD32: N/A | AE32: N/A | AF32: N/A | AG32: N/A | AH32: N/A | AJ32: N/A | AK32: N/A | AL32: N/A | AM32: N/A | AP32: =S32-R32 -> #VALUE! | AQ32: =AA32-Table1[[#This Row],[Closed Date]] -> #VALUE!
